[
  {
    "message": "…某月某日、午後７時…"
  },
  {
    "name": "彦麻呂",
    "message": "では来週の月曜日に。"
  },
  {
    "name": "おばあちゃん",
    "message": "ありがとうございましたぁ。"
  },
  {
    "message": "パタンッ。"
  },
  {
    "name": "彦麻呂",
    "message": "ほっ…。"
  },
  {
    "message": "今日も一日が無事に終了。"
  },
  {
    "message": "麻呂は最後の患者を送り出し。"
  },
  {
    "message": "背伸びをしながら安堵の溜息をつく。"
  },
  {
    "message": "あのメールから２週間。"
  },
  {
    "message": "麻呂も電話を差し控え。"
  },
  {
    "message": "何事もない感じで、時が過ぎていった。"
  },
  {
    "message": "一度だけ奥さんの家へ行ったけど。"
  },
  {
    "message": "外から見えた部屋の灯火に安心し。"
  },
  {
    "message": "麻呂はチャイムも押さずに家路へ戻る。"
  },
  {
    "message": "別に後悔はしてない。"
  },
  {
    "message": "あの灯りの向こうで。"
  },
  {
    "message": "マー君と楽しげな会話を交わす奥さん。"
  },
  {
    "message": "その幸せそうな姿を信じ。"
  },
  {
    "message": "敢えて割り込む事を避けただけ。"
  },
  {
    "name": "彦麻呂",
    "message": "今日は…。"
  },
  {
    "message": "冷や奴にするでおじゃるよ。"
  },
  {
    "message": "御飯は午後８時過ぎの炊きあがり。"
  },
  {
    "message": "あと５分でその時刻で。"
  },
  {
    "message": "炊飯器はふっくら仕上げの真っ最中。"
  },
  {
    "name": "彦麻呂",
    "message": "…お米っていい匂いでおじゃるねぇ。"
  },
  {
    "message": "奥さん。"
  },
  {
    "message": "麻呂は約束を守ってるでおじゃるよ。"
  },
  {
    "message": "ちゃんと週の半分は自炊をし。"
  },
  {
    "message": "献立の種類もだいぶ増えたでおじゃる。"
  },
  {
    "message": "イカリングはスーパーの出来合いだけど。"
  },
  {
    "message": "それくらいは許されるでおじゃるね？"
  },
  {
    "name": "彦麻呂",
    "message": "ほほっ…。"
  },
  {
    "message": "一人の夕御飯。"
  },
  {
    "message": "一人のお風呂。"
  },
  {
    "message": "今やそれが当たり前。"
  },
  {
    "message": "元々からそうだったわけだし。"
  },
  {
    "message": "悲観する事は何もないでおじゃる。"
  },
  {
    "message": "暫くしたら婚活を始めて。"
  },
  {
    "message": "今度こそ結婚をするでおじゃるよ。"
  },
  {
    "message": "その時は奥さんを呼んで。"
  },
  {
    "message": "盛大に祝って欲しいでおじゃるねぇ。"
  },
  {
    "name": "彦麻呂",
    "message": "もぐもぐもぐ…？"
  },
  {
    "message": "傍らに置かれた携帯。"
  },
  {
    "message": "着信の合図がピカピカ瞬き。"
  },
  {
    "message": "今になってメールが届いてる事に気づく。"
  },
  {
    "message": "仕事中はずっとバイブモード。"
  },
  {
    "message": "最近は携帯の存在自体が薄くなり。"
  },
  {
    "message": "電池切れ寸前の時も間々あった。"
  },
  {
    "name": "彦麻呂",
    "message": "…誰からでおじゃるかねぇ。"
  },
  {
    "message": "相変わらずのガラケー。"
  },
  {
    "message": "麻呂はパクッと蓋を開け。"
  },
  {
    "message": "モグモグしながら画面を覗き込む。"
  },
  {
    "name": "彦麻呂",
    "message": "…え？"
  },
  {
    "message": "差出人は奥さん。"
  },
  {
    "message": "メールの内容は…。"
  },
  {
    "message": "「たすけｔ」"
  },
  {
    "message": "これだけ。"
  },
  {
    "message": "語尾がアルファベットの「ｔ」。"
  },
  {
    "message": "何やらヤバい雰囲気。"
  },
  {
    "message": "どうする？"
  },
  {
    "message": "ぶー、ぶー、ぶー。"
  },
  {
    "name": "彦麻呂",
    "message": "ぁ…。"
  },
  {
    "message": "メールじゃなく電話？"
  },
  {
    "message": "奥さん？"
  },
  {
    "message": "奥さんでおじゃるか？"
  },
  {
    "message": "ピッ。"
  },
  {
    "message": "麻呂は番号も確認せず。"
  },
  {
    "message": "反射的に通話ボタンを押してた。"
  },
  {
    "name": "彦麻呂",
    "message": "もしもしっ？"
  },
  {
    "name": "女の声",
    "message": "あ、あの…。"
  },
  {
    "name": "彦麻呂",
    "message": "…。"
  },
  {
    "message": "違った。"
  },
  {
    "message": "奥さんの声じゃない。"
  },
  {
    "name": "雪菜",
    "message": "雪菜です…石原、雪菜…。"
  },
  {
    "name": "彦麻呂",
    "message": "ぁ…。"
  },
  {
    "name": "雪菜",
    "message": "こんばんは。"
  },
  {
    "name": "彦麻呂",
    "message": "こ、こんばんはぁ。"
  },
  {
    "name": "雪菜",
    "message": "ご無沙汰してます。"
  },
  {
    "name": "彦麻呂",
    "message": "こちらこそぉ。"
  },
  {
    "name": "雪菜",
    "message": "こんな時間にすみません。"
  },
  {
    "name": "彦麻呂",
    "message": "い、いいえ。"
  },
  {
    "name": "雪菜",
    "message": "お話をしても大丈夫ですか？"
  },
  {
    "name": "彦麻呂",
    "message": "えーと、ですねぇ。"
  },
  {
    "name": "雪菜",
    "message": "っ、用件はすぐ終わりますから。"
  },
  {
    "name": "彦麻呂",
    "message": "…そのご用件とは？"
  },
  {
    "name": "雪菜",
    "message": "大変ぶしつけですが、太雪亭に、来て頂けませんか？"
  },
  {
    "name": "彦麻呂",
    "message": "…。"
  },
  {
    "name": "彦麻呂",
    "message": "…今から？"
  },
  {
    "name": "雪菜",
    "message": "今日じゃないと、ダメなんです。"
  },
  {
    "name": "彦麻呂",
    "message": "…。"
  },
  {
    "name": "雪菜",
    "message": "勝手な事を言ってごめんなさい。私、先生が来るのを待ってます。"
  },
  {
    "name": "彦麻呂",
    "message": "…。"
  },
  {
    "message": "そう言った彼女。"
  },
  {
    "message": "忙しそうだった麻呂を気遣い。"
  },
  {
    "message": "こちらの返事も待たず、すぐに電話を切った。"
  },
  {
    "message": "奥さん。"
  },
  {
    "message": "そして雪菜ちゃん。"
  },
  {
    "message": "もちろん両方を選ぶのは無理。"
  },
  {
    "message": "駒を進める先はどちらか一方で。"
  },
  {
    "message": "それによって麻呂の未来も大きく変わりそう。"
  },
  {
    "message": "太雪亭へ行く"
  },
  {
    "message": "咲美の家にダッシュ"
  },
  {
    "name": "彦麻呂",
    "message": "…。"
  },
  {
    "message": "決めたでおじゃる。"
  },
  {
    "message": "麻呂は太雪亭へ行くでおじゃる。"
  },
  {
    "message": "こちらは幸せルートです。"
  },
  {
    "message": "ハッピーエンドを先に見届けますか？"
  },
  {
    "message": "はい"
  },
  {
    "message": "いいえ"
  },
  {
    "message": "御意。"
  },
  {
    "name": "彦麻呂",
    "message": "ど、どっちへ行くでおじゃるかぁ？"
  },
  {
    "name": "彦麻呂",
    "message": "…。"
  },
  {
    "message": "決めたでおじゃる。"
  },
  {
    "message": "麻呂は奥さんのウチへ行くでおじゃる。"
  },
  {
    "message": "「今日じゃないとダメなんです」"
  },
  {
    "message": "こう言った時の彼女。"
  },
  {
    "message": "麻呂の琴線が震えるほど切なげで。"
  },
  {
    "message": "切羽詰まってる感じがした。"
  },
  {
    "name": "彦麻呂",
    "message": "…。"
  },
  {
    "message": "電話から１０分後。"
  },
  {
    "message": "息を弾ませた麻呂は太雪亭の前に。"
  },
  {
    "message": "辺りに人影はほとんどなく。"
  },
  {
    "message": "家路に急ぐサラリーマンが数人いるだけ。"
  },
  {
    "message": "直接的には関係ない事だけど。"
  },
  {
    "message": "今の太雪亭を象徴してる感じがしてる。"
  },
  {
    "name": "彦麻呂",
    "message": "…中に入るでおじゃるか？"
  },
  {
    "message": "太雪亭に来て欲しい。"
  },
  {
    "message": "そう雪菜ちゃんは言ってた。"
  },
  {
    "message": "店の前での待ち合わせと思ってたけど。"
  },
  {
    "message": "どうやらそれは勝手な思い込みだったらしい。"
  },
  {
    "name": "彦麻呂",
    "message": "…お邪魔しますぅ。"
  },
  {
    "message": "引き戸に掛かった指先。"
  },
  {
    "message": "僅かながら躊躇が生まれ。"
  },
  {
    "message": "そこでいったん動きが止まる。"
  },
  {
    "message": "呼び出した理由は何でおじゃろう？"
  },
  {
    "message": "まさか夫婦で麻呂を説得？"
  },
  {
    "message": "出前持ちとして再びこの店で働かせ。"
  },
  {
    "message": "以前の活気を太雪亭に取り戻したい？"
  },
  {
    "name": "彦麻呂",
    "message": "…もう診療を再開しちゃいましたしねぇ。"
  },
  {
    "message": "今さら的なものも含め。"
  },
  {
    "message": "あらゆる憶測が浮かんでは消えていく。"
  },
  {
    "message": "どちらにしろ引き返すつもりがない以上。"
  },
  {
    "message": "腹をくくって扉を開けるしか道はない。"
  },
  {
    "message": "ガラガラガラ…。"
  },
  {
    "name": "彦麻呂",
    "message": "…。"
  },
  {
    "message": "真っ暗。"
  },
  {
    "message": "何も見えない。"
  },
  {
    "message": "後ろ手に引き戸を閉めたあと。"
  },
  {
    "message": "暫しその場で立ち尽くす。"
  },
  {
    "name": "彦麻呂",
    "message": "え？"
  },
  {
    "message": "その時だ。"
  },
  {
    "message": "誰かが麻呂の手を握った。"
  },
  {
    "message": "柔らかくて小さい女性の手。"
  },
  {
    "message": "加えてすぐ近くに人の気配。"
  },
  {
    "message": "その人物は暗闇に目が慣れてるのか。"
  },
  {
    "message": "麻呂を店の真ん中へ引っ張っていく。"
  },
  {
    "name": "雪菜",
    "message": "っ、嘘をついてごめんなさい。"
  },
  {
    "name": "彦麻呂",
    "message": "…。"
  },
  {
    "message": "雪菜ちゃんの声。"
  },
  {
    "message": "麻呂はちょっとだけホッとする。"
  },
  {
    "message": "でも声の位置が目の前からではなく。"
  },
  {
    "message": "聞こえてきたのはやたら下のほうからだ。"
  },
  {
    "name": "彦麻呂",
    "message": "どうして照明をつけないんですかぁ？"
  },
  {
    "message": "じいぃぃぃ。"
  },
  {
    "message": "返事の代わりにファスナーが下りる音。"
  },
  {
    "message": "彼女は無言で麻呂の股間をまさぐり。"
  },
  {
    "message": "萎えたチンポをデロンッと引き出した。"
  },
  {
    "name": "雪菜",
    "message": "んぐっ…。"
  },
  {
    "name": "彦麻呂",
    "message": "…。"
  },
  {
    "message": "もちろん何をしてるかわかる。"
  },
  {
    "message": "問題なのは理由だ。"
  },
  {
    "message": "いきなりの呼び出し。"
  },
  {
    "message": "真っ暗な店内で会話の欠片もなく。"
  },
  {
    "message": "夫でもない男のチンポを咥えるなんて。"
  },
  {
    "message": "普通ならあり得ない。"
  },
  {
    "message": "相手が雪菜ちゃんなら尚更で。"
  },
  {
    "message": "よほどの事でも、こんなのはない。"
  },
  {
    "name": "雪菜",
    "message": "んぐっ…ごめんなさい…っ…ごめんなさい…。"
  },
  {
    "message": "それでも現実に起こってる。"
  },
  {
    "message": "麻呂はその必死さに気圧され。"
  },
  {
    "message": "しがみつく彼女を押し退けられない。"
  },
  {
    "name": "彦麻呂",
    "message": "ど、どうして暗いんですかねぇ。"
  },
  {
    "message": "口から出るのは同じ質問ばかり。"
  },
  {
    "message": "相変わらず雪菜ちゃんからの返事はなく。"
  },
  {
    "message": "ピチャピチャと濡れた音だけが聞こえてくる。"
  },
  {
    "name": "雪菜",
    "message": "んぐっ…んぐっ…ぴちゃ…んぐっ…。"
  },
  {
    "name": "雪菜",
    "message": "くはっ…んぐっ…んっ…んっ…はあっ…んっ…。"
  },
  {
    "name": "雪菜",
    "message": "んぐっ…んぐっ…ぴちゃっ…んぐっ…んっ…んっ…はあっ…。"
  },
  {
    "name": "雪菜",
    "message": "ちゅぱっ…んぐっ…んぐっ…ぴちゃっ…ちゅうっ…んぐっ…んぐっ…んぐっ…ぅ…。"
  },
  {
    "name": "雪菜",
    "message": "はあっ…はあっ…んぐっ…んぐっ…んっ…ちろっ…んぐっ…ちゅぱっ…んぐっ…んぐっ…んぐっ…ぅ…。"
  },
  {
    "name": "雪菜",
    "message": "んぐっ…はあっ…んぐっ…はあっ…んぐっ…んぐっ…んっ…ちゅうっ…んぐっ…ちゅうっ…ぺろっ…んぐっ…ぺろっ…ぺろっ…。"
  },
  {
    "name": "彦麻呂",
    "message": "くはぁ…っ。"
  },
  {
    "message": "ほとんど丸飲み。"
  },
  {
    "message": "いくら半勃ちとはいえ。"
  },
  {
    "message": "こんなにも口へ含めるのかと思うほど。"
  },
  {
    "message": "熱い吐息が麻呂の陰毛を湿らせ。"
  },
  {
    "message": "白魚のような指が陰茎の根元を擦ってた。"
  },
  {
    "message": "下にいるのは本当に雪菜ちゃん？"
  },
  {
    "message": "闇の中にぼんやり浮かぶその姿。"
  },
  {
    "message": "だんだんと目が慣れ。"
  },
  {
    "message": "彼女が一糸も纏ってない事に今さら気づく。"
  },
  {
    "name": "彦麻呂",
    "message": "は、裸ですかぁ？"
  },
  {
    "name": "雪菜",
    "message": "んぐっ…んぐっ…んっ…んぐっ…。"
  },
  {
    "name": "彦麻呂",
    "message": "どうして服を着てないんですかぁ？"
  },
  {
    "name": "雪菜",
    "message": "ぴちゃっ…んぐっ…んっ…んぐっ…ちゅうっ…んぐっ…。"
  },
  {
    "name": "彦麻呂",
    "message": "っ…。"
  },
  {
    "message": "麻呂は目を閉じ。"
  },
  {
    "message": "気持ちを落ち着かせようとしてる。"
  },
  {
    "message": "これは夢でおじゃるか？"
  },
  {
    "message": "チンポを咥えてるのは、どこかのアバズレ女？"
  },
  {
    "message": "あの清楚で。"
  },
  {
    "message": "いつだって奥ゆかしく。"
  },
  {
    "message": "困ったような笑顔が可愛くて。"
  },
  {
    "message": "麻呂の役に立とうと一生懸命だった彼女。"
  },
  {
    "message": "つまりそれはこっちの勝手なイメージで。"
  },
  {
    "name": "雪菜",
    "message": "「…ふん」"
  },
  {
    "message": "本当は酸いも甘いも極めた大人の女性。"
  },
  {
    "message": "周囲には妹キャラを騙りながら。"
  },
  {
    "message": "夜になればフェラばかりしてる若妻？"
  },
  {
    "name": "雪菜",
    "message": "「男って馬鹿よねぇ」"
  },
  {
    "message": "こんな事を言いながら。"
  },
  {
    "message": "あの仏頂面な兄貴のチンポを…。"
  },
  {
    "name": "彦麻呂",
    "message": "っ…。"
  },
  {
    "message": "いや。"
  },
  {
    "message": "兄貴じゃない。"
  },
  {
    "message": "旦那でおじゃるぅ。"
  },
  {
    "message": "昼間はお兄ちゃん。"
  },
  {
    "message": "夜は旦那様。"
  },
  {
    "message": "もしかしたら昼と夜は何もかもが逆で。"
  },
  {
    "message": "セックスの時は彼女が威張ってるのかも。"
  },
  {
    "name": "雪菜",
    "message": "「早くチンポをおっ勃てなさいよ」"
  },
  {
    "name": "兄貴で旦那",
    "message": "「は、はいぃ」"
  },
  {
    "name": "雪菜",
    "message": "「もう出ちゃったの？　だらしないわねぇ」"
  },
  {
    "name": "兄貴で旦那",
    "message": "「す、すみません」"
  },
  {
    "name": "雪菜",
    "message": "「今夜は寝かさないから、覚悟しておきなさいよ」"
  },
  {
    "name": "兄貴で旦那",
    "message": "「っ、もう勘弁して下さぁい」"
  },
  {
    "name": "雪菜",
    "message": "「私って、性欲が強い女なの」"
  },
  {
    "name": "兄貴で旦那",
    "message": "「ぞ、存じ上げてます」"
  },
  {
    "name": "雪菜",
    "message": "「いいから入れなさいよ、この濡れた谷間の中に」"
  },
  {
    "name": "兄貴で旦那",
    "message": "「は、はい」"
  },
  {
    "name": "雪菜",
    "message": "「そのチンポで私の中を掻き回して」"
  },
  {
    "name": "彦麻呂",
    "message": "ぅ…っ…。"
  },
  {
    "message": "エロい。"
  },
  {
    "message": "エロすぎるぅ。"
  },
  {
    "message": "見た目が清楚で実はスケベ。"
  },
  {
    "message": "逆にそのギャップが魅力的で。"
  },
  {
    "message": "そんな雪菜ちゃんでも嫌いになれない。"
  },
  {
    "name": "雪菜",
    "message": "ふむぅ…ぐ…っ。"
  },
  {
    "name": "彦麻呂",
    "message": "ぁ…。"
  },
  {
    "message": "今までと違う呻き。"
  },
  {
    "message": "その声で麻呂はハッと我に返り。"
  },
  {
    "message": "現実の彼女へ視線を戻した。"
  },
  {
    "name": "雪菜",
    "message": "っ…。"
  },
  {
    "message": "エロい妄想で完全勃起。"
  },
  {
    "message": "たぶんさっきの呻きは、急な膨張にビックリし。"
  },
  {
    "message": "思わずチンポを吐き出してしまった時の声。"
  },
  {
    "message": "彼女は亀頭の部分だけを咥え。"
  },
  {
    "message": "その圧倒的なサイズに戸惑ってた。"
  },
  {
    "message": "だけどそこからが普通じゃない。"
  },
  {
    "message": "彼女は背中へ回した腕をギュッと引き寄せ。"
  },
  {
    "message": "半ば強引に口の中へ埋没させようとする。"
  },
  {
    "name": "雪菜",
    "message": "むぐううぅぅ…っ。"
  },
  {
    "message": "口の端を切れそうなくらい広げ。"
  },
  {
    "message": "ヘビのように生き物を飲み込む勢い。"
  },
  {
    "name": "雪菜",
    "message": "んぐ…ぅ…。"
  },
  {
    "message": "亀頭の先端が喉奥に当たり。"
  },
  {
    "message": "それでも彼女は手綱を緩めない。"
  },
  {
    "name": "雪菜",
    "message": "んげっ…んぐっ…んぐっ…。"
  },
  {
    "message": "フェラというよりは他の行為。"
  },
  {
    "message": "根元に近いくらい奥まで埋め。"
  },
  {
    "message": "唇で擦りながらズルンッと吐き出した。"
  },
  {
    "message": "そしてそれの繰り返し。"
  },
  {
    "message": "彼女の目端には涙が滲み。"
  },
  {
    "message": "今にもポロポロと零れ落ちそう。"
  },
  {
    "message": "なんでそこまでするのか。"
  },
  {
    "message": "まるで自ら拷問を受けてるみたいで。"
  },
  {
    "message": "麻呂はますます理解不能になってくる。"
  },
  {
    "name": "彦麻呂",
    "message": "っ、少し話をしませんかぁ？"
  },
  {
    "name": "雪菜",
    "message": "んっ…んっ…。"
  },
  {
    "message": "彼女はイヤイヤ。"
  },
  {
    "message": "まるでこの行為が命綱であるように。"
  },
  {
    "message": "麻呂の勃起チンポを口から放そうとしない。"
  },
  {
    "name": "雪菜",
    "message": "んぐぅ…んんっ…んげっ…じゅぼ…っ。"
  },
  {
    "name": "雪菜",
    "message": "じゅるっ…んんっ…じゅぼっ…じゅぼっ…んぐっ…ぅっ。"
  },
  {
    "name": "雪菜",
    "message": "ぬぽぉっ…じゅるっ…んぐっ…じゅぼっ…じゅぼっ…んぐっ…んぐっ…ぅ。"
  },
  {
    "name": "雪菜",
    "message": "じゅぼっ…じゅぼっ…んぐぅっ…じゅるっ…じゅぼっ…じゅぼっ…んぐぅっ…はあっ…くちゅうっ…んぐっ…ぅ。"
  },
  {
    "name": "雪菜",
    "message": "じゅるっ…じゅぼっ…じゅぼっ…じゅるっ…じゅぼっ…じゅぼっ…んぐぅっ…はあっ…じゅぼっ…んぐっ…じゅぼっ…じゅぼっ…。"
  },
  {
    "message": "みっちりした口の端。"
  },
  {
    "message": "そこからヨダレがダラダラ垂れ。"
  },
  {
    "message": "雪菜ちゃんとは思えない惨さが漂う。"
  },
  {
    "message": "それが妙にエロい。"
  },
  {
    "message": "けど可哀想。"
  },
  {
    "message": "麻呂は彼女の頭に手を添え。"
  },
  {
    "message": "思いっきりじゃないにしろ、その動きを止めようとした。"
  },
  {
    "name": "雪菜",
    "message": "んっ…。"
  },
  {
    "message": "でも彼女は逆らう。"
  },
  {
    "message": "リズミカルな動きができなくても。"
  },
  {
    "message": "奥深く埋める行為を中断しようとしない。"
  },
  {
    "name": "彦麻呂",
    "message": "強情ですねぇ。"
  },
  {
    "name": "雪菜",
    "message": "んぐぅっ…じゅぼっ…じゅぼっ…じゅぼっ…。"
  },
  {
    "name": "彦麻呂",
    "message": "何の為にこんな事をしてるのか。"
  },
  {
    "name": "雪菜",
    "message": "じゅぼっ…じゅぼっ…じゅぼっ…じゅぼっ…じゅぼっ…。"
  },
  {
    "name": "彦麻呂",
    "message": "それだけでもハッキリさせましょうよ。"
  },
  {
    "message": "ぐいっ。"
  },
  {
    "message": "ぬちゅるんっ。"
  },
  {
    "name": "雪菜",
    "message": "ぁ…ぃ、いゃ…。"
  },
  {
    "name": "彦麻呂",
    "message": "何の為か教えて下さいなぁ。"
  },
  {
    "message": "暗闇の中。"
  },
  {
    "message": "麻呂を見上げる彼女の白い顔が、ぼんやり浮かぶ。"
  },
  {
    "name": "雪菜",
    "message": "っ、これしかないからです。"
  },
  {
    "name": "彦麻呂",
    "message": "これと言うのは？"
  },
  {
    "name": "雪菜",
    "message": "できる事が、これしかないんです。"
  },
  {
    "name": "彦麻呂",
    "message": "ですから何の為に？"
  },
  {
    "name": "雪菜",
    "message": "っ、自分の為。"
  },
  {
    "message": "じゅぼぉ…。"
  },
  {
    "name": "雪菜",
    "message": "り、りぶんのためぇ…。"
  },
  {
    "message": "再びチンポを飲み込み。"
  },
  {
    "message": "彼女は麻呂との会話を拒絶した。"
  },
  {
    "name": "彦麻呂",
    "message": "…雪菜さんの為？"
  },
  {
    "message": "言葉での返事は無し。"
  },
  {
    "message": "喉奥にチンポを埋めたまま。"
  },
  {
    "message": "無言でコクリと頷くだけ。"
  },
  {
    "name": "彦麻呂",
    "message": "その返事に嘘はないですねぇ？"
  },
  {
    "name": "雪菜",
    "message": "コ、コクリ。"
  },
  {
    "name": "彦麻呂",
    "message": "なら協力致します。"
  },
  {
    "message": "ぐいっ。"
  },
  {
    "name": "雪菜",
    "message": "！？"
  },
  {
    "name": "彦麻呂",
    "message": "雪菜さんの為と、おっしゃるなら…。"
  },
  {
    "name": "雪菜",
    "message": "じゅぼっ…んっ…んんっ…ん～っ！！"
  },
  {
    "name": "彦麻呂",
    "message": "私も喜んで協力しますよ。"
  },
  {
    "name": "雪菜",
    "message": "んぐぅっ…くはぁっ…じゅぼっ…んっ…んっ…んっ！！"
  },
  {
    "message": "その言葉とは裏腹。"
  },
  {
    "message": "彼女のタイミングを無視し。"
  },
  {
    "message": "麻呂は勝手に喉奥へチンポを突っ込む。"
  },
  {
    "message": "その度に雪菜ちゃんはムセ返り。"
  },
  {
    "message": "リバースさせそうな音をゴロゴロ鳴らしてた。"
  },
  {
    "name": "彦麻呂",
    "message": "…話がしたくなったら、いつでも言って下さい。"
  },
  {
    "message": "くちゅっ、ぐちゅっ、じゅぼっ、ぐちゅっ、ぐちゅっ…。"
  },
  {
    "name": "雪菜",
    "message": "んげっ…んぐっ…じゅぼっ…んぐっ…んっ…。"
  },
  {
    "name": "雪菜",
    "message": "んっ…んんっ…んっ…じゅぼっ…んっ…じゅぼっ…んっ…。"
  },
  {
    "name": "雪菜",
    "message": "んぐぅっ…んんっ…じゅぼっ…くはぁっ…じゅぼっ…んっ…んぐっ…んぐっ…んぐぅ…っ。"
  },
  {
    "name": "雪菜",
    "message": "んんっ…じゅぼっ…ちゅうっ…んぐぅっ…んぐぅっ…んんっ…ぐちゅっ…んんんっ…じゅぼっ…うぅ…っ。"
  },
  {
    "name": "雪菜",
    "message": "んぐっ…じゅぼっ…んぐっ…んっ…んぐぅ…んっ…ぐはぁ…っ…んげ…んっ…んんっ…んっ…ぐぽっ…じゅぼっ…ん、んっんっ！！"
  },
  {
    "message": "ぬちゅるんっ。"
  },
  {
    "message": "唾液が気管に入り。"
  },
  {
    "message": "彼女は反射的にチンポを吐き出す。"
  },
  {
    "message": "握ってた手も麻呂から離れ。"
  },
  {
    "message": "ムセながら苦しげに口を押さえてた。"
  },
  {
    "name": "雪菜",
    "message": "うげぇ…っ…げほっ…げほっ…げほっ…。"
  },
  {
    "name": "彦麻呂",
    "message": "おやぁ。"
  },
  {
    "name": "雪菜",
    "message": "げほっ…ごほっ…うっ…げほっ…げほっ…。"
  },
  {
    "name": "彦麻呂",
    "message": "具合が悪そうですねぇ。"
  },
  {
    "name": "雪菜",
    "message": "っ…ごほっ…んっ…ごほっ…。"
  },
  {
    "name": "彦麻呂",
    "message": "私は医者ですから。"
  },
  {
    "message": "踞る彼女の側を離れ。"
  },
  {
    "message": "麻呂は手探りで壁伝いに歩く。"
  },
  {
    "name": "彦麻呂",
    "message": "…いくらでも診て差し上げますよ。"
  },
  {
    "message": "ここは勝手知ったる他人の店。"
  },
  {
    "message": "すぐに目的の場所へ辿り着き。"
  },
  {
    "message": "指先でパチンとスイッチを入れてやる。"
  },
  {
    "message": "パチッ。"
  },
  {
    "name": "雪菜",
    "message": "きゃっ！！"
  },
  {
    "message": "可愛らしい悲鳴。"
  },
  {
    "message": "灯った蛍光灯の下で彼女は慌てふためき。"
  },
  {
    "message": "身の隠せる場所を必死に探してる。"
  },
  {
    "name": "彦麻呂",
    "message": "どこへ行くつもりですかぁ？"
  },
  {
    "name": "雪菜",
    "message": "あ、明かりを消して下さい。"
  },
  {
    "name": "彦麻呂",
    "message": "私は診て差し上げると言ったんです。"
  },
  {
    "name": "雪菜",
    "message": "ぅ…。"
  },
  {
    "name": "彦麻呂",
    "message": "どうぞこちらへ。"
  },
  {
    "message": "最初に雪菜を指さし。"
  },
  {
    "message": "続けて麻呂の真ん前を指さす。"
  },
  {
    "name": "彦麻呂",
    "message": "私の正面に立って下さいな。"
  },
  {
    "name": "雪菜",
    "message": "で、でも…。"
  },
  {
    "message": "カンペキに怯えた顔。"
  },
  {
    "message": "彼女はテーブルの脇に隠れ。"
  },
  {
    "message": "膝を抱えるようにしゃがんだ格好。"
  },
  {
    "message": "オッパイは膝に押し潰され。"
  },
  {
    "message": "太腿の奥には肉の亀裂が覗いてる。"
  },
  {
    "name": "彦麻呂",
    "message": "言う事を聞かないつもりですか？"
  },
  {
    "name": "雪菜",
    "message": "っ…。"
  },
  {
    "name": "彦麻呂",
    "message": "早くしないと帰りますよ。"
  },
  {
    "name": "雪菜",
    "message": "だ、だめ…。"
  },
  {
    "name": "雪菜",
    "message": "い、言う事を聞きました。"
  },
  {
    "name": "彦麻呂",
    "message": "ありがとうございますぅ。"
  },
  {
    "name": "雪菜",
    "message": "だから…帰らないで下さい。"
  },
  {
    "name": "彦麻呂",
    "message": "患者を見捨てるような事はしません。"
  },
  {
    "message": "完全に麻呂は医者モード。"
  },
  {
    "message": "顔色一つ変えないよう気を配り。"
  },
  {
    "message": "彼女の身体を舐めるように眺める。"
  },
  {
    "name": "彦麻呂",
    "message": "お名前は？"
  },
  {
    "name": "雪菜",
    "message": "い、石原…雪菜。"
  },
  {
    "name": "彦麻呂",
    "message": "お歳は？"
  },
  {
    "name": "雪菜",
    "message": "…２２歳です。"
  },
  {
    "name": "彦麻呂",
    "message": "ご結婚は？"
  },
  {
    "name": "雪菜",
    "message": "し、してます。"
  },
  {
    "name": "彦麻呂",
    "message": "お子さんは？"
  },
  {
    "name": "雪菜",
    "message": "いません。"
  },
  {
    "name": "彦麻呂",
    "message": "今日は指輪をしてるんですね。"
  },
  {
    "name": "雪菜",
    "message": "ぁ…。"
  },
  {
    "message": "シンプルな銀色のリング。"
  },
  {
    "message": "一瞬だけ彼女は隠すようなそぶりを見せ。"
  },
  {
    "message": "すぐそれが意味のない事だと気づく。"
  },
  {
    "name": "彦麻呂",
    "message": "どうして今日に限って指輪を？"
  },
  {
    "name": "雪菜",
    "message": "っ、これからは…正直でありたいから。"
  },
  {
    "name": "彦麻呂",
    "message": "それは全てに於いてですか？"
  },
  {
    "name": "雪菜",
    "message": "もう誰にも、嘘はつきたくないです。"
  },
  {
    "name": "彦麻呂",
    "message": "ならどんな質問にも、答えられますよね？"
  },
  {
    "name": "雪菜",
    "message": "答えます。"
  },
  {
    "name": "彦麻呂",
    "message": "では旦那さんの名前をどうぞ。"
  },
  {
    "name": "雪菜",
    "message": "石原…太郎…です。"
  },
  {
    "name": "彦麻呂",
    "message": "…。"
  },
  {
    "name": "彦麻呂",
    "message": "…それで太雪亭なわけですねぇ。"
  },
  {
    "name": "雪菜",
    "message": "夫婦の名前を、一文字ずつ取りました。"
  },
  {
    "name": "彦麻呂",
    "message": "その旦那さんはどちらに？"
  },
  {
    "name": "雪菜",
    "message": "叔父の屋敷へ行ってます。"
  },
  {
    "name": "彦麻呂",
    "message": "お金を借りてる方のおウチですか？"
  },
  {
    "name": "雪菜",
    "message": "はい。"
  },
  {
    "name": "彦麻呂",
    "message": "つまり今は留守をしてると。"
  },
  {
    "name": "雪菜",
    "message": "…帰りは、明日の朝になるそうです。"
  },
  {
    "name": "彦麻呂",
    "message": "その時を狙って私を呼び出した？"
  },
  {
    "name": "雪菜",
    "message": "…そういう事になります。"
  },
  {
    "name": "彦麻呂",
    "message": "フェラチオをする為に？"
  },
  {
    "name": "雪菜",
    "message": "…。"
  },
  {
    "name": "彦麻呂",
    "message": "それも全裸で。"
  },
  {
    "name": "雪菜",
    "message": "ぅ…。"
  },
  {
    "name": "彦麻呂",
    "message": "返事をして下さいな。"
  },
  {
    "name": "雪菜",
    "message": "お、おっしゃる通りです。"
  },
  {
    "name": "彦麻呂",
    "message": "何の為に？"
  },
  {
    "name": "雪菜",
    "message": "ですから…自分の、為に。"
  },
  {
    "name": "彦麻呂",
    "message": "こんな事をして何のメリットが？"
  },
  {
    "name": "雪菜",
    "message": "っ、私自身の気が済むんです。"
  },
  {
    "name": "彦麻呂",
    "message": "は？"
  },
  {
    "name": "雪菜",
    "message": "結果的に、先生を…騙したわけですから。"
  },
  {
    "name": "彦麻呂",
    "message": "ご結婚されてた事をですか？"
  },
  {
    "name": "雪菜",
    "message": "はい。"
  },
  {
    "name": "彦麻呂",
    "message": "それで旦那がいない隙に、禊ぎを済ませてしまおう、と？"
  },
  {
    "name": "雪菜",
    "message": "そう思って貰って、かまいません。"
  },
  {
    "name": "彦麻呂",
    "message": "病んでますねぇ。"
  },
  {
    "message": "ずいっ。"
  },
  {
    "name": "雪菜",
    "message": "ぁ…。"
  },
  {
    "message": "麻呂が一歩前へ出ると。"
  },
  {
    "message": "彼女が一歩後ずさりする。"
  },
  {
    "name": "彦麻呂",
    "message": "どうして逃げるんでしょう？"
  },
  {
    "name": "雪菜",
    "message": "っ、逃げてないです。"
  },
  {
    "name": "彦麻呂",
    "message": "でも一歩下がりました。"
  },
  {
    "name": "雪菜",
    "message": "ぅ…。"
  },
  {
    "name": "彦麻呂",
    "message": "本当は恐い？"
  },
  {
    "name": "雪菜",
    "message": "こ、恐くありません。"
  },
  {
    "name": "彦麻呂",
    "message": "ではじっとしてて下さいね。"
  },
  {
    "message": "麻呂は腕を伸ばし。"
  },
  {
    "message": "豊満な乳房に触れようとする。"
  },
  {
    "message": "指先との距離が縮まる毎に彼女は肩を窄め。"
  },
  {
    "message": "身体がどんどん後ろへ反っていった。"
  },
  {
    "message": "だけどそれも限界。"
  },
  {
    "message": "後ずさり無しではもう無理。"
  },
  {
    "message": "諦めたように彼女は身体を戻し。"
  },
  {
    "message": "自ら乳房を麻呂の指に近づける。"
  },
  {
    "message": "ぷにっ。"
  },
  {
    "name": "雪菜",
    "message": "ぁ…。"
  },
  {
    "message": "指先が膨らみに触れ。"
  },
  {
    "message": "弾力を確かめるようプニッと摘まれた。"
  },
  {
    "message": "その感触は想像以上で。"
  },
  {
    "message": "瑞々しい張りが殊のほか心地良い。"
  },
  {
    "name": "彦麻呂",
    "message": "触っちゃいましたねぇ。"
  },
  {
    "name": "雪菜",
    "message": "か、かまいません。"
  },
  {
    "name": "彦麻呂",
    "message": "そう言いながら身体が縮まってますぅ。"
  },
  {
    "name": "雪菜",
    "message": "っ、もっと触られても大丈夫です。"
  },
  {
    "name": "彦麻呂",
    "message": "旦那さんの手じゃないのに？"
  },
  {
    "name": "雪菜",
    "message": "は、はい。"
  },
  {
    "name": "彦麻呂",
    "message": "いけない奥さんですねぇ。"
  },
  {
    "name": "雪菜",
    "message": "っ、自分でもそう思います。"
  },
  {
    "name": "彦麻呂",
    "message": "…。"
  },
  {
    "message": "掌で膨らみを包み込み。"
  },
  {
    "message": "下から持ち上げるよう揉みしだく。"
  },
  {
    "message": "たっぷりした重さは圧倒的で。"
  },
  {
    "message": "Ｇカップでは収まらない肉厚を感じた。"
  },
  {
    "message": "やがて矛先は乳房の先端へ。"
  },
  {
    "message": "すでに蕾は硬くシコっており。"
  },
  {
    "message": "大袈裟じゃなくツンと上に尖ってる。"
  },
  {
    "name": "雪菜",
    "message": "っ、摘んで下さい。"
  },
  {
    "name": "彦麻呂",
    "message": "ほっ…。"
  },
  {
    "message": "リクエストに応え。"
  },
  {
    "message": "麻呂は蕾を指の腹に挟んだ。"
  },
  {
    "message": "そのままクリクリと弄び。"
  },
  {
    "message": "彼女の反応を確かめながら強さを加減する。"
  },
  {
    "name": "雪菜",
    "message": "も、もっと強くていいです。"
  },
  {
    "message": "ぎゅっ。"
  },
  {
    "name": "雪菜",
    "message": "っ…もっと。"
  },
  {
    "message": "ぎゅっ。"
  },
  {
    "name": "雪菜",
    "message": "も、もっと。"
  },
  {
    "name": "彦麻呂",
    "message": "潰れちゃいますよ。"
  },
  {
    "name": "雪菜",
    "message": "い、いいんです。"
  },
  {
    "name": "彦麻呂",
    "message": "…。"
  },
  {
    "message": "ぎゅうっ。"
  },
  {
    "name": "雪菜",
    "message": "！？"
  },
  {
    "message": "身体がビクっと震え。"
  },
  {
    "message": "膝が緩んで落ちそうになった。"
  },
  {
    "name": "彦麻呂",
    "message": "痛かったですねぇ。"
  },
  {
    "name": "雪菜",
    "message": "っ、平気…です…。"
  },
  {
    "name": "彦麻呂",
    "message": "痛いのがお好きとか？"
  },
  {
    "name": "雪菜",
    "message": "い、今は。"
  },
  {
    "name": "彦麻呂",
    "message": "これは本格的な治療が必要ですねぇ。"
  },
  {
    "message": "麻呂は両手で乳首を摘み。"
  },
  {
    "message": "クリクリ動かしながら、顔をじっと見つめる。"
  },
  {
    "name": "彦麻呂",
    "message": "覚悟はいいですかぁ？"
  },
  {
    "name": "雪菜",
    "message": "は、はい。"
  },
  {
    "name": "彦麻呂",
    "message": "まずは立ち入った問診から始めましょう。"
  },
  {
    "message": "処女を失った年齢は？"
  },
  {
    "message": "男性経験は何人ですか？"
  },
  {
    "message": "旦那さんとの性生活はどうでしょう？"
  },
  {
    "message": "フェラチオは得意ですか？"
  },
  {
    "message": "一番の性感帯はどこでしょう？"
  },
  {
    "message": "どんな体位がお好きですか？"
  },
  {
    "message": "イッた事はありますか？"
  },
  {
    "name": "彦麻呂",
    "message": "処女を失った年齢は？"
  },
  {
    "name": "雪菜",
    "message": "１８歳の時です。"
  },
  {
    "name": "彦麻呂",
    "message": "相手はどんな方ですか？"
  },
  {
    "name": "雪菜",
    "message": "…今の主人と…結ばれました。"
  },
  {
    "name": "彦麻呂",
    "message": "相手は旦那さんですよねぇ。"
  },
  {
    "name": "雪菜",
    "message": "はい。"
  },
  {
    "name": "彦麻呂",
    "message": "けっこう歳が離れてるのでは？"
  },
  {
    "name": "雪菜",
    "message": "主人は７つ年上です。"
  },
  {
    "name": "彦麻呂",
    "message": "どちらで知り合ったのでしょう？"
  },
  {
    "name": "雪菜",
    "message": "…幼馴染み、なんです。"
  },
  {
    "name": "彦麻呂",
    "message": "ほっ…。"
  },
  {
    "name": "雪菜",
    "message": "近所のお兄ちゃんで、よく遊んで貰いました。"
  },
  {
    "name": "彦麻呂",
    "message": "もしかして妹のように可愛がられてた？"
  },
  {
    "name": "雪菜",
    "message": "…かも知れません。"
  },
  {
    "name": "彦麻呂",
    "message": "結婚後に兄妹を装っていたのも、全く嘘ではなかったわけですね。"
  },
  {
    "name": "雪菜",
    "message": "…。"
  },
  {
    "name": "彦麻呂",
    "message": "では次が最後の質問になります。"
  },
  {
    "name": "彦麻呂",
    "message": "では次の質問を…。"
  },
  {
    "name": "彦麻呂",
    "message": "男性経験は何人ですかぁ？"
  },
  {
    "name": "雪菜",
    "message": "一人です。"
  },
  {
    "name": "彦麻呂",
    "message": "ようするにそれは…。"
  },
  {
    "name": "雪菜",
    "message": "主人、という事になります。"
  },
  {
    "name": "彦麻呂",
    "message": "旦那さん以外の男性と、性交渉が一度もない？"
  },
  {
    "name": "雪菜",
    "message": "一度もありません。"
  },
  {
    "name": "彦麻呂",
    "message": "わかりましたぁ。"
  },
  {
    "name": "雪菜",
    "message": "…少ないですよね。"
  },
  {
    "name": "彦麻呂",
    "message": "セックスは人数じゃありませんので。"
  },
  {
    "name": "雪菜",
    "message": "…。"
  },
  {
    "name": "彦麻呂",
    "message": "では次が最後の質問になります。"
  },
  {
    "name": "彦麻呂",
    "message": "では次の質問を…。"
  },
  {
    "name": "彦麻呂",
    "message": "旦那さんとの性生活はどうでしょう？"
  },
  {
    "name": "雪菜",
    "message": "行為自体は、定期的にあります。"
  },
  {
    "name": "彦麻呂",
    "message": "週に何回ぐらいですか？"
  },
  {
    "name": "雪菜",
    "message": "最近は…１回ぐらいです。"
  },
  {
    "name": "彦麻呂",
    "message": "という事は…。"
  },
  {
    "name": "雪菜",
    "message": "先生と知り合ったあとも、何回かセックスしてます。"
  },
  {
    "name": "彦麻呂",
    "message": "ほっ…。"
  },
  {
    "name": "雪菜",
    "message": "こんな大人しそうな顔して、やる事はやってるんです。"
  },
  {
    "name": "彦麻呂",
    "message": "結婚してるわけですから。"
  },
  {
    "name": "雪菜",
    "message": "っ、そんなの言い訳になりません。"
  },
  {
    "name": "彦麻呂",
    "message": "フェラチオは得意ですか？"
  },
  {
    "name": "雪菜",
    "message": "最初は苦手でしたけど、今は…。"
  },
  {
    "name": "彦麻呂",
    "message": "…今は？"
  },
  {
    "name": "雪菜",
    "message": "１８歳から、主人に教えられました。"
  },
  {
    "name": "彦麻呂",
    "message": "旦那さんはフェラがお好き、と？"
  },
  {
    "name": "雪菜",
    "message": "喉の奥までペニスを入れる事ができた時、主人が凄く褒めてくれたのを覚えてます。"
  },
  {
    "name": "彦麻呂",
    "message": "奥さんも嬉しかったですかぁ？"
  },
  {
    "name": "雪菜",
    "message": "大人になれた気がしました。"
  },
  {
    "name": "彦麻呂",
    "message": "今まで何百回も咥えたんですねぇ。"
  },
  {
    "name": "雪菜",
    "message": "それこそ、数え切れないくらい。"
  },
  {
    "name": "彦麻呂",
    "message": "ほっ…。"
  },
  {
    "name": "雪菜",
    "message": "咥えてる時の顔を…見て貰えましたか？"
  },
  {
    "name": "彦麻呂",
    "message": "もちろん。"
  },
  {
    "name": "雪菜",
    "message": "私、あんな顔になっちゃうんです。頬がヘコんで、涎を垂らして、意地汚い女に。"
  },
  {
    "name": "彦麻呂",
    "message": "イヤらしい感じがして良いのでは？"
  },
  {
    "name": "雪菜",
    "message": "でも、看板娘が聞いて呆れます。"
  },
  {
    "name": "彦麻呂",
    "message": "一番の性感帯はどこでしょう？"
  },
  {
    "name": "雪菜",
    "message": "一番は…膣の奥です。"
  },
  {
    "name": "彦麻呂",
    "message": "クリトリスではなく？"
  },
  {
    "name": "雪菜",
    "message": "何度も繰り返しされて、主人に開発されました。"
  },
  {
    "name": "彦麻呂",
    "message": "繰り返しと申しますと？"
  },
  {
    "name": "雪菜",
    "message": "向かい合わせに座る体位の事です。ペニスを摩擦するのではなく、その格好で奥をグリグリされて、主人が果てるまでずっと続きます。"
  },
  {
    "name": "彦麻呂",
    "message": "それをお付き合いされた頃から…。"
  },
  {
    "name": "雪菜",
    "message": "処女を失ったのもその体位でした。あの人は、私の顔を間近に見て、セックスするのが大好きですから。"
  },
  {
    "name": "彦麻呂",
    "message": "ほっ…。"
  },
  {
    "name": "雪菜",
    "message": "昼間は男なんか知らない顔で、お客さんに笑顔をふりまいて…夜はそんな事をしてたんです。"
  },
  {
    "name": "彦麻呂",
    "message": "恋人同士なら宜しいじゃないですかぁ。"
  },
  {
    "name": "雪菜",
    "message": "１８歳なのに膣奥でイク女ですよ？"
  },
  {
    "name": "彦麻呂",
    "message": "どんな体位がお好きですか？"
  },
  {
    "name": "雪菜",
    "message": "…主人の好みでしょうか？"
  },
  {
    "name": "彦麻呂",
    "message": "雪菜さん個人の好みで結構ですぅ。"
  },
  {
    "name": "彦麻呂",
    "message": "旦那さんの好みは先ほど伺いましたので、今度は雪菜さんの好みをお願いしますぅ。"
  },
  {
    "name": "雪菜",
    "message": "私自身は、騎乗位が好きです。"
  },
  {
    "name": "彦麻呂",
    "message": "宜しければ理由をどうぞぉ。"
  },
  {
    "name": "雪菜",
    "message": "恥ずかしいからに決まってます。"
  },
  {
    "name": "彦麻呂",
    "message": "…何が恥ずかしいのでしょう？"
  },
  {
    "name": "雪菜",
    "message": "私は、乳房の揺れを見られるのが嫌いで、最も弾んでしまうのが、騎乗位なんです。"
  },
  {
    "name": "彦麻呂",
    "message": "おっしゃってる事が相反してるような？"
  },
  {
    "name": "雪菜",
    "message": "変なのは自分でも理解してます。ですから誰にも言えませんし、主人にも話した事はないです。"
  },
  {
    "name": "彦麻呂",
    "message": "…もう一つ質問して宜しいですかぁ？"
  },
  {
    "name": "雪菜",
    "message": "何でも訊いて下さい。"
  },
  {
    "name": "彦麻呂",
    "message": "以前にミニスカートを穿いて、ティッシュを配りましたよね？"
  },
  {
    "name": "雪菜",
    "message": "中乃町の駅前で配りました。"
  },
  {
    "name": "彦麻呂",
    "message": "あの時はどんな気持ちでしたか？"
  },
  {
    "name": "雪菜",
    "message": "もちろんイヤです。"
  },
  {
    "name": "彦麻呂",
    "message": "何故イヤなのでしょう？"
  },
  {
    "name": "雪菜",
    "message": "みんなジロジロ見ますし。"
  },
  {
    "name": "彦麻呂",
    "message": "店内で同じ格好だった時は？"
  },
  {
    "name": "雪菜",
    "message": "こんな事を言ってはダメですけど、正直お客さんが嫌いになりました。"
  },
  {
    "name": "彦麻呂",
    "message": "やはりジロジロ見るからですか？"
  },
  {
    "name": "雪菜",
    "message": "わざと物を落としたりして、私に拾わせたりするんです。この事は、先生もご存知だと思いますが。"
  },
  {
    "name": "彦麻呂",
    "message": "それで下着を見られてましたねぇ。"
  },
  {
    "name": "雪菜",
    "message": "あの短さでは隠しようがありません。"
  },
  {
    "name": "彦麻呂",
    "message": "見られてる時の気持ちは？"
  },
  {
    "name": "雪菜",
    "message": "…。"
  },
  {
    "name": "彦麻呂",
    "message": "答えて下さいな。"
  },
  {
    "name": "雪菜",
    "message": "イヤです。"
  },
  {
    "name": "彦麻呂",
    "message": "それ以外には？"
  },
  {
    "name": "雪菜",
    "message": "…心が、ムズムズしました。"
  },
  {
    "name": "彦麻呂",
    "message": "どうしてでしょう？"
  },
  {
    "name": "雪菜",
    "message": "…やっぱり心がムズムズしました。"
  },
  {
    "name": "彦麻呂",
    "message": "今度はどうしてでしょう？"
  },
  {
    "name": "雪菜",
    "message": "主人の気持ちを考えると、いたたまれなくなって。"
  },
  {
    "name": "彦麻呂",
    "message": "そのご主人が選んだ服装なのに？"
  },
  {
    "name": "雪菜",
    "message": "だから変な気持ちになります。お客さんに下着を見られた後は、真っ直ぐ主人の顔を見られません。"
  },
  {
    "name": "彦麻呂",
    "message": "色々と複雑なんですねぇ。"
  },
  {
    "name": "雪菜",
    "message": "…。"
  },
  {
    "name": "彦麻呂",
    "message": "では次が最後の質問になります。"
  },
  {
    "name": "彦麻呂",
    "message": "では次の質問に参りますぅ。"
  },
  {
    "name": "彦麻呂",
    "message": "イッた事はありますか？"
  },
  {
    "name": "雪菜",
    "message": "ですから、膣で何回も。"
  },
  {
    "name": "雪菜",
    "message": "数え切れないくらいあります。"
  },
  {
    "name": "彦麻呂",
    "message": "セックスの度にイクわけですね。"
  },
  {
    "name": "雪菜",
    "message": "私が果てないと、主人は満足しません。"
  },
  {
    "name": "彦麻呂",
    "message": "激しくイクほうでしょうか？"
  },
  {
    "name": "雪菜",
    "message": "木造のアパートで同棲してた時に、苦情を言われた事がありました。"
  },
  {
    "name": "彦麻呂",
    "message": "アノ声がうるさい、と？"
  },
  {
    "name": "雪菜",
    "message": "そうです。"
  },
  {
    "name": "彦麻呂",
    "message": "若い時から感じやすい身体なわけですね。"
  },
  {
    "name": "雪菜",
    "message": "壁際でしてたせいもありますけど。"
  },
  {
    "name": "彦麻呂",
    "message": "は？"
  },
  {
    "name": "雪菜",
    "message": "主人と顔見知りだった隣の学生さんに、お前の喘ぎ声を聞かせてやりたいって。"
  },
  {
    "name": "彦麻呂",
    "message": "それで素直に言う事を聞いたんですかぁ？"
  },
  {
    "name": "雪菜",
    "message": "主人が望んだ事ですから、頷くしかありませんでした。"
  },
  {
    "name": "彦麻呂",
    "message": "で、隣人から文句を言われる、と。"
  },
  {
    "name": "雪菜",
    "message": "それも…私に、直接です。"
  },
  {
    "name": "彦麻呂",
    "message": "あれま。"
  },
  {
    "name": "雪菜",
    "message": "主人は、部屋の奥で聞き耳を立てて。"
  },
  {
    "name": "彦麻呂",
    "message": "ニヤニヤしてる？"
  },
  {
    "name": "雪菜",
    "message": "次のセックスの時に責められます。お前の声が無駄に大きいから、俺は恥をかかされた、って。"
  },
  {
    "name": "彦麻呂",
    "message": "理不尽ですねぇ。"
  },
  {
    "name": "雪菜",
    "message": "その時も壁際にいるわけですから、声を我慢するのが、凄く大変でした。"
  },
  {
    "name": "彦麻呂",
    "message": "我慢してる時の気持ちは？"
  },
  {
    "name": "雪菜",
    "message": "ですから、辛いです。"
  },
  {
    "name": "彦麻呂",
    "message": "それ以外には？"
  },
  {
    "name": "雪菜",
    "message": "…心がムズムズします。"
  },
  {
    "name": "彦麻呂",
    "message": "どうしてでしょう？"
  },
  {
    "name": "雪菜",
    "message": "…やっぱり、心がムズムズします。"
  },
  {
    "name": "彦麻呂",
    "message": "今度はどうしてでしょう？"
  },
  {
    "name": "雪菜",
    "message": "おかしな話ですけど、愛されてる気がして。"
  },
  {
    "name": "彦麻呂",
    "message": "なるほどぉ。"
  },
  {
    "name": "雪菜",
    "message": "…。"
  },
  {
    "name": "彦麻呂",
    "message": "では次が最後の質問になります。"
  },
  {
    "name": "彦麻呂",
    "message": "では次の質問に…。"
  },
  {
    "message": "太雪亭へ呼び出した本当の理由は？"
  },
  {
    "name": "彦麻呂",
    "message": "太雪亭へ呼び出した本当の理由は？"
  },
  {
    "name": "雪菜",
    "message": "…理由は前に答えました。"
  },
  {
    "name": "彦麻呂",
    "message": "ご主人が留守の間に、フェラチオする為…ですかぁ？"
  },
  {
    "name": "雪菜",
    "message": "そうです。"
  },
  {
    "name": "彦麻呂",
    "message": "それもご自分の為に？"
  },
  {
    "name": "雪菜",
    "message": "はい。"
  },
  {
    "name": "彦麻呂",
    "message": "私にできる事はこれしかない、そうおっしゃってましたね。"
  },
  {
    "name": "雪菜",
    "message": "…言いました。"
  },
  {
    "name": "彦麻呂",
    "message": "そのできる事をしたあと、私に何を望むのでしょう？"
  },
  {
    "name": "雪菜",
    "message": "…何も望みません。"
  },
  {
    "name": "彦麻呂",
    "message": "それは不思議ですねぇ。"
  },
  {
    "name": "雪菜",
    "message": "勝手に、謝りたいだけです。"
  },
  {
    "name": "彦麻呂",
    "message": "騙してた事を？"
  },
  {
    "name": "雪菜",
    "message": "私は先生を、傷つけてしまいました。"
  },
  {
    "name": "彦麻呂",
    "message": "では全裸になってた理由は？"
  },
  {
    "name": "雪菜",
    "message": "嘘つきで、恥じらいもない女ですから。"
  },
  {
    "name": "彦麻呂",
    "message": "ならどうして照明を消してたんでしょう？"
  },
  {
    "name": "雪菜",
    "message": "…。"
  },
  {
    "name": "彦麻呂",
    "message": "明るくしたら隠れようとしましたが。"
  },
  {
    "name": "雪菜",
    "message": "それは…。"
  },
  {
    "name": "彦麻呂",
    "message": "明るいとやっぱり恥ずかしい？"
  },
  {
    "name": "雪菜",
    "message": "っ、一応は…女ですし。"
  },
  {
    "name": "彦麻呂",
    "message": "なら恥じらいはありますねぇ。"
  },
  {
    "name": "雪菜",
    "message": "…。"
  },
  {
    "name": "彦麻呂",
    "message": "そうなると裸は自分への罰ですか？"
  },
  {
    "name": "雪菜",
    "message": "…それもあります。"
  },
  {
    "name": "彦麻呂",
    "message": "も？"
  },
  {
    "name": "雪菜",
    "message": "逃げられないようにしました。"
  },
  {
    "name": "彦麻呂",
    "message": "は？"
  },
  {
    "name": "雪菜",
    "message": "私が私から。"
  },
  {
    "name": "彦麻呂",
    "message": "どうしてそこまで追い込む必要が？"
  },
  {
    "name": "雪菜",
    "message": "…。"
  },
  {
    "name": "彦麻呂",
    "message": "まだ何かありそうですねぇ。"
  },
  {
    "name": "雪菜",
    "message": "先生を、騙すような事は…してません。"
  },
  {
    "name": "彦麻呂",
    "message": "わかってますよぉ。"
  },
  {
    "message": "麻呂は乳房から手を放し。"
  },
  {
    "message": "真顔で彼女の目を見つめた。"
  },
  {
    "name": "彦麻呂",
    "message": "最初はこの行為の引き替えとして、私を太雪亭へ呼び戻すつもりかも…そう勘ぐってしまいましたが。"
  },
  {
    "name": "雪菜",
    "message": "…。"
  },
  {
    "name": "彦麻呂",
    "message": "どうやらそうではなさそうですし。"
  },
  {
    "name": "雪菜",
    "message": "…太雪亭はなくなります。"
  },
  {
    "name": "彦麻呂",
    "message": "はい？"
  },
  {
    "name": "雪菜",
    "message": "このお店は…潰れるんです。"
  },
  {
    "name": "彦麻呂",
    "message": "…。"
  },
  {
    "name": "彦麻呂",
    "message": "…冗談ですよね？"
  },
  {
    "name": "雪菜",
    "message": "もう、やっていくのは無理なんです。主人が叔父の家へ行ってる理由も、借りたお金をどう返すかって話で…。"
  },
  {
    "name": "雪菜",
    "message": "っ、月々の返済すら苦しかったのに、いきなりまとめて返せだなんて。叔父に督促されたら、全てオシマイなんです。"
  },
  {
    "name": "彦麻呂",
    "message": "どうして督促されたんですかぁ？"
  },
  {
    "name": "雪菜",
    "message": "…叔父を怒らせてしまいました。"
  },
  {
    "name": "彦麻呂",
    "message": "どなたが？"
  },
  {
    "name": "雪菜",
    "message": "っ、夫婦揃って。"
  },
  {
    "name": "彦麻呂",
    "message": "何でそんな事に？"
  },
  {
    "name": "雪菜",
    "message": "…。"
  },
  {
    "name": "彦麻呂",
    "message": "言いにくい事なんですね。"
  },
  {
    "name": "雪菜",
    "message": "アルバイトをしてた親戚の子が、私に…。"
  },
  {
    "name": "彦麻呂",
    "message": "…。"
  },
  {
    "name": "雪菜",
    "message": "最初の頃は、子供と思って我慢してたんですけど、日に日にしてくる事が、エスカレートしてきて…。"
  },
  {
    "name": "彦麻呂",
    "message": "何をされたんでしょう？"
  },
  {
    "name": "雪菜",
    "message": "っ、主人が見てないところで、胸を触られたり。"
  },
  {
    "name": "彦麻呂",
    "message": "思い違いではなく？"
  },
  {
    "name": "雪菜",
    "message": "擦れ違い様に、ギュッと。"
  },
  {
    "name": "彦麻呂",
    "message": "…こんな感じに？"
  },
  {
    "message": "むにゅっ。"
  },
  {
    "name": "雪菜",
    "message": "そ、そうです。"
  },
  {
    "name": "彦麻呂",
    "message": "あとは？"
  },
  {
    "name": "雪菜",
    "message": "腕を掴んで、キスしようとしてきました。"
  },
  {
    "message": "ぶちゅっ。"
  },
  {
    "name": "雪菜",
    "message": "！？"
  },
  {
    "name": "彦麻呂",
    "message": "…こんなふうに？"
  },
  {
    "name": "雪菜",
    "message": "そ、そうです。"
  },
  {
    "name": "彦麻呂",
    "message": "舌は入れられましたかぁ？"
  },
  {
    "name": "雪菜",
    "message": "っ、口を結んで阻止しました。"
  },
  {
    "name": "彦麻呂",
    "message": "本当でしょうか？"
  },
  {
    "message": "ぶちゅっ、くちゅぅ…。"
  },
  {
    "name": "雪菜",
    "message": "ぅ…くぅ…。"
  },
  {
    "name": "彦麻呂",
    "message": "こうして無理にこじ開けられ。"
  },
  {
    "name": "雪菜",
    "message": "むふぅ…っ…んっ…くちゅ…んっ…んっ…。"
  },
  {
    "name": "彦麻呂",
    "message": "舌を入れられたんじゃないですかぁ？"
  },
  {
    "name": "雪菜",
    "message": "ギ、ギリギリされてません。"
  },
  {
    "name": "彦麻呂",
    "message": "こんな事はぁ？"
  },
  {
    "message": "れろれろれろっ。"
  },
  {
    "name": "雪菜",
    "message": "んちゅう…っ…むふぅんっ…。"
  },
  {
    "name": "彦麻呂",
    "message": "旦那さんが見てないのを良い事に…。"
  },
  {
    "message": "れろれろれろれろっ、れろれろれろれろっ。"
  },
  {
    "name": "雪菜",
    "message": "んっ、ん…はあっ…はあっ…ん～っ。"
  },
  {
    "name": "彦麻呂",
    "message": "好き勝手をされたのでは？"
  },
  {
    "name": "雪菜",
    "message": "そ、そんな事…ないです…ぅ。"
  },
  {
    "name": "彦麻呂",
    "message": "どれくらいキスは続きましたかぁ？"
  },
  {
    "name": "雪菜",
    "message": "っ、１０秒くらいだったと思います。"
  },
  {
    "name": "彦麻呂",
    "message": "その間に逃げようと思わなかった？"
  },
  {
    "name": "雪菜",
    "message": "っ、もちろん…思いました。"
  },
  {
    "name": "彦麻呂",
    "message": "でもジッとしてたわけですねぇ。"
  },
  {
    "name": "雪菜",
    "message": "っ、思ったより、ずっと力が強かったんです。"
  },
  {
    "name": "彦麻呂",
    "message": "場所はどちらで？"
  },
  {
    "name": "雪菜",
    "message": "厨房からは見えにくい、ウォーターサーバーの、陰とか。"
  },
  {
    "name": "彦麻呂",
    "message": "…あそこですかぁ。"
  },
  {
    "message": "麻呂は裸の彼女を抱き締め。"
  },
  {
    "message": "キスをしたままヨチヨチ歩きで連れて行く。"
  },
  {
    "name": "雪菜",
    "message": "も、もうあの場所に行きたくありません。"
  },
  {
    "name": "彦麻呂",
    "message": "現場検証ですよぉ。"
  },
  {
    "name": "雪菜",
    "message": "っ、思い出したくないんです。"
  },
  {
    "message": "彼女の申し出は聞き入れられず。"
  },
  {
    "message": "数秒後にはサーバーの陰へ。"
  },
  {
    "message": "確かに厨房からは見えにくく。"
  },
  {
    "message": "旦那の目を逃れるには格好の場所かも。"
  },
  {
    "name": "彦麻呂",
    "message": "…ここでキスされたんですねぇ？"
  },
  {
    "name": "雪菜",
    "message": "はい…んっ…。"
  },
  {
    "name": "彦麻呂",
    "message": "でもお客さんから、丸見えなのでは？"
  },
  {
    "name": "雪菜",
    "message": "そういうところだけ機転が利いて、いつもお客さんがいない時を狙って…。"
  },
  {
    "name": "彦麻呂",
    "message": "…いつも？"
  },
  {
    "message": "べろちゅううぅぅ…。"
  },
  {
    "name": "雪菜",
    "message": "ん、ん～～っ！"
  },
  {
    "name": "彦麻呂",
    "message": "キスされたのは一度じゃない？"
  },
  {
    "name": "雪菜",
    "message": "っ、一度じゃないですぅ。"
  },
  {
    "name": "彦麻呂",
    "message": "何回くらいですかぁ？"
  },
  {
    "name": "雪菜",
    "message": "２回…"
  },
  {
    "message": "３回…"
  },
  {
    "message": "４回…。"
  },
  {
    "name": "彦麻呂",
    "message": "…どんどん増えていきますねぇ。"
  },
  {
    "name": "雪菜",
    "message": "んっ…思い出しながら…数えてるんですぅ。"
  },
  {
    "name": "彦麻呂",
    "message": "される度に舌だけは死守？"
  },
  {
    "name": "雪菜",
    "message": "…。"
  },
  {
    "name": "彦麻呂",
    "message": "あれぇ？"
  },
  {
    "name": "雪菜",
    "message": "し、死守…しま…。"
  },
  {
    "name": "彦麻呂",
    "message": "…しま？"
  },
  {
    "name": "雪菜",
    "message": "…。"
  },
  {
    "message": "べろちゅううぅ…っ。"
  },
  {
    "name": "雪菜",
    "message": "んっ、んふぅっ…べろっ…んふっ…んんっ…んっ…。"
  },
  {
    "name": "彦麻呂",
    "message": "本当は唇を割られましたねぇ？"
  },
  {
    "name": "雪菜",
    "message": "ほ、ほんのちょっとだけです。"
  },
  {
    "message": "べろっ、べろっ、べろっ。"
  },
  {
    "name": "雪菜",
    "message": "っ、今みたいに奥までは…。"
  },
  {
    "message": "ちゅううううぅぅっ。"
  },
  {
    "name": "雪菜",
    "message": "は、入ってきてません。"
  },
  {
    "name": "彦麻呂",
    "message": "相手のガキはそれで納得しましたか？"
  },
  {
    "name": "雪菜",
    "message": "もっと、口を開けろと怒られました。"
  },
  {
    "name": "彦麻呂",
    "message": "それで雪菜さんは？"
  },
  {
    "name": "雪菜",
    "message": "もちろん、聞く耳は持たないです。"
  },
  {
    "name": "彦麻呂",
    "message": "そのまま引き下がるヤツとは思えませんが。"
  },
  {
    "name": "雪菜",
    "message": "っ、だから腹いせに、私の胸を…。"
  },
  {
    "name": "彦麻呂",
    "message": "…胸をぉ？"
  },
  {
    "name": "雪菜",
    "message": "モ、モミモミしてきました。"
  },
  {
    "name": "彦麻呂",
    "message": "こんな感じでしょうかぁ。"
  },
  {
    "message": "モミモミモミっ、モミモミモミっ。"
  },
  {
    "name": "雪菜",
    "message": "っ…そうです。"
  },
  {
    "name": "彦麻呂",
    "message": "キスしたまま？"
  },
  {
    "name": "雪菜",
    "message": "し、してたりしてなかったり…。"
  },
  {
    "name": "彦麻呂",
    "message": "限りなく愛撫に近いじゃないですかぁ。"
  },
  {
    "message": "ちゅううううっ、モミモミモミっ。"
  },
  {
    "name": "雪菜",
    "message": "くっ…んっ…。"
  },
  {
    "name": "彦麻呂",
    "message": "もしかして膨らみの先端も弄られた？"
  },
  {
    "name": "雪菜",
    "message": "あっ…くぅ…先端は…ぁ…。"
  },
  {
    "name": "彦麻呂",
    "message": "さすがにそこまでは許しませんよね？"
  },
  {
    "name": "雪菜",
    "message": "ぅ…。"
  },
  {
    "name": "彦麻呂",
    "message": "あれぇ？"
  },
  {
    "message": "つまみっ。"
  },
  {
    "name": "雪菜",
    "message": "ひっ…ん…。"
  },
  {
    "name": "彦麻呂",
    "message": "ガキにこんな事までされてしまった、と。"
  },
  {
    "name": "雪菜",
    "message": "され…まし…たぁ…。"
  },
  {
    "name": "彦麻呂",
    "message": "セーターの上から？"
  },
  {
    "name": "雪菜",
    "message": "さ、最初は上から…。"
  },
  {
    "name": "彦麻呂",
    "message": "だんだんエスカレートしていったんですねぇ。"
  },
  {
    "name": "雪菜",
    "message": "慣れてくると、セーターに、手を入れられて。"
  },
  {
    "name": "彦麻呂",
    "message": "くぅ…っ。"
  },
  {
    "message": "もみもみっ、もみもみっ。"
  },
  {
    "name": "雪菜",
    "message": "っ、次はブラの内側まで、手が潜り込んできて…。"
  },
  {
    "name": "彦麻呂",
    "message": "そのままポッチを摘まれた？"
  },
  {
    "name": "雪菜",
    "message": "摘まれましたぁ。"
  },
  {
    "name": "彦麻呂",
    "message": "こんな事が日々続いたわけですか？"
  },
  {
    "name": "雪菜",
    "message": "は、はい。"
  },
  {
    "name": "彦麻呂",
    "message": "それでも奥さんは我慢してた。"
  },
  {
    "name": "雪菜",
    "message": "っ、お金を借りてる叔父の存在が大きすぎて、勤務態度が悪くても文句一つ言えない子です。"
  },
  {
    "name": "彦麻呂",
    "message": "そうやって我慢した挙げ句は？"
  },
  {
    "name": "雪菜",
    "message": "…え？"
  },
  {
    "name": "彦麻呂",
    "message": "触られたのは胸で終わりでしょうか？"
  },
  {
    "name": "雪菜",
    "message": "ぅ…。"
  },
  {
    "name": "彦麻呂",
    "message": "…ですよねぇ。"
  },
  {
    "name": "雪菜",
    "message": "ぁ…。"
  },
  {
    "message": "麻呂は彼女を抱きかかえ。"
  },
  {
    "message": "テーブルの上にポテッと座らせる。"
  },
  {
    "message": "雪菜は完全にされるがままで。"
  },
  {
    "message": "お人形さんみたいに、こっちを見てるだけ。"
  },
  {
    "name": "雪菜",
    "message": "っ…。"
  },
  {
    "name": "彦麻呂",
    "message": "次にどこを触られたか教えて下さい。"
  },
  {
    "name": "雪菜",
    "message": "で、ですから…。"
  },
  {
    "name": "彦麻呂",
    "message": "正直に、どうぞ。"
  },
  {
    "name": "雪菜",
    "message": "…下腹部…です。"
  },
  {
    "name": "彦麻呂",
    "message": "ほっ…。"
  },
  {
    "name": "雪菜",
    "message": "っ、性器を指で…弄られました。"
  },
  {
    "name": "彦麻呂",
    "message": "どのあたりでしょう？"
  },
  {
    "name": "雪菜",
    "message": "ど、どのあたりと言われても…。"
  },
  {
    "name": "彦麻呂",
    "message": "見せてないと説明しにくいですかぁ？"
  },
  {
    "message": "ぐいっ。"
  },
  {
    "name": "雪菜",
    "message": "ぁ…。"
  },
  {
    "message": "強引に足を拡げられ。"
  },
  {
    "message": "何もかもが白日の下に。"
  },
  {
    "message": "薄く生えた恥毛では隠しようがなく。"
  },
  {
    "message": "肉の谷間からヒダの部分まで露出させてる。"
  },
  {
    "name": "彦麻呂",
    "message": "ここら辺りでしょうかねぇ。"
  },
  {
    "name": "雪菜",
    "message": "ぅ…っ…。"
  },
  {
    "message": "麻呂の指が伸び。"
  },
  {
    "message": "恥丘から始まる縦筋をツーッとなぞった。"
  },
  {
    "message": "彼女は内股の筋をピンと筋立たせ。"
  },
  {
    "message": "繰り返し小さく頷いてる。"
  },
  {
    "name": "雪菜",
    "message": "っ、そこを触られました。"
  },
  {
    "name": "彦麻呂",
    "message": "指で直にですかぁ？"
  },
  {
    "name": "雪菜",
    "message": "ベルトの上から手を入れられ、下着の上からモゾモゾと…です。"
  },
  {
    "name": "彦麻呂",
    "message": "こんな感じですかねぇ。"
  },
  {
    "message": "もぞ、ぷに、もぞ、ぷに…。"
  },
  {
    "name": "雪菜",
    "message": "っ…そんな感じです。"
  },
  {
    "name": "彦麻呂",
    "message": "下着を割れ目に食い込ませながら？"
  },
  {
    "name": "雪菜",
    "message": "は、はい。"
  },
  {
    "name": "彦麻呂",
    "message": "ガキの指は先へ進みましたか？"
  },
  {
    "name": "雪菜",
    "message": "っ、進みました。"
  },
  {
    "name": "彦麻呂",
    "message": "クリトリスも弄られたんですねぇ？"
  },
  {
    "name": "雪菜",
    "message": "そ、そこは気づかずに、どんどん下のほうへ。"
  },
  {
    "name": "彦麻呂",
    "message": "下にあるのは膣の入り口ですが…。"
  },
  {
    "message": "谷間からはみ出た陰唇。"
  },
  {
    "message": "入り組んだその隙間へ指を差し込み。"
  },
  {
    "message": "パクッとＶの字に拡げてみる。"
  },
  {
    "message": "淡い桜色の粘膜が顔を覗かせ。"
  },
  {
    "message": "トロッとした粘液がテーブルの上へ。"
  },
  {
    "name": "雪菜",
    "message": "あ…す、すみません。"
  },
  {
    "name": "彦麻呂",
    "message": "こんなに弄られてたら、誰だってこうなります。"
  },
  {
    "name": "雪菜",
    "message": "…え？"
  },
  {
    "name": "彦麻呂",
    "message": "ですから気にしないで下さいな。"
  },
  {
    "name": "雪菜",
    "message": "…。"
  },
  {
    "message": "優しい言葉に慣れてないのか。"
  },
  {
    "message": "麻呂を見る彼女はキョトンとした顔だ。"
  },
  {
    "name": "彦麻呂",
    "message": "指は入れられなかったんですね？"
  },
  {
    "name": "雪菜",
    "message": "っ、直接的には、入ってません。"
  },
  {
    "name": "彦麻呂",
    "message": "直接的とは？"
  },
  {
    "name": "雪菜",
    "message": "下着の上から強引に…ギュッと潜る感じで。"
  },
  {
    "name": "彦麻呂",
    "message": "入っちゃってるじゃないですかぁ。"
  },
  {
    "name": "雪菜",
    "message": "で、でも下着の上からです。"
  },
  {
    "name": "彦麻呂",
    "message": "もしかしてその時も濡れてました？"
  },
  {
    "name": "雪菜",
    "message": "…。"
  },
  {
    "message": "彼女はヌルッとした感触を思い出し。"
  },
  {
    "message": "ガキから潤された屈辱に唇の端を噛んだ。"
  },
  {
    "name": "雪菜",
    "message": "っ…濡れてたと思います。"
  },
  {
    "name": "彦麻呂",
    "message": "だから簡単にズブッと入っちゃった？"
  },
  {
    "name": "雪菜",
    "message": "そ、そうです。"
  },
  {
    "name": "彦麻呂",
    "message": "今は下着を穿いておりませんが…。"
  },
  {
    "message": "くちゅう…。"
  },
  {
    "name": "雪菜",
    "message": "ひ…ぅ…。"
  },
  {
    "name": "彦麻呂",
    "message": "こんな感じで潜ったんですかぁ？"
  },
  {
    "name": "雪菜",
    "message": "も、もう少し奥まで…。"
  },
  {
    "name": "彦麻呂",
    "message": "他人様の奥さんなのに、図々しいガキですねぇ。"
  },
  {
    "message": "ぐちゅう…っ。"
  },
  {
    "name": "雪菜",
    "message": "それくらい…ですぅ。"
  },
  {
    "name": "彦麻呂",
    "message": "潜り込ませたあとは？"
  },
  {
    "name": "雪菜",
    "message": "っ、乱暴に、出したり入れたりを、繰り返してましたぁ。"
  },
  {
    "name": "彦麻呂",
    "message": "…思春期の洟垂れ小僧がやりそうな事です。"
  },
  {
    "message": "ぐちゅっ…ぬぷぅっ…ぐちゅっ…ぬぷぅっ…。"
  },
  {
    "name": "雪菜",
    "message": "あっ…う…っ…。"
  },
  {
    "name": "彦麻呂",
    "message": "指の付け根がクリトリスに当たりますね。"
  },
  {
    "name": "雪菜",
    "message": "は、はい。"
  },
  {
    "name": "彦麻呂",
    "message": "ガキの時も同じように？"
  },
  {
    "name": "雪菜",
    "message": "っ、当たってました。"
  },
  {
    "name": "彦麻呂",
    "message": "ガキはそれに気づかず…。"
  },
  {
    "name": "雪菜",
    "message": "ず、ずっと出し入れを。"
  },
  {
    "message": "ぐちゅっ…ぬぷぅっ…ぐちゅっ…ぬぷぅっ…。"
  },
  {
    "name": "雪菜",
    "message": "あっ…っ…あっ…う…っ…。"
  },
  {
    "message": "ぬぷぅっ…ぐちゅっ…ぬぷぅっ…ぐちゅっ…ぬぷぅっ…。"
  },
  {
    "name": "雪菜",
    "message": "あぁ…っ…んっ…あっ…ぁ…っ…あぁ…っ…。"
  },
  {
    "name": "彦麻呂",
    "message": "我慢しても声が出ちゃいましたか？"
  },
  {
    "name": "雪菜",
    "message": "で、出ちゃいました。"
  },
  {
    "name": "彦麻呂",
    "message": "旦那さんが側にいるのに？"
  },
  {
    "name": "雪菜",
    "message": "は、はい。"
  },
  {
    "name": "彦麻呂",
    "message": "そのガキはバレる事も恐れず？"
  },
  {
    "name": "雪菜",
    "message": "…何も恐がってなかったですから。"
  },
  {
    "name": "彦麻呂",
    "message": "生意気なクソガキですねぇ。"
  },
  {
    "name": "雪菜",
    "message": "主人が叱れないのを、知ってましたし。"
  },
  {
    "name": "彦麻呂",
    "message": "もしかして旦那さんは…。"
  },
  {
    "name": "雪菜",
    "message": "…。"
  },
  {
    "message": "彼女は長い睫を伏せ。"
  },
  {
    "message": "悲しげにコクリと頷く。"
  },
  {
    "name": "雪菜",
    "message": "ずっと前から…勘付いてたと思います。"
  },
  {
    "name": "彦麻呂",
    "message": "奥さんがイタズラされてるのを？"
  },
  {
    "name": "雪菜",
    "message": "はい。"
  },
  {
    "name": "彦麻呂",
    "message": "でも見て見ないフリをしてた？"
  },
  {
    "name": "雪菜",
    "message": "っ、そうするしかありません。"
  },
  {
    "name": "彦麻呂",
    "message": "それじゃガキもつけ上がりますぅ。"
  },
  {
    "name": "雪菜",
    "message": "…おっしゃる通りです。"
  },
  {
    "name": "彦麻呂",
    "message": "エスカレートしたでしょうねぇ。"
  },
  {
    "name": "雪菜",
    "message": "最後は勃起したペニスを出して、その上に残りのナルトを乗せて、このままお前の口で頬張れって…。"
  },
  {
    "name": "彦麻呂",
    "message": "そりゃあさすがのご主人も…。"
  },
  {
    "name": "雪菜",
    "message": "堪忍袋の緒が切れました。カウンターを乗り越えた主人が、怒鳴りながら胸ぐらを掴んで…。"
  },
  {
    "message": "膣の内側がキュッと窄まり。"
  },
  {
    "message": "豊満な胸元にゾワッと鳥肌が立つ。"
  },
  {
    "name": "彦麻呂",
    "message": "…殴っちゃったんですねぇ。"
  },
  {
    "name": "雪菜",
    "message": "っ、それも、ゲンコツじゃなく…ビール瓶で。"
  },
  {
    "name": "彦麻呂",
    "message": "あれま。"
  },
  {
    "name": "雪菜",
    "message": "そのせいで、額に５針も縫う怪我を…。"
  },
  {
    "name": "彦麻呂",
    "message": "そして父親である叔父サンは大激怒、ですかぁ？"
  },
  {
    "name": "雪菜",
    "message": "キズが残るとお医者さんに告げられ、絶対に許さないと言われちゃいました。"
  },
  {
    "name": "彦麻呂",
    "message": "それが督促された理由ですねぇ。"
  },
  {
    "name": "雪菜",
    "message": "…私、来週から叔父様のお屋敷で働きます。"
  },
  {
    "name": "彦麻呂",
    "message": "は？"
  },
  {
    "name": "雪菜",
    "message": "主人はそれで呼び出されてるんです。もちろん話し合い次第ですけど、撤回はしてくれないと思いますから。"
  },
  {
    "name": "彦麻呂",
    "message": "…。"
  },
  {
    "name": "雪菜",
    "message": "少しでも、借金を返さないといけませんし。"
  },
  {
    "name": "彦麻呂",
    "message": "家政婦って事ですかぁ？"
  },
  {
    "name": "雪菜",
    "message": "住み込みなので、中乃町ともサヨナラです。"
  },
  {
    "name": "彦麻呂",
    "message": "それじゃあ…。"
  },
  {
    "name": "雪菜",
    "message": "先生と、二度と会う事はないかも知れません。"
  },
  {
    "name": "彦麻呂",
    "message": "…寂しくなりますねぇ。"
  },
  {
    "name": "雪菜",
    "message": "私も…です…。"
  },
  {
    "message": "瞳が切なげに揺れ。"
  },
  {
    "message": "彼女は開いてた脚をそっと閉じる。"
  },
  {
    "name": "雪菜",
    "message": "私、先生の事が好きでした。"
  },
  {
    "name": "彦麻呂",
    "message": "…。"
  },
  {
    "name": "雪菜",
    "message": "妹なんて、嘘をついてごめんなさい。"
  },
  {
    "name": "彦麻呂",
    "message": "…もういいんですよぉ。"
  },
  {
    "name": "雪菜",
    "message": "これだけでも、ちゃんと言えて良かった。"
  },
  {
    "name": "彦麻呂",
    "message": "私も聞けて良かったですぅ。"
  },
  {
    "name": "雪菜",
    "message": "…。"
  },
  {
    "message": "彼女は今にも泣きそう。"
  },
  {
    "message": "だけど我慢する事を躾られてるせいで。"
  },
  {
    "message": "素直に感情を出す事ができなくなってる。"
  },
  {
    "name": "彦麻呂",
    "message": "ここにいる理由がジワジワ判ってきましたぁ。"
  },
  {
    "name": "雪菜",
    "message": "っ、もう一回フェラチオしてもいいですか？"
  },
  {
    "message": "涙が零れる寸前。"
  },
  {
    "message": "彼女は麻呂の返事を待たず。"
  },
  {
    "message": "遮二無二チンポへしゃぶりつく。"
  },
  {
    "name": "雪菜",
    "message": "じゅぼっ…じゅぼっ…んぐっ…じゅぼっ…じゅぼっ…んぐっ…じゅぼっ…ちゅるっ…んぐっ…じゅぼっ…じゅぼっ…じゅぼっ…。"
  },
  {
    "name": "雪菜",
    "message": "んぐぅっ…くちゅっ…じゅぼっ…じゅぼっ…ちゅうっ…じゅぼっ…じゅるっ…んぐっ…んぐっ…じゅぼっ…じゅぼっ…じゅぼっ…。"
  },
  {
    "name": "雪菜",
    "message": "んふぅっ…じゅぼっ…じゅぼっ…くちゅっ…んぐっ…じゅぼっ…じゅぼっ…んぐっ…んぐっ…じゅぼっ…じゅぼっ…くちゅっ…ぅ。"
  },
  {
    "message": "頬が凹もうがお構いなし。"
  },
  {
    "message": "じゅるじゅると垂れる涎も気にせず。"
  },
  {
    "message": "彼女は自分の気持ちをペニスに注ぎ込む。"
  },
  {
    "message": "時にムセ。"
  },
  {
    "message": "上気した頬に涙がポロポロ零れた。"
  },
  {
    "message": "それは最初の時より扇情的で。"
  },
  {
    "message": "温もりが肉芯へ届くほどの熱の入れよう。"
  },
  {
    "message": "摩擦する時は下唇に力が入り。"
  },
  {
    "message": "より亀頭の裏側へ刺激を与えようとする。"
  },
  {
    "message": "介添えの手はいつの間にか会陰へ這い。"
  },
  {
    "message": "欲情を煽るようリズミカルに。"
  },
  {
    "message": "奉仕。"
  },
  {
    "message": "この言葉がピッタリな行為。"
  },
  {
    "message": "彼女が旦那から何を仕込まれてきたか。"
  },
  {
    "message": "説明をされなくても窺い知る事ができる。"
  },
  {
    "message": "ちゅるんっ…。"
  },
  {
    "name": "雪菜",
    "message": "…大きい…です。"
  },
  {
    "message": "くちゅっ…ぺろっ…。"
  },
  {
    "name": "雪菜",
    "message": "主人以外のオチンポは、舐めた事がありません。"
  },
  {
    "name": "彦麻呂",
    "message": "…でしたよねぇ。"
  },
  {
    "name": "雪菜",
    "message": "良かったら、命令して貰えませんか？"
  },
  {
    "message": "そう言いながら彼女は舌先で鈴口を弄び。"
  },
  {
    "message": "溢れ出るカウパーを啜るように吸う。"
  },
  {
    "name": "彦麻呂",
    "message": "何をでしょう？"
  },
  {
    "name": "雪菜",
    "message": "メス豚のように舐めろ、って。"
  },
  {
    "name": "彦麻呂",
    "message": "メス豚のように舐めろぉ。"
  },
  {
    "name": "雪菜",
    "message": "…喜んで。"
  },
  {
    "name": "雪菜",
    "message": "じゅぼぉ…っ。"
  },
  {
    "name": "彦麻呂",
    "message": "く…は…。"
  },
  {
    "name": "雪菜",
    "message": "んぐっ…メス豚のように…じゅぼっ…じゅぼっ…じゅぼっ…先生のチンポ、舐めますぅ…じゅぼっ…じゅぼっ…じゅぼっ…。"
  },
  {
    "name": "雪菜",
    "message": "んっ…も、もっと奥まで…主人のより…奥まで…んぐっ…じゅぼっ…んぐっ…じゅぼっ…じゅぼっ…じゅぼっ…じゅぼっ…っ。"
  },
  {
    "name": "雪菜",
    "message": "あぁ…ヨダレが垂れるぅ…メス豚じゃなくて…メス牛みたいに…じゅぼっ…じゅぼっ…じゅぼっ…じゅぼっ…んぐっ…じゅぼっ…。"
  },
  {
    "name": "彦麻呂",
    "message": "ブタじゃなくてウシにしますかぁ？"
  },
  {
    "name": "雪菜",
    "message": "ぁ…。"
  },
  {
    "message": "今の言葉がよほど嬉しかったのか。"
  },
  {
    "message": "乳房が揺れるくらい身体を戦慄かせる。"
  },
  {
    "message": "ちゅるんっ…。"
  },
  {
    "name": "雪菜",
    "message": "こ、このホルスタインって、馬鹿にしちゃって下さい。"
  },
  {
    "name": "彦麻呂",
    "message": "このホルスタイン。"
  },
  {
    "name": "雪菜",
    "message": "っ、オッパイだけの馬鹿女。"
  },
  {
    "name": "彦麻呂",
    "message": "オッパイだけの馬鹿女ぁ。"
  },
  {
    "name": "雪菜",
    "message": "あ、ありがとうございます。"
  },
  {
    "message": "身体の震えが止まらず。"
  },
  {
    "message": "瞳の奥が悦びの色で満たされる。"
  },
  {
    "name": "雪菜",
    "message": "好き…やっぱり…先生、好き…です。"
  },
  {
    "name": "彦麻呂",
    "message": "っ、好きなのは私のほうですよぉ。"
  },
  {
    "name": "雪菜",
    "message": "尊敬できる人だって、今もずっと思ってます。"
  },
  {
    "name": "彦麻呂",
    "message": "何だかこそばゆいですぅ。"
  },
  {
    "name": "雪菜",
    "message": "先生と一緒だった時が一番楽しかった。仕事にも張り合いがあって、出前から戻るのが待ち遠しくて。"
  },
  {
    "name": "雪菜",
    "message": "こんなブスなのに優しくしてくれて。私の作ったオニギリを食べてくれて、夜桜も見に連れて行ってくれて。"
  },
  {
    "name": "彦麻呂",
    "message": "雪菜さんはブスじゃありません。"
  },
  {
    "name": "雪菜",
    "message": "ブスです。"
  },
  {
    "name": "彦麻呂",
    "message": "どこから見ても美人じゃないですか。"
  },
  {
    "name": "雪菜",
    "message": "っ、心と身体の美しい人が、本当の美人です。"
  },
  {
    "name": "雪菜",
    "message": "じゅぼぉ…私は違います…んぐっ…。"
  },
  {
    "name": "彦麻呂",
    "message": "くぅ…っ。"
  },
  {
    "name": "雪菜",
    "message": "んぐぅ…んぐっっ…私は性欲の強い、ただのブタで…じゅぼっ…だからあんな子に触られても…んぐっ…私は濡れちゃうんですぅ。"
  },
  {
    "name": "彦麻呂",
    "message": "辛い立場になればなるほど、逆に感じてしまうのでは？"
  },
  {
    "name": "雪菜",
    "message": "っ、主人が近くにいると特に…じゅぼっ…いつも叱られてばかりで…んぐっ…お前は役立たずって言われて…んぐっ…。"
  },
  {
    "name": "雪菜",
    "message": "だから何でも言う事を聞きました…じゅぼっ…脱げと言われれば脱いだし、舐めろと言われれば舐めた…んぐっ…ぅ…。"
  },
  {
    "name": "彦麻呂",
    "message": "…偏った関係ですねぇ。"
  },
  {
    "name": "雪菜",
    "message": "そんな事ばかりしてたら、変な性癖がついちゃって…直そうとしても主人には何も言えなくて…じゅぼっ…じゅぼっ…んぐっ…。"
  },
  {
    "name": "雪菜",
    "message": "っ、自分の事になると、お願い一つできません…主人以外でも、それは変わらなくて…逆に言われた事は、何でも聞いちゃって…。"
  },
  {
    "name": "彦麻呂",
    "message": "私には色々と指導してくれたじゃないですかぁ。今こうして咥えてるオチンポだって、雪菜さんのほうから積極的にですよぉ。"
  },
  {
    "name": "雪菜",
    "message": "せ、先生だと何故か甘えられて…んぐっ…じゅぼっ…そんな人は今まで一人もいなかった…じゅるっ…じゅぼっ…じゅぼっ…。"
  },
  {
    "name": "彦麻呂",
    "message": "私も他の人も同じですがねぇ。"
  },
  {
    "name": "雪菜",
    "message": "他の人だと無理ですぅ…んぐっ…お客さんでも無理…ぃ…。"
  },
  {
    "name": "彦麻呂",
    "message": "優しい人だってちゃんといます。"
  },
  {
    "name": "雪菜",
    "message": "っ、意地悪なお客さんばかりです…わざとコショーとか落として、だけど私も私で、下着が見えるのわかってて、それでもしゃがんじゃって…。"
  },
  {
    "name": "彦麻呂",
    "message": "タンメンとギョーザを。"
  },
  {
    "name": "雪菜",
    "message": "…え？"
  },
  {
    "message": "ちゅるんっ。"
  },
  {
    "name": "雪菜",
    "message": "…何て言ったんですか？"
  },
  {
    "name": "彦麻呂",
    "message": "タンメンとギョーザをお願いしますぅ。"
  },
  {
    "name": "雪菜",
    "message": "ぁ…。"
  },
  {
    "message": "麻呂の意を汲んだのか。"
  },
  {
    "message": "或いは身体が反応してしまったのか。"
  },
  {
    "message": "咄嗟に彼女はチンポから手を放し。"
  },
  {
    "message": "オッパイを揺らしながら立ち上がる。"
  },
  {
    "name": "雪菜",
    "message": "いらっしゃい…ませ？"
  },
  {
    "name": "彦麻呂",
    "message": "太雪亭の看板娘は無愛想でしたっけ？"
  },
  {
    "name": "雪菜",
    "message": "い、いらっしゃいませ。"
  },
  {
    "name": "彦麻呂",
    "message": "タンメンとギョーザを。"
  },
  {
    "name": "雪菜",
    "message": "タンメンとギョーザ一つ、入ります。"
  },
  {
    "message": "彼女は厨房へ入り。"
  },
  {
    "message": "いつもしてた動作をエアでしてる。"
  },
  {
    "message": "麻呂が客で来てた頃を思い出してるのか。"
  },
  {
    "message": "どこか本気で懐かしそう。"
  },
  {
    "name": "雪菜",
    "message": "っ、お待たせしました。"
  },
  {
    "name": "彦麻呂",
    "message": "美味しそうですねぇ。"
  },
  {
    "message": "もちろんトレーには何も乗ってない。"
  },
  {
    "message": "でも彼女はテーブルにタンメンを置き。"
  },
  {
    "message": "麻呂は割り箸をパチンと分ける。"
  },
  {
    "message": "ぽとんっ、ころっっ…。"
  },
  {
    "name": "雪菜",
    "message": "ぁ…。"
  },
  {
    "name": "彦麻呂",
    "message": "あれぇ。"
  },
  {
    "message": "割り箸とぶつかったコショーが落ち。"
  },
  {
    "message": "コロコロと彼女のほうへ転がっていった。"
  },
  {
    "message": "暫し二人はそれを目で追いかけ。"
  },
  {
    "message": "止まったところで顔を見合わせる。"
  },
  {
    "name": "彦麻呂",
    "message": "どうしますか？"
  },
  {
    "name": "雪菜",
    "message": "ど、どうしましょう。"
  },
  {
    "name": "彦麻呂",
    "message": "普通のお客さんなら、自分で拾いますよねぇ。"
  },
  {
    "message": "麻呂は椅子をずらし。"
  },
  {
    "message": "コショーを拾おうと腕を伸ばした。"
  },
  {
    "name": "雪菜",
    "message": "っ、私が拾います。"
  },
  {
    "name": "彦麻呂",
    "message": "何も命令されてないのに？"
  },
  {
    "name": "雪菜",
    "message": "頼まれてはいませんが、拾ってあげたいかな…って。"
  },
  {
    "name": "彦麻呂",
    "message": "つまり雪菜さんの意志で？"
  },
  {
    "name": "雪菜",
    "message": "そうです。"
  },
  {
    "name": "彦麻呂",
    "message": "優しい看板娘さんですねぇ。なら、思った通りにして下さい。"
  },
  {
    "message": "麻呂は椅子を戻し。"
  },
  {
    "message": "拾う動作を中断する。"
  },
  {
    "message": "代わりに彼女がそこへしゃがみ込み。"
  },
  {
    "message": "かつて見た光景でコショーを拾ってくれた。"
  },
  {
    "name": "彦麻呂",
    "message": "すぐお客さんに渡しますか？"
  },
  {
    "name": "雪菜",
    "message": "…え？"
  },
  {
    "name": "彦麻呂",
    "message": "自分のしたいようにして下さい。"
  },
  {
    "name": "雪菜",
    "message": "…。"
  },
  {
    "name": "彦麻呂",
    "message": "下着を見られてた時、イヤでしたよねぇ？"
  },
  {
    "name": "雪菜",
    "message": "っ、イヤでした。"
  },
  {
    "name": "彦麻呂",
    "message": "でも心がムズムズ？"
  },
  {
    "name": "雪菜",
    "message": "そ、そうです。"
  },
  {
    "name": "彦麻呂",
    "message": "今は？"
  },
  {
    "name": "雪菜",
    "message": "やっぱり…ムズムズします。"
  },
  {
    "name": "彦麻呂",
    "message": "旦那さんが側にいないのに？"
  },
  {
    "name": "雪菜",
    "message": "ぁ…。"
  },
  {
    "name": "彦麻呂",
    "message": "どうしてでしょう？"
  },
  {
    "name": "雪菜",
    "message": "わ、わからないです。"
  },
  {
    "name": "彦麻呂",
    "message": "あの時と同じように見られてますが。"
  },
  {
    "name": "雪菜",
    "message": "…そうですよね。"
  },
  {
    "name": "彦麻呂",
    "message": "それも下着どころか性器を直に。"
  },
  {
    "name": "雪菜",
    "message": "ぅ…。"
  },
  {
    "name": "彦麻呂",
    "message": "ここから先も雪菜さんの自由ですよ。"
  },
  {
    "name": "雪菜",
    "message": "っ、暫く…このままじっとしていたい。"
  },
  {
    "name": "彦麻呂",
    "message": "…わかりましたぁ。"
  },
  {
    "name": "雪菜",
    "message": "ワガママ言って、すみません。"
  },
  {
    "name": "彦麻呂",
    "message": "私はどうすればいいでしょう？"
  },
  {
    "name": "雪菜",
    "message": "で、できれば、イヤらしい、お客さんに。"
  },
  {
    "name": "彦麻呂",
    "message": "了解しましたぁ。"
  },
  {
    "message": "麻呂はタンメンを食べる仕草で。"
  },
  {
    "message": "チラチラと彼女へ視線を向ける。"
  },
  {
    "message": "まず顔を見て。"
  },
  {
    "message": "それから胸を見て。"
  },
  {
    "message": "最後はヒダが覗く肉の谷間へ。"
  },
  {
    "message": "それを何度も順番で繰り返し。"
  },
  {
    "message": "コショーを渡したくなるまで止めてあげない。"
  },
  {
    "name": "雪菜",
    "message": "ぁ…ぅ…。"
  },
  {
    "name": "彦麻呂",
    "message": "じろじろじろじろ。"
  },
  {
    "name": "雪菜",
    "message": "ぅ…ぁ…ぅ…。"
  },
  {
    "name": "彦麻呂",
    "message": "じろじろじろじろ、じろじろじろじろ。"
  },
  {
    "name": "雪菜",
    "message": "ぃ…ゃ…。"
  },
  {
    "message": "膝を擦り寄せ。"
  },
  {
    "message": "顔で必死にイヤイヤしてた。"
  },
  {
    "message": "辛いのに幸せで。"
  },
  {
    "message": "居たたまれないのに続けたい。"
  },
  {
    "message": "歪な恍惚感が全身を包み込み。"
  },
  {
    "message": "指で突っつけばパチンと弾けてしまいそう。"
  },
  {
    "message": "とろっ…。"
  },
  {
    "name": "雪菜",
    "message": "ゃ…ゃ…。"
  },
  {
    "message": "モジモジで膣壁が揉まれたのだろう。"
  },
  {
    "message": "透明の雫が糸を引きながら床へ垂れ落ち。"
  },
  {
    "message": "かつての仕事場に小さな水溜まりを作る。"
  },
  {
    "message": "その羞恥心に彼女は耳まで真っ赤となり。"
  },
  {
    "message": "床を隠そうとする仕草も、やたら可愛らしく見えた。"
  },
  {
    "name": "雪菜",
    "message": "か、勝手に出ちゃいました。"
  },
  {
    "name": "彦麻呂",
    "message": "私は何も言ってませんが。"
  },
  {
    "name": "雪菜",
    "message": "す、すみません。"
  },
  {
    "name": "彦麻呂",
    "message": "次は何をしたくなりましたかぁ？"
  },
  {
    "name": "雪菜",
    "message": "な、何をって…。"
  },
  {
    "name": "彦麻呂",
    "message": "命令する人間はどこにもいませんよ。"
  },
  {
    "name": "雪菜",
    "message": "っ…逆にそれで困ってます。"
  },
  {
    "name": "彦麻呂",
    "message": "自分の思ったとおりにすれば良いかと。"
  },
  {
    "name": "雪菜",
    "message": "本当に…いいんですか？"
  },
  {
    "name": "彦麻呂",
    "message": "はい。"
  },
  {
    "name": "雪菜",
    "message": "どんな…事でも？"
  },
  {
    "name": "彦麻呂",
    "message": "何がダメというルールは、どこにもありませんので。"
  },
  {
    "name": "雪菜",
    "message": "…。"
  },
  {
    "name": "彦麻呂",
    "message": "戸惑わずにどうぞ。"
  },
  {
    "name": "雪菜",
    "message": "っ、見られてて、凄く辛いのに。"
  },
  {
    "name": "彦麻呂",
    "message": "ですよねぇ。"
  },
  {
    "name": "雪菜",
    "message": "ど、どういうわけか心の中で…。"
  },
  {
    "name": "彦麻呂",
    "message": "何を思いましたかぁ？"
  },
  {
    "name": "雪菜",
    "message": "こ、こうしたいって思いました。"
  },
  {
    "message": "彼女は膝を開き。"
  },
  {
    "message": "奥の奥まで余すところ無く見せた。"
  },
  {
    "message": "あの時と違い今日は全裸で。"
  },
  {
    "message": "クリトリスまでちょっと見えちゃってる。"
  },
  {
    "name": "雪菜",
    "message": "っ、軽蔑しますよね？"
  },
  {
    "name": "彦麻呂",
    "message": "どちらの返事を望んでますかぁ？"
  },
  {
    "name": "雪菜",
    "message": "両方…かも…です。"
  },
  {
    "name": "彦麻呂",
    "message": "良い返事ですぅ。"
  },
  {
    "name": "雪菜",
    "message": "先生の事が好きですから、嫌われたくありません。"
  },
  {
    "name": "彦麻呂",
    "message": "素直に自分の気持ちが言えてますねぇ。"
  },
  {
    "name": "雪菜",
    "message": "でも、その好きな先生から、白い目でじっと見られて、どうしようもない女って…。"
  },
  {
    "name": "彦麻呂",
    "message": "そう思われたいですか？"
  },
  {
    "name": "雪菜",
    "message": "へ、ヘンタイでごめんなさい。"
  },
  {
    "name": "彦麻呂",
    "message": "それが本当の雪菜さんなら、そのままでも十分素敵です。"
  },
  {
    "name": "雪菜",
    "message": "…え？"
  },
  {
    "name": "彦麻呂",
    "message": "無理に直す必要など無いのでは？"
  },
  {
    "name": "雪菜",
    "message": "だ、だって…。"
  },
  {
    "name": "彦麻呂",
    "message": "何より誰にも迷惑をかけてません。"
  },
  {
    "name": "雪菜",
    "message": "…。"
  },
  {
    "name": "彦麻呂",
    "message": "むしろ人を幸せにしてると思いますが。"
  },
  {
    "name": "雪菜",
    "message": "…私が…幸せ…に？"
  },
  {
    "name": "彦麻呂",
    "message": "はい。"
  },
  {
    "name": "雪菜",
    "message": "今の私でも、役に立てるんですか？"
  },
  {
    "name": "彦麻呂",
    "message": "もちろんですよぉ。"
  },
  {
    "name": "雪菜",
    "message": "…。"
  },
  {
    "name": "彦麻呂",
    "message": "だからしたい事をしていいんです。"
  },
  {
    "name": "雪菜",
    "message": "…。"
  },
  {
    "name": "彦麻呂",
    "message": "思ってる事をどうぞぉ。"
  },
  {
    "name": "雪菜",
    "message": "…。"
  },
  {
    "name": "彦麻呂",
    "message": "心の中にある言葉をそのまま口から。"
  },
  {
    "name": "雪菜",
    "message": "…入れたい。"
  },
  {
    "name": "彦麻呂",
    "message": "何をですかぁ？"
  },
  {
    "name": "雪菜",
    "message": "っ、大きくて痛そうだから、そのチンポを入れたい。最初に見た時から、ずっとそう思ってました。"
  },
  {
    "name": "彦麻呂",
    "message": "セックスされる事を望んでるんですねぇ。"
  },
  {
    "name": "雪菜",
    "message": "っ、主人以外の男の人を、知ってみたい。"
  },
  {
    "name": "彦麻呂",
    "message": "なら自分の意志で誘って下さいなぁ。"
  },
  {
    "name": "雪菜",
    "message": "私が…誘う…？"
  },
  {
    "message": "慣れない行為にオドオド。"
  },
  {
    "message": "だけど彼女なりの一生懸命さで。"
  },
  {
    "message": "麻呂の手をギュッと握ってきた。"
  },
  {
    "name": "雪菜",
    "message": "こ、こっち…。"
  },
  {
    "message": "引っ張られる麻呂。"
  },
  {
    "message": "彼女の掌は緊張で汗ばみ。"
  },
  {
    "message": "歩く幅も今までの半分くらいに。"
  },
  {
    "message": "彼女の行き先はさっき座ったテーブル。"
  },
  {
    "message": "言葉の辿々しさそのまま。"
  },
  {
    "message": "卓の上に乗る仕草もかなりぎこちない。"
  },
  {
    "name": "雪菜",
    "message": "ここ…です。"
  },
  {
    "name": "彦麻呂",
    "message": "ここと言われましても。"
  },
  {
    "name": "雪菜",
    "message": "っ、先生のオチンポを、ここに下さい。"
  },
  {
    "name": "彦麻呂",
    "message": "どこにですかぁ？"
  },
  {
    "name": "雪菜",
    "message": "っ、私のオマンコに、です。"
  },
  {
    "name": "彦麻呂",
    "message": "ほほっ…。"
  },
  {
    "name": "雪菜",
    "message": "入れて…入れて…。"
  },
  {
    "message": "言葉はどんどん短くなり。"
  },
  {
    "message": "幼子みたいに目的だけを繰り返す。"
  },
  {
    "message": "それだけ彼女は興奮しており。"
  },
  {
    "message": "熔解し始めた女芯を、どうにも止められない。"
  },
  {
    "name": "雪菜",
    "message": "ら、乱暴なのが…いいです。"
  },
  {
    "name": "彦麻呂",
    "message": "暴力は苦手ですねぇ。"
  },
  {
    "name": "雪菜",
    "message": "っ、言葉だけでかまいません。串刺しにしてやるって。"
  },
  {
    "name": "彦麻呂",
    "message": "では…。"
  },
  {
    "message": "麻呂は息を吸い込み。"
  },
  {
    "message": "芝居がかった声でドスを利かせる。"
  },
  {
    "name": "彦麻呂",
    "message": "串刺しにしてやりますよ。"
  },
  {
    "name": "雪菜",
    "message": "い、いや…やだ…。"
  },
  {
    "name": "彦麻呂",
    "message": "今更そんな事を言っても無駄です。"
  },
  {
    "name": "雪菜",
    "message": "や、やだ、やだぁ…あっちに行って…。"
  },
  {
    "name": "彦麻呂",
    "message": "ほほっ…。"
  },
  {
    "message": "いと犯しぃ。"
  },
  {
    "message": "麻呂は勃起チンポの根元を掴み。"
  },
  {
    "message": "濡れそぼる入り口へ、グイッと突き立てた。"
  },
  {
    "message": "腰を逃がす彼女。"
  },
  {
    "message": "でも潤う窪みは罪深く。"
  },
  {
    "message": "ヌルンッとチンポの先端を導いてしまう。"
  },
  {
    "message": "ぬちゅずるんぐちゅっ。"
  },
  {
    "name": "雪菜",
    "message": "ひゃぁ…はんっ…！！"
  },
  {
    "message": "ずぶずぶずずぶずぶずぶ…ぅ…。"
  },
  {
    "name": "雪菜",
    "message": "あ、あ～～っ、い、いや…大きいっ…裂ける…ぅ。"
  },
  {
    "message": "ずぶっ、ずぶっ、ぐいっ…ずずぶ…ぅ…。"
  },
  {
    "name": "雪菜",
    "message": "はああぁぁぁんっ…も、もう入りません…。"
  },
  {
    "name": "彦麻呂",
    "message": "く…はぁ…。"
  },
  {
    "name": "雪菜",
    "message": "抜いて…抜いて…ぇ…。"
  },
  {
    "message": "言葉とは裏腹。"
  },
  {
    "message": "吸盤みたいに膣壁が吸い付き。"
  },
  {
    "message": "母性そのものに抱き締められてるよう。"
  },
  {
    "message": "麻呂は一瞬で魔法をかけられ。"
  },
  {
    "message": "その温もりの虜となる。"
  },
  {
    "name": "彦麻呂",
    "message": "っ…気持ちいいですぅ。"
  },
  {
    "name": "雪菜",
    "message": "だ、だめ…。"
  },
  {
    "name": "彦麻呂",
    "message": "…は？"
  },
  {
    "name": "雪菜",
    "message": "気持ち良くない、って。"
  },
  {
    "name": "彦麻呂",
    "message": "気持ち良くないぃ。"
  },
  {
    "name": "雪菜",
    "message": "こ、この役立たずって。"
  },
  {
    "name": "彦麻呂",
    "message": "この役立たずぅ。"
  },
  {
    "message": "びくっ。"
  },
  {
    "name": "雪菜",
    "message": "そ、そう…そっちが…いい…。"
  },
  {
    "name": "彦麻呂",
    "message": "旦那さんから常にその言葉を？"
  },
  {
    "name": "雪菜",
    "message": "っ、セックスの最中はあんまり。"
  },
  {
    "name": "彦麻呂",
    "message": "だから欲しいわけですねぇ。"
  },
  {
    "name": "雪菜",
    "message": "…コクリ。"
  },
  {
    "name": "彦麻呂",
    "message": "この役立たず。"
  },
  {
    "name": "雪菜",
    "message": "あぁ…。"
  },
  {
    "name": "彦麻呂",
    "message": "オッパイが大きいだけで、他は何もない女性ですぅ。"
  },
  {
    "name": "雪菜",
    "message": "そ、それ…いい…。"
  },
  {
    "message": "びくっ、びくっ…。"
  },
  {
    "name": "雪菜",
    "message": "ひ…ぅ…。"
  },
  {
    "name": "彦麻呂",
    "message": "オッパイ以外は捨てちゃって下さい。"
  },
  {
    "name": "雪菜",
    "message": "そ、そんなぁ…。"
  },
  {
    "message": "びくびくっ。"
  },
  {
    "name": "彦麻呂",
    "message": "まだブタのほうが役に立ちますねぇ。"
  },
  {
    "name": "雪菜",
    "message": "あぁ…ぁ…。"
  },
  {
    "name": "彦麻呂",
    "message": "違うと言うなら反論して下さいなぁ。"
  },
  {
    "name": "雪菜",
    "message": "っ…。"
  },
  {
    "message": "彼女は何も言わない。"
  },
  {
    "message": "というより言えない。"
  },
  {
    "message": "ただただ目をギュッと閉じ。"
  },
  {
    "message": "意地悪な言葉に身を縮こまらせてた。"
  },
  {
    "name": "彦麻呂",
    "message": "どうやら認めちゃったみたいですねぇ。"
  },
  {
    "name": "雪菜",
    "message": "っ、私は、嘘つきで…ダメ女です。"
  },
  {
    "name": "彦麻呂",
    "message": "何を今さら。"
  },
  {
    "name": "雪菜",
    "message": "ぅ…。"
  },
  {
    "name": "彦麻呂",
    "message": "だから身体で罪を償ってるじゃないですかぁ。"
  },
  {
    "name": "雪菜",
    "message": "身体で…罪を…。"
  },
  {
    "message": "びくっ、びくっ、びくっ…。"
  },
  {
    "message": "剥き身となった秘孔を突かれ。"
  },
  {
    "message": "彼女は精神的なオルガスムを感じてる。"
  },
  {
    "message": "胸の谷間には玉のような汗を浮かべ。"
  },
  {
    "message": "絶頂を迎えた後みたいに肩で息をしてた。"
  },
  {
    "name": "雪菜",
    "message": "そ、それでオシマイですか？"
  },
  {
    "name": "彦麻呂",
    "message": "ほっ…？"
  },
  {
    "name": "雪菜",
    "message": "っ、そっちこそレイプ魔のくせに。"
  },
  {
    "name": "彦麻呂",
    "message": "…。"
  },
  {
    "message": "わざと気色ばみ。"
  },
  {
    "message": "麻呂の演技が萎えないよう下支え。"
  },
  {
    "message": "内助の功とはまさにこの事で。"
  },
  {
    "message": "その心遣いに男心がトロけてしまいそう。"
  },
  {
    "name": "雪菜",
    "message": "っ、口だけなんて、ガッカリです。"
  },
  {
    "name": "彦麻呂",
    "message": "そう思うのは時期尚早かと。"
  },
  {
    "name": "雪菜",
    "message": "嘘つきに、罰一つ与えられない、ボウヤですね。"
  },
  {
    "name": "彦麻呂",
    "message": "どんな意地悪が良いか考えてたんですよぉ。"
  },
  {
    "message": "ずりゅっ…。"
  },
  {
    "name": "雪菜",
    "message": "あ…ぅ…っ…。"
  },
  {
    "name": "彦麻呂",
    "message": "今日は機嫌が良いですから、特別に選ばせてあげますぅ。"
  },
  {
    "message": "できる限り選択権は彼女に。"
  },
  {
    "message": "誰かが望む事をさせるのではなく。"
  },
  {
    "message": "彼女が思う事を麻呂がしてあげたい。"
  },
  {
    "name": "彦麻呂",
    "message": "何がお望みか言って下さいな。"
  },
  {
    "name": "雪菜",
    "message": "わ、私が最も、恥ずかしいと思ってる部分を。"
  },
  {
    "name": "彦麻呂",
    "message": "…このデカすぎるオッパイですねぇ。"
  },
  {
    "name": "雪菜",
    "message": "そこを揺らされるのが、一番、イヤですぅ。"
  },
  {
    "message": "彼女が言い終わるのと同時。"
  },
  {
    "message": "麻呂は腰をグイッとしゃくり。"
  },
  {
    "message": "楔を打ち込むように奥へ突っ込んだ。"
  },
  {
    "name": "雪菜",
    "message": "ひっ！！"
  },
  {
    "message": "乳房がブルンッと揺れ。"
  },
  {
    "message": "子宮口に亀頭がぶち当たった。"
  },
  {
    "message": "グニャッとチンポの胴がしなり。"
  },
  {
    "message": "空気の通り道ができるほど膣道が拡がる。"
  },
  {
    "name": "雪菜",
    "message": "あぁぁぁ…凄い…ですぅ…っ。"
  },
  {
    "message": "本気でビックリした彼女。"
  },
  {
    "message": "結ばれてる部分を改めて目視し。"
  },
  {
    "message": "張り詰め過ぎた膣口に目がまん丸だ。"
  },
  {
    "name": "雪菜",
    "message": "さ、裂けちゃいます。"
  },
  {
    "name": "彦麻呂",
    "message": "ギリギリセーフですねぇ。"
  },
  {
    "name": "雪菜",
    "message": "広がっちゃって、クリトリスも、見えてますぅぅ。"
  },
  {
    "name": "彦麻呂",
    "message": "ですから何でしょう？"
  },
  {
    "name": "雪菜",
    "message": "こ、これじゃ拷問です。"
  },
  {
    "message": "言葉と表情は被虐的なのに。"
  },
  {
    "message": "膣の中は悦びを隠せない。"
  },
  {
    "message": "ウネウネと生き物みたいにのたうち。"
  },
  {
    "message": "本当はもっと酷い仕打ちを待ち望んでる。"
  },
  {
    "name": "彦麻呂",
    "message": "クリを剥かれちゃった気分はどうですかぁ？"
  },
  {
    "name": "雪菜",
    "message": "っ、先生のオチンポが、大きすぎるんです。"
  },
  {
    "name": "彦麻呂",
    "message": "旦那さん以外の男に膣を拡げられて…。"
  },
  {
    "message": "ずぶぅっ…。"
  },
  {
    "name": "雪菜",
    "message": "ひゃっ…あ…っ…！！"
  },
  {
    "name": "彦麻呂",
    "message": "そのうえ乳房をこんなふうに。"
  },
  {
    "message": "ぶるんっ、ぶるんっ、ぱぱんっ、ぱふんっ、ぶるんっ…。"
  },
  {
    "name": "雪菜",
    "message": "あっ…ひっ…んっ…い、いや…弾む…ぅ。"
  },
  {
    "name": "彦麻呂",
    "message": "本当にダメな奥さんですねぇ。"
  },
  {
    "message": "ぱぱんっ、ぶるんっ、ぶるんっ、ぱぱんっ、ぶるんっ、ぶるんっ…。"
  },
  {
    "name": "雪菜",
    "message": "は、恥ずかしい…オッパイ揺れるの…恥ずかしいっ…。"
  },
  {
    "message": "波打つ肉の塊。"
  },
  {
    "message": "張りと柔らかさがグチャグチャとなり。"
  },
  {
    "message": "その弾み具合は暴れウマのよう。"
  },
  {
    "name": "彦麻呂",
    "message": "なんて下品なオッパイなんでしょう。"
  },
  {
    "name": "雪菜",
    "message": "っ、だからイヤなんですぅ。"
  },
  {
    "message": "ぶるんっ、ぶるんっ、ぱぱんっ、ぶるんっ、ぶるんっ…。"
  },
  {
    "name": "雪菜",
    "message": "あぐっ…はあっ…見ないで、先生ぇ…あんっ…はあっ…ひんっ…あっ…あっ…あっ…あぁ…っ…はあっ…はあっ…。"
  },
  {
    "name": "雪菜",
    "message": "ああぁ…お、大きい…先生の、大きい…ひんっ…凄いです…奥まで…前からでも…あぐっ…奥にぃ…届きますぅ…。"
  },
  {
    "message": "ぐりんっ、ぶるんっ、ぶるんっ、ぱぱんっ、ぐりんっ、ぶるんっ…。"
  },
  {
    "name": "雪菜",
    "message": "い、いや…それ…だめ…です。"
  },
  {
    "message": "ぐりんっ、ぐりんっ、ぱぱんっ、ぱぱんっ、ぐりんっ、ぐりんっ…。"
  },
  {
    "name": "雪菜",
    "message": "あひゃぅ…っ…えぁ…っ…ひぃ…だめ…センセ…だめ…そこ…主人に…躾られた…場所ぉ…。"
  },
  {
    "message": "ぐりんっ、ぐりんっ、ぐりんっ、ぐりんっ、ぐりんっ…。"
  },
  {
    "name": "雪菜",
    "message": "あ～～～～～～～～っっ、奥をグリグリされるとっ。"
  },
  {
    "message": "ぐりんっ、ぐりんっ、ぐりんっ、ぐりんっ、ぐりんっ…。"
  },
  {
    "name": "雪菜",
    "message": "グリグリされるとっ、グリグリされると…ぉ。"
  },
  {
    "message": "言葉が途切れ。"
  },
  {
    "message": "口がパクパクアワアワ。"
  },
  {
    "message": "むっちりした下腹が戦慄くように痙攣し。"
  },
  {
    "message": "一定のリズムで腰がヒクヒクしゃくってた。"
  },
  {
    "name": "雪菜",
    "message": "ああぁっ…だ、だめ…イ、イク…先に…だめ…ぇ。"
  },
  {
    "name": "彦麻呂",
    "message": "好きにしていいんですよ。"
  },
  {
    "name": "雪菜",
    "message": "あんっ…はんっ…せ、先生…っ。"
  },
  {
    "name": "彦麻呂",
    "message": "イッちゃいたい時にイッていいんです。"
  },
  {
    "name": "雪菜",
    "message": "そ、そんなの申し訳ないですぅ。"
  },
  {
    "name": "彦麻呂",
    "message": "それも旦那さんの躾ですかぁ？"
  },
  {
    "name": "雪菜",
    "message": "が、我慢できず先にイクと…俺の事を考えてないって…。"
  },
  {
    "name": "彦麻呂",
    "message": "それは逆じゃないですかねぇ。"
  },
  {
    "name": "雪菜",
    "message": "ぎ、ぎゃく…ぅ？"
  },
  {
    "name": "彦麻呂",
    "message": "相手を想う気持ちがあるからこそ、気持ち良くなっちゃうわけですし。"
  },
  {
    "name": "雪菜",
    "message": "そ、そうなんですか？"
  },
  {
    "name": "彦麻呂",
    "message": "私の事を好きと言ってくれましたよね？"
  },
  {
    "name": "雪菜",
    "message": "い、言いましたぁ。"
  },
  {
    "name": "彦麻呂",
    "message": "なら素直にイッて下さいな。"
  },
  {
    "name": "雪菜",
    "message": "ほ、本当に…いいん…ですか？"
  },
  {
    "name": "彦麻呂",
    "message": "かまいません。"
  },
  {
    "name": "雪菜",
    "message": "っ、先生は、おいてきぼりでも？"
  },
  {
    "name": "彦麻呂",
    "message": "はい。"
  },
  {
    "name": "雪菜",
    "message": "謝りながらイッても…許して貰えますか…？"
  },
  {
    "name": "彦麻呂",
    "message": "それでより気持ち良くなれるなら。"
  },
  {
    "name": "雪菜",
    "message": "た、たぶんなっちゃいます。"
  },
  {
    "name": "彦麻呂",
    "message": "それなら雪菜さんの自由です。"
  },
  {
    "name": "雪菜",
    "message": "自由…私の…自由…ぅ。"
  },
  {
    "message": "ぱぱんっ、ぐりんっ、ぱぱんっ、ぐりんっ、ぱぱんっ…っ。"
  },
  {
    "name": "雪菜",
    "message": "ひぃんっ…もっと…奥にぃ…。"
  },
  {
    "message": "麻呂の動きに合わせ。"
  },
  {
    "message": "彼女は自分の腰を前へ突き出す。"
  },
  {
    "message": "奥へ当たる強さが、そのぶんだけ増し。"
  },
  {
    "message": "判子を押すようにグリっと嬲られた。"
  },
  {
    "name": "雪菜",
    "message": "す、すぐイキそうですぅ。"
  },
  {
    "message": "ぐりんっ、ぐりんっ、ぐりんっ、ぐりんっ、ぐりんっ、ぐりんっ…っ。"
  },
  {
    "name": "雪菜",
    "message": "あぐっ…オッパイが大きくてごめんなさいっ…みっともなく揺らしてごめんなさいっ…。"
  },
  {
    "name": "雪菜",
    "message": "け、結婚しててごめんなさいっ…あぐっ…嘘をついててごめんなさいっ…先に、先に、あああぁぁぁぁ…っ。"
  },
  {
    "message": "びくびくびくびくっ。"
  },
  {
    "name": "雪菜",
    "message": "っ、先にイッちゃって、ゴメンナサイッ…。"
  },
  {
    "message": "びっくんっ、びっくんっ…。"
  },
  {
    "name": "雪菜",
    "message": "あ、あ～～～～～っ、気持ちいいですぅ…っ。"
  },
  {
    "message": "びくびくびくびくびくっ。"
  },
  {
    "name": "雪菜",
    "message": "ま、まだ…続く…凄い…っ…先生…凄いぃ…。"
  },
  {
    "name": "彦麻呂",
    "message": "どこが気持ちいいか教えて下さいな。"
  },
  {
    "name": "雪菜",
    "message": "オ、オマンコの奥…雪菜のオマンコ…ぉ。"
  },
  {
    "message": "びくっ…びくっ…びくっ…。"
  },
  {
    "name": "雪菜",
    "message": "あ…く…はぁ…っ…はあっ…はあっ…。"
  },
  {
    "name": "雪菜",
    "message": "くぅ…んっ…はあっ…はあっ…んっ…はあっ…はぁ…っ。"
  },
  {
    "name": "彦麻呂",
    "message": "イキましたかぁ？"
  },
  {
    "name": "雪菜",
    "message": "イ、イキ…まし…たぁ…。"
  },
  {
    "message": "びくっ…び…くっ…。"
  },
  {
    "name": "雪菜",
    "message": "あぁ…っ…はあっ…んっ…はあっ…っ…。"
  },
  {
    "name": "彦麻呂",
    "message": "…では次の幕を開けましょう。"
  },
  {
    "name": "雪菜",
    "message": "ぁ…っ…。"
  },
  {
    "message": "麻呂は彼女を抱きかかえ。"
  },
  {
    "message": "交わったまま足の上へひょいと乗せる。"
  },
  {
    "message": "イッた直後の彼女は何の抗いもできず。"
  },
  {
    "message": "麻呂の身体にしがみつく事しかできない。"
  },
  {
    "message": "ぐにゅう…っ。"
  },
  {
    "name": "雪菜",
    "message": "ひいいぃ…っ。"
  },
  {
    "name": "彦麻呂",
    "message": "いかがですかぁ？"
  },
  {
    "name": "雪菜",
    "message": "く、口からチンポ…出ちゃいます…ぅ。"
  },
  {
    "name": "彦麻呂",
    "message": "確かに深く突き刺さってますねぇ。"
  },
  {
    "name": "雪菜",
    "message": "し、主人と同じ体位はダメですぅ。"
  },
  {
    "name": "彦麻呂",
    "message": "対抗したい気分になってきました。"
  },
  {
    "name": "雪菜",
    "message": "せ、先生のは大きすぎますっ…子宮が持ち上がってますっ…。"
  },
  {
    "message": "ぐにゅっ、ぐにゅっ、ぐにゅっ…。"
  },
  {
    "name": "雪菜",
    "message": "ひゃううぅ…こ、こんなのされたら…主人とできなくなる…ひんっ…身体が変わっちゃう…先生用の膣になっちゃう…ぅ。"
  },
  {
    "message": "ぐにゅっ、ぐにゅっ、ぐにゅっ、ぐにゅっ…。"
  },
  {
    "name": "雪菜",
    "message": "あぐぅっ…だめ…また続けて…イク…っ。"
  },
  {
    "message": "ずりゅっ、ぐにゅっ、ぐにゅっ、ぐにゅっ、ぐにゅっ…。"
  },
  {
    "name": "雪菜",
    "message": "ああぁぁ…気持ちいいのが消えない…ずっとそのままですぅっ…はあっ…はあっ…先生のオチンポって凄い…っ。"
  },
  {
    "name": "彦麻呂",
    "message": "奥さんの膣も素敵ですよぉ。"
  },
  {
    "name": "雪菜",
    "message": "っ、私のは、ダメマンコと言って下さい。"
  },
  {
    "name": "彦麻呂",
    "message": "このダメマンコぉ。"
  },
  {
    "name": "雪菜",
    "message": "誰も悦ばせられない、ダメダメオマンコォ。"
  },
  {
    "name": "彦麻呂",
    "message": "誰も悦ばせられない、ダメダメオマンコォ。"
  },
  {
    "name": "雪菜",
    "message": "だ、だから頑張らないといけないんです。"
  },
  {
    "message": "ずんっ、ずりゅっ、ずんっ、ぐにゅっ、ずんっ…。"
  },
  {
    "name": "雪菜",
    "message": "っ、一生懸命に生きないといけないんですぅ。"
  },
  {
    "message": "ずんっ、ずんっ、ぐにぃ、ずんっ、ずんっ、ずんっ…。"
  },
  {
    "name": "雪菜",
    "message": "あ…ぐっ…せ、先生…ぇ…。"
  },
  {
    "message": "いつの間にか彼女は。"
  },
  {
    "message": "子宮が持ち上がる事も厭わず。"
  },
  {
    "message": "まるで自分自身へ何かを刻み込むように。"
  },
  {
    "message": "自ら麻呂の上で腰を弾ませ始めてた。"
  },
  {
    "message": "ヌルンっとチンポを引き抜き。"
  },
  {
    "message": "ストンと臀部を落とす。"
  },
  {
    "message": "こんな単純な行為だったけど。"
  },
  {
    "message": "奥へ行きつく度に彼女は身体を震わせ。"
  },
  {
    "message": "苦痛と快感の混ざった嬌声を上げてる。"
  },
  {
    "name": "雪菜",
    "message": "はんっ…あっ…あっ…あっ…あぁ…っ…はぁ…んっ…。"
  },
  {
    "message": "大きな乳房は二人の間に挟まれ。"
  },
  {
    "message": "ツンと勃った先端を麻呂の胸板に擦りつけた状態。"
  },
  {
    "message": "繋がる部分から立ち上る匂いも酷く扇情的で。"
  },
  {
    "message": "交わる淫音に負けないくらい生々しい。"
  },
  {
    "name": "雪菜",
    "message": "グ、グリグリしていいですか？"
  },
  {
    "name": "彦麻呂",
    "message": "雪菜さんの自由ですぅ。"
  },
  {
    "name": "雪菜",
    "message": "じ、じゃあ、しますぅ。"
  },
  {
    "message": "腰をズンと落とした彼女。"
  },
  {
    "message": "そこですぐに引き抜かず。"
  },
  {
    "message": "ポルチオで亀頭を優しく愛で始めた。"
  },
  {
    "message": "完全に、いい子、いい子、状態。"
  },
  {
    "message": "肉体以上に心が繋がり。"
  },
  {
    "message": "彼女の膣から悦びの涙が溢れた。"
  },
  {
    "name": "雪菜",
    "message": "し、幸せですぅ。"
  },
  {
    "message": "ぐにっ、ぐりっ、ぐにっ、ぐりっ…。"
  },
  {
    "name": "雪菜",
    "message": "あぁ…溶ける…熱いぃ…。"
  },
  {
    "message": "ぐりっ、ぐりっ、ぐにっ、ぐりっ、ぐりっ…。"
  },
  {
    "name": "雪菜",
    "message": "はぁ…っ…んっ…こ、ここ…いい…凄く…いい…。"
  },
  {
    "message": "腰の位置を微妙にずらし。"
  },
  {
    "message": "最も甘美な部分を探し出す雪菜。"
  },
  {
    "message": "旦那からは一方的に与えられるだけだったけど。"
  },
  {
    "message": "今の彼女は本当のセックスを知り始めてる。"
  },
  {
    "name": "雪菜",
    "message": "す、少し縦に動きますぅ。"
  },
  {
    "message": "ぬぷっ、ずんっ、ぬぷっ、ずんっ、ぬぷっ、ずんっ…。"
  },
  {
    "name": "雪菜",
    "message": "あぁ…こ、これもいい…奥に当たって…痺れてくる…っ。"
  },
  {
    "name": "雪菜",
    "message": "も、もう恐くないです…何でも我慢できる…あんっ…辛い事があったら…先生を思い出して…っ。"
  },
  {
    "message": "びくっ…。"
  },
  {
    "name": "雪菜",
    "message": "ひんっ…思い出して…思い出して…。"
  },
  {
    "message": "びくっ、びくっ、びくっ…。"
  },
  {
    "name": "雪菜",
    "message": "あぁ…ま、また…イッちゃい…ますぅ…。"
  },
  {
    "message": "びくびくっ、びくびくっ…。"
  },
  {
    "name": "雪菜",
    "message": "ああぁ…どうしよう…先生…どうしよう…っ…。"
  },
  {
    "message": "彼女はギュッと身を縮め。"
  },
  {
    "message": "オルガスムを必死に押し戻した。"
  },
  {
    "name": "雪菜",
    "message": "こ、今度は一緒です。"
  },
  {
    "message": "びくびくっ、びくびくっ…きゅうっ…。"
  },
  {
    "name": "雪菜",
    "message": "こ、これはお願いじゃなく、命令ですぅ。"
  },
  {
    "name": "彦麻呂",
    "message": "その言葉を待ってましたぁ。"
  },
  {
    "message": "ぐにゅうっ。"
  },
  {
    "name": "雪菜",
    "message": "ひいっん…。"
  },
  {
    "name": "彦麻呂",
    "message": "命令なら従わないといけませんねぇ。"
  },
  {
    "message": "ぬぷっ、ずんっ、ぬぷっ、ずんっ…。"
  },
  {
    "name": "雪菜",
    "message": "あ、あ～～っ！"
  },
  {
    "name": "彦麻呂",
    "message": "まだイッちゃダメですよぉ。"
  },
  {
    "message": "びくびくびくっ、びくびくびくっ。"
  },
  {
    "name": "雪菜",
    "message": "う～～～っ、だ、だめ…もう…我慢がぁ…。"
  },
  {
    "name": "彦麻呂",
    "message": "奥さんならできます。"
  },
  {
    "name": "雪菜",
    "message": "ひぃ…っ…センセ…もう…本当に…ぃ…。"
  },
  {
    "name": "彦麻呂",
    "message": "何でも乗り越えられますぅ。"
  },
  {
    "message": "ずりゅっ、ずぶぅっ、ぐりんっ、ずりゅっ、ずぶっ、ぐりんっ…っ。"
  },
  {
    "name": "雪菜",
    "message": "ひゃあっ…うっ…オ、オマンコ…くる…っ…。"
  },
  {
    "name": "彦麻呂",
    "message": "ま、まだダメですよぉ。"
  },
  {
    "name": "雪菜",
    "message": "ひっ…はぁっ…あっ…あっ…気持ちいい…も、もうだめっ…身体が浮いて、落ちそう…じ、地面がない…消えちゃった…ぁ。"
  },
  {
    "name": "彦麻呂",
    "message": "どこに出して欲しいですかぁ？"
  },
  {
    "name": "雪菜",
    "message": "っ…最後は…センセ…決めて…下さい…。"
  },
  {
    "message": "びくびくびくっ、びくびくびくっ…。"
  },
  {
    "name": "雪菜",
    "message": "こ、これも…雪菜からの…命令ですぅ…っ。"
  },
  {
    "name": "彦麻呂",
    "message": "…御意ぃ。"
  },
  {
    "message": "このまま膣の中に出す"
  },
  {
    "message": "雪菜の腔内に射精する"
  },
  {
    "name": "彦麻呂",
    "message": "このまま膣の中に出しますぅ。"
  },
  {
    "name": "雪菜",
    "message": "っ…。"
  },
  {
    "message": "無言で頷く彼女。"
  },
  {
    "message": "射精時の一体感が欲しいのか。"
  },
  {
    "message": "首へ巻き付く腕にギュッと力が入る。"
  },
  {
    "name": "彦麻呂",
    "message": "ゴムもつけず出しちゃいますよ。"
  },
  {
    "name": "雪菜",
    "message": "っ…嫌がってもいいですか？"
  },
  {
    "name": "彦麻呂",
    "message": "もちろん。"
  },
  {
    "name": "雪菜",
    "message": "じゃあ…い、いや…中は、いやっ…馬鹿ぁ…っ。"
  },
  {
    "message": "抗いは本心じゃない。"
  },
  {
    "message": "彼女は麻呂を悦ばせたい一心で。"
  },
  {
    "message": "わざと背中をペチペチ叩く。"
  },
  {
    "message": "それでいて弾む腰は激しさを増し。"
  },
  {
    "message": "膣壁も吸盤みたいにチンポへ吸い付かせてた。"
  },
  {
    "message": "ぐぢゅっ、ずぶんっ、ぐりんっ、ぐちゅっ…。"
  },
  {
    "name": "雪菜",
    "message": "ひんっ…結婚してる人に、出しちゃダメです。"
  },
  {
    "name": "彦麻呂",
    "message": "それでも出しちゃうんですねぇ。"
  },
  {
    "message": "ずこっっ、ずりゅっ、ぐりんっ、ずぶぅっ…。"
  },
  {
    "name": "雪菜",
    "message": "ひぃんっ…ヒトデナシぃ…っ…だめっ…だめっ…。"
  },
  {
    "message": "ぐちゅっ、ぐりんっ、ずりゅっ、ぐりんっ、ずぶぅっ…。"
  },
  {
    "name": "雪菜",
    "message": "な、中はやめて…っ…お願いです…はあっ…はあっ…主人に、主人に…叱られますっ…。"
  },
  {
    "name": "雪菜",
    "message": "ああぁぁっっ…本当に中はイヤっ…赤ちゃんできるぅ…はあっ…はあっ…センセ…抜いて、抜いて…オチンポ、抜いてっ…っ。"
  },
  {
    "message": "びくびくびくびくびくっ！"
  },
  {
    "name": "彦麻呂",
    "message": "はう…ぅ…あっ…！"
  },
  {
    "message": "びくびくびくびくびくっ、びくびくびくびくびくっ！"
  },
  {
    "name": "雪菜",
    "message": "ひぃぃっ…オチンポ…ヒクヒク…して…ぇ…っ。"
  },
  {
    "message": "ぎゅううううううううっ、ぎゅううううううううっ！"
  },
  {
    "name": "雪菜",
    "message": "だ、だめ…もう…っ…ゆ、雪菜も…イクうぅぅ…。"
  },
  {
    "name": "雪菜",
    "message": "あんっ…や、やだ…イッちゃうっ…センセ、出して…っ…もうダメ…本当に…本当に…だめぇぇ…っ。"
  },
  {
    "message": "ずびゅううううっ！！"
  },
  {
    "name": "雪菜",
    "message": "ひ…ぅ…っ。"
  },
  {
    "message": "ずびゅっ、ずびゅっ、ずびゅっ、ずびゅっ、ずびゅっ！"
  },
  {
    "name": "彦麻呂",
    "message": "くっ…はぁ…っ。"
  },
  {
    "name": "雪菜",
    "message": "あ～～～っ、出てるぅぅ…ドクドク、出てるぅっ…。"
  },
  {
    "message": "ずびゅっ、ずびゅっ、ずびゅっ、ずびゅっ、ずびゅっ！"
  },
  {
    "name": "雪菜",
    "message": "あ、あ…や、や…私もイッてる…センセと、一緒…っ。"
  },
  {
    "message": "ばびゅっ、ずびゅっ、ばびゅっ、ずびゅっ、ばびゅっ、ずびゅっ！"
  },
  {
    "name": "雪菜",
    "message": "あ、熱くて気持ちいい…っ…先生のドロドロぉ…っ…イッパイ出てる…それがわかりますぅ…。"
  },
  {
    "message": "ばびゅっ、ばびゅっ、ばびゅっ、ばびゅ、ばびゅっ、ばびゅっ！"
  },
  {
    "name": "雪菜",
    "message": "ひいぃ…んっ…凄い…先生の…凄い…っ。"
  },
  {
    "name": "雪菜",
    "message": "こ、こんなに出るの知らない…はあっ…はあっ…オマンコの中、グチュグチュ…だ、だから幸せぇ…凄く幸せです…ぅ。"
  },
  {
    "message": "混ざり合った愛液。"
  },
  {
    "message": "繋がる部分からブクブクと泡立ち。"
  },
  {
    "message": "テーブルの上へトロリと滴る。"
  },
  {
    "message": "その音に彼女は頬を赤らめ。"
  },
  {
    "message": "少女のような恥じらいを見せた。"
  },
  {
    "message": "ずっとこのままでいたい。"
  },
  {
    "message": "だけど時は無情で。"
  },
  {
    "message": "永遠に続く逢瀬など許してはくれない。"
  },
  {
    "name": "彦麻呂",
    "message": "口の中に出しますよぉ。"
  },
  {
    "name": "雪菜",
    "message": "は、はい。"
  },
  {
    "name": "彦麻呂",
    "message": "ナマで私の精液を飲んで下さいなぁ。"
  },
  {
    "name": "雪菜",
    "message": "っ、喜んで飲みますぅ。"
  },
  {
    "message": "ぬるちょっ、ぱっくんっ。"
  },
  {
    "message": "いきなりの深さ。"
  },
  {
    "message": "彼女は躊躇なく喉奥に飲み込み。"
  },
  {
    "message": "じゅぶじゅぶとフェラチオを開始する。"
  },
  {
    "name": "雪菜",
    "message": "じゅぶっ、じゅぼっ…ぬぽぉ…っ…んぐぅ…っ。"
  },
  {
    "message": "チンポを支えてない手は自分の股間へ。"
  },
  {
    "message": "グチョグチョの谷間を掻き分け。"
  },
  {
    "message": "彼女はすぐにクリトリスを探し当てた。"
  },
  {
    "name": "雪菜",
    "message": "んふぅっ…じゅぼっ、じゅぼっ…んぐぅ…じゅぼっ…。"
  },
  {
    "name": "彦麻呂",
    "message": "も、もう出そうですぅ。"
  },
  {
    "name": "雪菜",
    "message": "っ…じゅぼっ…じゅぼっ…んぐっ…じゅぼっ…じゅぼっ…。"
  },
  {
    "name": "彦麻呂",
    "message": "ゆ、雪菜…さん…っ。"
  },
  {
    "name": "雪菜",
    "message": "呼び捨てに…んぐぅっ…して下さい…。"
  },
  {
    "name": "彦麻呂",
    "message": "雪菜ぁ。"
  },
  {
    "name": "雪菜",
    "message": "は、はい…じゅぼっ…じゅぼっ…じゅぼっ…。"
  },
  {
    "name": "彦麻呂",
    "message": "っ、出る…出る…ぅ。"
  },
  {
    "name": "雪菜",
    "message": "んっ…出して下さい…じゅぼっ…じゅぼっ…雪菜の口に…じゅぼっ…じゅぼっ…イッパイ、出して…っ。"
  },
  {
    "name": "彦麻呂",
    "message": "っ、出る…出る…出る…あ～～～～～～っ！！"
  },
  {
    "message": "ずびゅううううっ！！"
  },
  {
    "name": "雪菜",
    "message": "んぐ…ぅ…。"
  },
  {
    "name": "彦麻呂",
    "message": "くっ…はぁ…っ。"
  },
  {
    "message": "ずびゅっ、ずびゅっ、ずびゅっ、ずびゅっ、ずびゅっ！"
  },
  {
    "name": "雪菜",
    "message": "んっ…くっ…ぅ…。"
  },
  {
    "message": "ずびゅっ、ずびゅっ、ずびゅっ、ずびゅっ、ずびゅっ！"
  },
  {
    "name": "雪菜",
    "message": "ん、ん～っ…んぐっ…んんっ…んっっ…。"
  },
  {
    "message": "膣に指を入れた彼女。"
  },
  {
    "message": "出し入れしながらクリトリスを擦り。"
  },
  {
    "message": "ちゃんと射精時にオルガスムを同期させてた。"
  },
  {
    "message": "しゃがんだ格好のまま膝が揺れ。"
  },
  {
    "message": "麻呂に掴まってないと腰が崩れそう。"
  },
  {
    "message": "それでも必死に堪え。"
  },
  {
    "message": "大切な精液は口端から一滴も洩らさない。"
  },
  {
    "message": "ばびゅっ、ずびゅっ、ばびゅっ、ずびゅっ、ばびゅっ、ずびゅっ！"
  },
  {
    "name": "雪菜",
    "message": "んっ…んぐっ…ごくっ…ごくっ…んっ…ごくっ…。"
  },
  {
    "message": "ばびゅっ、ばびゅっ、ばびゅっ、ばびゅ、ばびゅっ、ばびゅっ！"
  },
  {
    "name": "雪菜",
    "message": "ま、まだ出る…んっ…ごくっ…ごくっ…先生の…凄い…っ。"
  },
  {
    "name": "雪菜",
    "message": "こ、こんなに出るの知らない…はあっ…はあっ…匂いも強くて、男らしい…んぐっ…ごくっ…ごくっ…ごっ…くん…。"
  },
  {
    "message": "最後の一滴を鈴口から吸い上げ。"
  },
  {
    "message": "そこでようやくペニスを放した雪菜。"
  },
  {
    "message": "ぬちゅるんっ。"
  },
  {
    "name": "雪菜",
    "message": "んっ…。"
  },
  {
    "message": "当然ながら口の周りはベトベト。"
  },
  {
    "message": "抜け落ちる時の音もイヤらしく。"
  },
  {
    "message": "素に戻った彼女は少女の如く恥じらう。"
  },
  {
    "message": "どちらからともなく腕が伸び。"
  },
  {
    "message": "暫し店の真ん中での抱擁。"
  },
  {
    "message": "ずっとこのままでいたい。"
  },
  {
    "message": "だけど時は無情で。"
  },
  {
    "message": "永遠に続く逢瀬など許してはくれない。"
  },
  {
    "name": "雪菜",
    "message": "あ、あの…。"
  },
  {
    "name": "彦麻呂",
    "message": "はい。"
  },
  {
    "name": "雪菜",
    "message": "本当に、ありがとう…ございました。"
  },
  {
    "message": "そう言って深々とお辞儀。"
  },
  {
    "message": "麻呂は何も言えず。"
  },
  {
    "message": "ただ彼女の姿を目に焼き付けてるだけ。"
  },
  {
    "name": "雪菜",
    "message": "これで…決心をつける事ができます。"
  },
  {
    "message": "再び深々と頭を下げ。"
  },
  {
    "message": "そのまま厨房の奥へ姿を消していく。"
  },
  {
    "message": "ちょっと名残惜しげだったけど。"
  },
  {
    "message": "何かを断ち切る強い意志も感じられた。"
  },
  {
    "name": "彦麻呂",
    "message": "…。"
  },
  {
    "message": "麻呂を見送るのはあまりに辛い。"
  },
  {
    "message": "たぶんそういう事なのだろう。"
  },
  {
    "message": "だからまるで何もなかったように。"
  },
  {
    "message": "店の中を元の静けさに戻して欲しい。"
  },
  {
    "message": "パチッ。"
  },
  {
    "message": "麻呂は照明を落とし。"
  },
  {
    "message": "そのまま引き戸を開けて外へ。"
  },
  {
    "message": "がらがらがら…。"
  },
  {
    "name": "彦麻呂",
    "message": "…。"
  },
  {
    "name": "彦麻呂",
    "message": "…ふぅ。"
  },
  {
    "name": "彦麻呂",
    "message": "…。"
  },
  {
    "name": "彦麻呂",
    "message": "…これで良かったんですかねぇ。"
  },
  {
    "message": "答えの出ない問い掛け。"
  },
  {
    "message": "麻呂は月を仰ぎ見ながら。"
  },
  {
    "message": "暫し店の外で立ち尽くしてた。"
  },
  {
    "message": "ちょっとしたボタンの掛け違いで。"
  },
  {
    "message": "思わぬ方向へ堕ちていくのが人生。"
  },
  {
    "message": "だからこそ立ち入れず。"
  },
  {
    "message": "傍観者でいなければならない時もある。"
  },
  {
    "message": "麻呂は溜息をつき。"
  },
  {
    "message": "トボトボと家路へ。"
  },
  {
    "message": "幸いにも辺りに人影はなく。"
  },
  {
    "message": "背中を丸めていても気にはならない。"
  },
  {
    "message": "麻呂は来た道をそのまま戻り。"
  },
  {
    "message": "変わり映えのない我が家へ帰るだけ。"
  },
  {
    "message": "俯いていても迷子にならず。"
  },
  {
    "message": "退屈だろうが平穏は保証されてる。"
  },
  {
    "message": "だけど太雪亭を閉めるあの二人。"
  },
  {
    "message": "これからどんな道を歩き。"
  },
  {
    "message": "どんな苦難を乗り越えて行くのだろうか…。"
  },
  {
    "message": "雪菜のエピローグを見る"
  },
  {
    "message": "先に進む"
  },
  {
    "message": "御意。"
  },
  {
    "message": "御意。"
  }
]