[
  {
    "message": "…。"
  },
  {
    "message": "先生。"
  },
  {
    "message": "映像はここで途切れ。"
  },
  {
    "message": "唐突な感じで終わっちゃってました。"
  },
  {
    "message": "画面は真っ黒。"
  },
  {
    "message": "その後はノイズすら消え。"
  },
  {
    "message": "早送りしても続きは始まりません。"
  },
  {
    "message": "でも記憶だけはちゃんと残ってます。"
  },
  {
    "message": "確か午後１時を過ぎた頃でしょうか。"
  },
  {
    "message": "襖越しにチャイムの音が聞こえ。"
  },
  {
    "message": "リビングが急に騒がしくなった時の事を…。"
  },
  {
    "message": "ピンポーン。"
  },
  {
    "name": "布施",
    "message": "…。"
  },
  {
    "message": "ピンポーン。"
  },
  {
    "name": "布施",
    "message": "ふぁ…や、やっと帰って…来た？"
  },
  {
    "message": "うたた寝をしてたのか。"
  },
  {
    "message": "布施の声はやたら寝惚けた感じ。"
  },
  {
    "message": "直後にドタドタと足音がして。"
  },
  {
    "message": "遠くからドアの開く音が聞こえてくる。"
  },
  {
    "name": "横山",
    "message": "エラい目に遭ったよ。"
  },
  {
    "name": "布施",
    "message": "ど、どうしたの？"
  },
  {
    "name": "横山",
    "message": "駅前のケーキ屋で、具合が悪くなって。"
  },
  {
    "name": "布施",
    "message": "っ、奥さん、大丈夫…？"
  },
  {
    "name": "咲美",
    "message": "…。"
  },
  {
    "name": "横山",
    "message": "悪いけど布団を敷いてくれるかな。"
  },
  {
    "name": "布施",
    "message": "わ、わかった。"
  },
  {
    "message": "襖が開き。"
  },
  {
    "message": "ようやく僕は事態を飲み込みました。"
  },
  {
    "message": "横山に肩を貸された咲美。"
  },
  {
    "message": "足に力が入っておらず。"
  },
  {
    "message": "一人で歩くのはほぼ無理な状態です。"
  },
  {
    "name": "夫",
    "message": "さ、咲美？"
  },
  {
    "name": "横山",
    "message": "大丈夫ですから。"
  },
  {
    "message": "横山は立ち上がろうとした僕を制し。"
  },
  {
    "message": "早く布団を敷くよう布施を急かします。"
  },
  {
    "message": "そのまま彼女は仰向けに寝かされ。"
  },
  {
    "message": "焦点の合わない視線を天井に。"
  },
  {
    "message": "意識も朦朧としてるのか。"
  },
  {
    "message": "僕が覗き込んでる事さえ気づきません。"
  },
  {
    "name": "布施",
    "message": "っ、どうしてこんな事に？"
  },
  {
    "name": "横山",
    "message": "我慢させすぎちゃいましたね。"
  },
  {
    "name": "布施",
    "message": "我慢って何よ。"
  },
  {
    "name": "横山",
    "message": "俗に言う限界突破ってヤツです。"
  },
  {
    "message": "布施も僕も意味がわからず。"
  },
  {
    "message": "ポカンと横山の顔を見てるだけ。"
  },
  {
    "name": "横山",
    "message": "暫く寝かせれば、戻ると思いますよ。"
  },
  {
    "message": "大して心配する様子もなく。"
  },
  {
    "message": "冷蔵庫からビールを取り出す横山。"
  },
  {
    "message": "その態度に腹も立ちましたけど。"
  },
  {
    "message": "彼の言葉に嘘はありませんでした。"
  },
  {
    "message": "ただ思った以上に時間はかかり。"
  },
  {
    "message": "意識が普通になったのは４時間後。"
  },
  {
    "message": "朦朧とした感じが消え。"
  },
  {
    "message": "天井を見つめる目にも息吹が宿ってます。"
  },
  {
    "name": "横山",
    "message": "…入りますね。"
  },
  {
    "message": "襖が開き。"
  },
  {
    "message": "その隙間から横山の顔が。"
  },
  {
    "message": "邪魔をされた気分にもなりましたが。"
  },
  {
    "message": "今は文句を言う権利などない僕です。"
  },
  {
    "name": "横山",
    "message": "大丈夫ですか？"
  },
  {
    "name": "咲美",
    "message": "…。"
  },
  {
    "message": "黙って頷く彼女。"
  },
  {
    "message": "横山に対して怒ってる様子もなく。"
  },
  {
    "message": "懸命に記憶を巻き戻してる感じでした。"
  },
  {
    "name": "横山",
    "message": "お風呂を入れておきました。"
  },
  {
    "name": "咲美",
    "message": "…。"
  },
  {
    "name": "横山",
    "message": "湯船に浸かればスッキリしますよ。"
  },
  {
    "message": "手を差し伸べられ。"
  },
  {
    "message": "咲美はその優しさを受け容れます。"
  },
  {
    "message": "彼女は僕の側からいなくなり。"
  },
  {
    "message": "また一人の時間が過ぎていくだけです。"
  },
  {
    "message": "そして３０分後。"
  },
  {
    "message": "彼女が浴室から出て来た時。"
  },
  {
    "message": "横山は脱衣所でカメラを待ち構え。"
  },
  {
    "message": "パジャマに着替える事を許しません。"
  },
  {
    "name": "咲美",
    "message": "…。"
  },
  {
    "name": "横山",
    "message": "だいぶ顔色も良くなりましたね。"
  },
  {
    "name": "咲美",
    "message": "…すぐ始めるんですか？"
  },
  {
    "name": "横山",
    "message": "もう外は暗くなってしまいました。明日の朝になれば散会ですし、今夜しかチャンスがないので。"
  },
  {
    "name": "咲美",
    "message": "…わかってます。"
  },
  {
    "name": "横山",
    "message": "もう私のサポートは期待しないように。契約を成立させるかは、奥さんが決めて下さい。"
  },
  {
    "name": "咲美",
    "message": "…。"
  },
  {
    "name": "横山",
    "message": "準備だけはしておきましたから。"
  },
  {
    "name": "咲美",
    "message": "…。"
  },
  {
    "name": "横山",
    "message": "布施さんの相手をしないと、これから先はないですよ。"
  },
  {
    "name": "咲美",
    "message": "…。"
  },
  {
    "name": "横山",
    "message": "どうしますか？"
  },
  {
    "name": "咲美",
    "message": "…やります。"
  },
  {
    "name": "咲美",
    "message": "ぅ…。"
  },
  {
    "name": "布施",
    "message": "今度こそ宜しく。"
  },
  {
    "name": "咲美",
    "message": "っ…。"
  },
  {
    "name": "横山",
    "message": "口を開けないと始まりません。"
  },
  {
    "name": "咲美",
    "message": "く、口を…。"
  },
  {
    "name": "横山",
    "message": "自分からペニスを含むんです。"
  },
  {
    "name": "咲美",
    "message": "っ、口を…口を…。"
  },
  {
    "name": "布施",
    "message": "早くぅ。"
  },
  {
    "name": "横山",
    "message": "奥さんの意志に任せて下さい。"
  },
  {
    "name": "布施",
    "message": "はーい。"
  },
  {
    "name": "咲美",
    "message": "む…。"
  },
  {
    "name": "横山",
    "message": "…。"
  },
  {
    "name": "布施",
    "message": "ドキドキしてきた♪"
  },
  {
    "name": "咲美",
    "message": "ぅ…ぅ…。"
  },
  {
    "name": "布施",
    "message": "長年の夢が叶うなんて。"
  },
  {
    "name": "咲美",
    "message": "や、やっぱり…。"
  },
  {
    "name": "横山",
    "message": "…無理ですか？"
  },
  {
    "name": "咲美",
    "message": "っ…。"
  },
  {
    "name": "横山",
    "message": "…私が手伝える事は、これが最後ですよ。"
  },
  {
    "message": "横山は立ち上がり。"
  },
  {
    "message": "真っ暗な和室の中へ。"
  },
  {
    "message": "何やら話声がこしょこしょ聞こえ。"
  },
  {
    "message": "そのまま旦那を伴い戻ってきた。"
  },
  {
    "name": "咲美",
    "message": "ぁ…。"
  },
  {
    "name": "夫",
    "message": "さ、咲美…。"
  },
  {
    "name": "横山",
    "message": "旦那さんにも契約を履行して頂きます。責任を持って奥さんを貸し出す事は、覚え書きにも明記してあるんですから。"
  },
  {
    "name": "夫",
    "message": "っ、咲美の前に僕以外のチンポが…。"
  },
  {
    "name": "横山",
    "message": "ここで何もしなければ、本当の木偶の坊ですよ。"
  },
  {
    "name": "夫",
    "message": "わ、わかってます。"
  },
  {
    "name": "横山",
    "message": "これがアナタの望んだ事でしょう？"
  },
  {
    "name": "夫",
    "message": "っ、僕が望んだのは襖越しに…。"
  },
  {
    "name": "横山",
    "message": "目の前で見て臆しましたか？"
  },
  {
    "name": "夫",
    "message": "っ、想像してたのと少し違ってて…。"
  },
  {
    "name": "横山",
    "message": "今さら何を言ってるんですか。"
  },
  {
    "name": "夫",
    "message": "す、すみません。"
  },
  {
    "name": "横山",
    "message": "旦那さんから奥さんを説得して下さい。"
  },
  {
    "name": "夫",
    "message": "さ、咲美。"
  },
  {
    "name": "咲美",
    "message": "っ…なに？"
  },
  {
    "name": "夫",
    "message": "だから、あの…その…。"
  },
  {
    "message": "ぶー、ぶー、ぶー。"
  },
  {
    "name": "布施",
    "message": "は？"
  },
  {
    "name": "横山",
    "message": "…。"
  },
  {
    "name": "夫",
    "message": "け、携帯？"
  },
  {
    "name": "横山",
    "message": "そのまま動かないで下さい。"
  },
  {
    "message": "再び横山は立ち上がり。"
  },
  {
    "message": "バイブ音が聞こえる洋間の中へ。"
  },
  {
    "message": "待ち時間はほとんど無く。"
  },
  {
    "message": "一息つく隙間も彼女に与えられない。"
  },
  {
    "name": "横山",
    "message": "…奥さん以外は喋らないように。"
  },
  {
    "message": "ピッ。"
  },
  {
    "name": "咲美",
    "message": "ぁ…。"
  },
  {
    "message": "いきなり耳へ押し当てられ。"
  },
  {
    "message": "今まで以上に咲美の顔が強張った。"
  },
  {
    "name": "咲美",
    "message": "も、もしもし？"
  },
  {
    "name": "彦麻呂",
    "message": "奥さんですかぁ？"
  },
  {
    "name": "咲美",
    "message": "あ…先生…。"
  },
  {
    "name": "彦麻呂",
    "message": "昨夜はどうしたんでしょう？"
  },
  {
    "name": "咲美",
    "message": "な、何が？"
  },
  {
    "name": "彦麻呂",
    "message": "メールの内容が妙だったので、何回か、電話を差し上げたんですが。"
  },
  {
    "name": "咲美",
    "message": "っ、出られなくてゴメン。"
  },
  {
    "name": "彦麻呂",
    "message": "何か込み入った事情でも？"
  },
  {
    "name": "咲美",
    "message": "実はマー君と揉めちゃって。センセーも知ってる、隠しカメラの件で。"
  },
  {
    "name": "彦麻呂",
    "message": "メールを送るほどの、大喧嘩になったとか？"
  },
  {
    "name": "咲美",
    "message": "け、けっこうハデに。"
  },
  {
    "name": "彦麻呂",
    "message": "まさか殴り合いまで…。"
  },
  {
    "name": "咲美",
    "message": "さ、さすがにそれはない。"
  },
  {
    "name": "彦麻呂",
    "message": "それで私にヘルプをしたと？"
  },
  {
    "name": "咲美",
    "message": "っ、熱くなってる最中だったから、書いてる途中で送っちゃって。"
  },
  {
    "name": "彦麻呂",
    "message": "そうだったんですかぁ。"
  },
  {
    "name": "咲美",
    "message": "心配かけてゴメンね。"
  },
  {
    "name": "彦麻呂",
    "message": "大事でないのなら、それで良いですが。"
  },
  {
    "name": "咲美",
    "message": "仲裁に入って貰おうと思ったけど、そのあとマー君も落ち着いてくれた。今も、ちょっとだけギクシャクしてるけど。"
  },
  {
    "name": "彦麻呂",
    "message": "取り敢えずおさまったわけですねぇ。"
  },
  {
    "name": "咲美",
    "message": "うん。"
  },
  {
    "name": "彦麻呂",
    "message": "…？"
  },
  {
    "name": "咲美",
    "message": "なに？"
  },
  {
    "name": "彦麻呂",
    "message": "近くにどなたかいますか？"
  },
  {
    "name": "咲美",
    "message": "マー君がいる。"
  },
  {
    "name": "彦麻呂",
    "message": "今日はお休みなんですねぇ。"
  },
  {
    "name": "咲美",
    "message": "マ、マー君と話す？"
  },
  {
    "name": "彦麻呂",
    "message": "今は遠慮しておきますぅ。"
  },
  {
    "name": "咲美",
    "message": "っ、これから、ちょうど、御飯なんだ。"
  },
  {
    "name": "彦麻呂",
    "message": "これは失礼しました。"
  },
  {
    "name": "咲美",
    "message": "今度は、こっちから電話するよ。先生も忙しいだろうけど、身体に気を付けて頑張って。"
  },
  {
    "name": "彦麻呂",
    "message": "お気遣いに感謝ですぅ。それでは、また今度。"
  },
  {
    "message": "ピッ。"
  },
  {
    "name": "咲美",
    "message": "…。"
  },
  {
    "name": "横山",
    "message": "親しそうな方ですね。"
  },
  {
    "name": "咲美",
    "message": "べ、別に。"
  },
  {
    "name": "横山",
    "message": "昨日から何度も何度も、かけられてるようです。"
  },
  {
    "name": "咲美",
    "message": "っ…普通の知り合い。"
  },
  {
    "name": "横山",
    "message": "そうですか。"
  },
  {
    "name": "咲美",
    "message": "…携帯の電源を切って欲しい。"
  },
  {
    "name": "横山",
    "message": "ペニスをしゃぶる覚悟を決めたのなら。"
  },
  {
    "name": "咲美",
    "message": "…。"
  },
  {
    "name": "横山",
    "message": "これから御飯なんですよね？"
  },
  {
    "name": "布施",
    "message": "…俺も同じ事を思ってたぁ。"
  },
  {
    "name": "横山",
    "message": "食べないんですか？"
  },
  {
    "name": "咲美",
    "message": "ぅ…っ…。"
  },
  {
    "name": "布施",
    "message": "俺のソーセージは美味しいよん♪"
  },
  {
    "name": "咲美",
    "message": "っ、ソーセージは嫌い。"
  },
  {
    "name": "横山",
    "message": "旦那さんからも、お願いしますよ。"
  },
  {
    "name": "夫",
    "message": "ぼ、僕…？"
  },
  {
    "name": "横山",
    "message": "盗撮の話を公にします？"
  },
  {
    "name": "夫",
    "message": "さ、咲美。"
  },
  {
    "name": "咲美",
    "message": "っ、何も聞きたくない。"
  },
  {
    "name": "夫",
    "message": "そ、そんな…。"
  },
  {
    "name": "咲美",
    "message": "っ、マー君だって知ってるよね。私がソーセージを嫌いなのは。"
  },
  {
    "name": "夫",
    "message": "咲美は好き嫌いのないのが自慢で…。"
  },
  {
    "name": "咲美",
    "message": "な、なんでそういう事を言うの？"
  },
  {
    "name": "夫",
    "message": "…だって本当の事じゃないか。"
  },
  {
    "name": "咲美",
    "message": "っ、今日から嫌いになった。"
  },
  {
    "name": "夫",
    "message": "そ、そんな事を言わないでよ。"
  },
  {
    "name": "咲美",
    "message": "…。"
  },
  {
    "name": "夫",
    "message": "嫌わずに食べて。"
  },
  {
    "name": "咲美",
    "message": "っ、本気で言ってる？"
  },
  {
    "name": "夫",
    "message": "そのソーセージを食べて。"
  },
  {
    "name": "咲美",
    "message": "わ、私は、あなたの奥さんなんだよ。"
  },
  {
    "name": "夫",
    "message": "っ、今は横山さんと布施さんに貸してるんだ。"
  },
  {
    "name": "咲美",
    "message": "ぃ…ゃ…。"
  },
  {
    "name": "夫",
    "message": "っ、お願いだからフェラチオをして。"
  },
  {
    "name": "咲美",
    "message": "ぃ、ぃゃ…。"
  },
  {
    "name": "夫",
    "message": "っ、布施さんのチンポを咥えてあげてよ。"
  },
  {
    "name": "咲美",
    "message": "ぃゃ…ぃゃ…。"
  },
  {
    "name": "夫",
    "message": "そ、そうしてる姿を僕は見たいんだ。"
  },
  {
    "name": "咲美",
    "message": "マ、マー君の馬鹿。"
  },
  {
    "name": "夫",
    "message": "このままだと契約不履行になっちゃうぅ。"
  },
  {
    "name": "咲美",
    "message": "マー君の馬鹿っ…マー君の馬鹿っ…。"
  },
  {
    "name": "咲美",
    "message": "マー君の馬鹿ぁぁ…はむんっ…うぐっ…げぇ…っ。"
  },
  {
    "name": "布施",
    "message": "うひょぉ…ぉ。"
  },
  {
    "name": "夫",
    "message": "あ、あ～～っ、ちょっと待って、やっぱり待って、咲美ぃぃっ。"
  },
  {
    "message": "馬鹿な僕をぶん殴る"
  },
  {
    "message": "馬鹿な僕をぶん殴る"
  },
  {
    "message": "馬鹿な僕をぶん殴る"
  },
  {
    "message": "馬鹿な僕をぶん殴る"
  },
  {
    "message": "当然です。"
  },
  {
    "message": "そう思われて当然です。"
  },
  {
    "message": "殴って下さい。"
  },
  {
    "message": "僕のした事は万死に値し。"
  },
  {
    "message": "１００万発殴られても罪は晴れません。"
  },
  {
    "message": "妻を犠牲にして自分を守る。"
  },
  {
    "message": "僕は馬鹿でした。"
  },
  {
    "message": "木偶の坊にもなれない大馬鹿でした。"
  },
  {
    "name": "布施",
    "message": "咥えるだけぇ？"
  },
  {
    "name": "咲美",
    "message": "んぐっ…くちゅっ…んぐっ…。"
  },
  {
    "name": "布施",
    "message": "そ、そうっっ、そうだよ…奥さん…。"
  },
  {
    "name": "咲美",
    "message": "んぐっ…んぐっ…んぐっ…くちゅっ…んぐっ…。"
  },
  {
    "name": "布施",
    "message": "もっと、もっと、深く…亀頭の下も舐めて…そうっ、そうっ。"
  },
  {
    "name": "咲美",
    "message": "んぐっ…んぐっ…ぺろっ、ぺろっ…んぐっ…んぐっ…ちゅぱっ…んぐっ…。"
  },
  {
    "name": "夫",
    "message": "咲美ぃ…咲美ぃ…。"
  },
  {
    "message": "非道すぎる夫の言葉に心が折れ。"
  },
  {
    "message": "そこからの咲美は別人になってしまいました。"
  },
  {
    "message": "僕のほうへは一瞥もくれず。"
  },
  {
    "message": "あれだけ嫌がってた布施のペニスを口に咥え。"
  },
  {
    "message": "取り方によっては見せつけるように。"
  },
  {
    "message": "僕にした事ないくらい、喉奥へ飲み込むんです。"
  },
  {
    "message": "あの可憐な唇で肉胴をズリズリと擦り。"
  },
  {
    "message": "唇の端からヨダレが垂れる事も厭わず。"
  },
  {
    "message": "ジュブジュブと下品な音をさせ。"
  },
  {
    "message": "布施から嬌声を簡単に引き出してました。"
  },
  {
    "name": "布施",
    "message": "ひゃっ…す、凄い…奥さん…凄いよ…。"
  },
  {
    "name": "咲美",
    "message": "んぐっ…ぐちゅっ…んぐっ…んぐっ…。"
  },
  {
    "name": "布施",
    "message": "く…は…ぁ…っ。"
  },
  {
    "name": "咲美",
    "message": "んぐっ…ちゅぱっ…んぐっ…んぐっ…んぐっ…んぐっ…。"
  },
  {
    "name": "咲美",
    "message": "んんっ…ちゅうっ…ちゅぱっ…んぐっ…んぐっ…んぐっ…ちゅぱっ…んぐっ…んっ…んっ…んぐっ…ぅ。"
  },
  {
    "name": "咲美",
    "message": "くちゅうっ…ぺろっ…んぐっ…ちゅうっ…ちゅぱっ…んぐっ…ぺろっ…んぐっ…ちゅぱっ…なめっ…なめっ…んぐっ…んっ…んっ。"
  },
  {
    "name": "布施",
    "message": "いいよっ、いいよっ…凄く、いいよっ。"
  },
  {
    "message": "あれだけ妻の意志に任せると言ったのに。"
  },
  {
    "message": "いつの間にかそのルールは済し崩しとなり。"
  },
  {
    "message": "布施は玉を舐めろだの。"
  },
  {
    "message": "竿を同時にシゴけだの。"
  },
  {
    "message": "あらゆるリクエストが横行し。"
  },
  {
    "message": "それを傍らの横山は止めもしません。"
  },
  {
    "message": "ただ一つだけ気になった事はありました。"
  },
  {
    "message": "何故か横山は一回だけ舌打ちをし。"
  },
  {
    "message": "ちょっと後悔するような態度を見せたんです。"
  },
  {
    "message": "その後は表情一つ替えずに行為を撮影し。"
  },
  {
    "message": "そうかと思えばソッポを向いたりもしてます。"
  },
  {
    "message": "だから布施はますますやり放題。"
  },
  {
    "message": "閉じていた妻の腿を開くよう頼み。"
  },
  {
    "message": "それだけでは飽き足らず、指で淫唇を拡げろとまで。"
  },
  {
    "message": "何よりショックだったのが妻の対応でした。"
  },
  {
    "message": "躊躇いもなく命令に従い。"
  },
  {
    "message": "娼婦のように腿を開いてしまったんです。"
  },
  {
    "message": "続けて指で淫唇を拡げ。"
  },
  {
    "message": "内側の桜肉を惜しげもなく晒してしまいます。"
  },
  {
    "name": "夫",
    "message": "ど、どうして？"
  },
  {
    "message": "身体が震えました。"
  },
  {
    "message": "簡単に性器を晒した事はもちろん。"
  },
  {
    "message": "その内側がグショグショだった事に。"
  },
  {
    "message": "妻は明らかに濡れてました。"
  },
  {
    "message": "見てわかるくらいだから相当にです。"
  },
  {
    "message": "普段は隠れてるクリトリスも頭をもたげ。"
  },
  {
    "message": "淫唇を押し退けるほど勃起してます。"
  },
  {
    "message": "これが本当に咲美？"
  },
  {
    "message": "性に対して奥手だった彼女？"
  },
  {
    "message": "そうやって自問自答を繰り返してる間。"
  },
  {
    "message": "妻は薄汚い玉袋をペロペロ舐め始めます。"
  },
  {
    "message": "疎らに生えた陰毛ごと口に含み。"
  },
  {
    "message": "ソープ嬢のような行為でも躊躇いはありません。"
  },
  {
    "name": "咲美",
    "message": "んっ…ぺろっ…くちゅ…んっ…んっ…。"
  },
  {
    "message": "奴隷の如く布施のリクエストに従い。"
  },
  {
    "message": "妻は何でもしてしまう淫婦に。"
  },
  {
    "message": "受け身側としても同様で。"
  },
  {
    "message": "乳房をギュッと掴まれても文句一つ言わず。"
  },
  {
    "message": "シコった先端を引っ張られようが、手を払うそぶりすらないんです。"
  },
  {
    "message": "自暴自棄。"
  },
  {
    "message": "そうとも取れるでしょう。"
  },
  {
    "message": "でも彼女の桜色に染まった頬を見てると。"
  },
  {
    "message": "僕はそれだけじゃない気がしてしまいます。"
  },
  {
    "message": "興奮してるんじゃないか？"
  },
  {
    "message": "本当は興味津々だったんじゃないか？"
  },
  {
    "message": "僕以外の男に。"
  },
  {
    "message": "僕以外のペニスに。"
  },
  {
    "name": "夫",
    "message": "っ…。"
  },
  {
    "message": "心臓が早鐘のように鳴り。"
  },
  {
    "message": "今にも口から出てきそうです。"
  },
  {
    "message": "なのに僕の股間は膨らみ。"
  },
  {
    "message": "それを気づかれないかと慌ててました。"
  },
  {
    "message": "こんな時でも自分の見栄が優先。"
  },
  {
    "message": "だから横山に気づかれないよう手を動かし。"
  },
  {
    "message": "チンポの位置を誤魔化そうとした時です…。"
  },
  {
    "message": "どびゅっう！！"
  },
  {
    "name": "咲美",
    "message": "ふぁ…っ…。"
  },
  {
    "message": "布施は唐突に果てました。"
  },
  {
    "message": "それが口腔で射精する口実なのか。"
  },
  {
    "message": "自分でも予期せず出ちゃったのか。"
  },
  {
    "message": "とにかく大量に精液は迸り。"
  },
  {
    "message": "紅潮した彼女の頬を膨らませます。"
  },
  {
    "name": "夫",
    "message": "ぁ…。"
  },
  {
    "message": "息をする事も忘れ。"
  },
  {
    "message": "行く末を見守る僕。"
  },
  {
    "message": "頭の中で覚え書きのページをめくり。"
  },
  {
    "message": "この場合の約束事を必死に思い出してました。"
  },
  {
    "name": "咲美",
    "message": "んん…んぷっ…んっ…。"
  },
  {
    "message": "布施はペニスを抜きません。"
  },
  {
    "message": "たぶんワザとです。"
  },
  {
    "message": "少しずつ少しずつ精液は喉奥へ流れ。"
  },
  {
    "message": "反射的に彼女は嚥下をするしかない状況に。"
  },
  {
    "name": "咲美",
    "message": "んぐっ…んっ…ごくっ…んんっ…ごくっ…ごくっ…。"
  },
  {
    "name": "布施",
    "message": "奥さぁん…。"
  },
  {
    "name": "咲美",
    "message": "ごくっ…ごくっ…んっ…ごくっ…ごくっ…んっ…ごくっ…。"
  },
  {
    "name": "夫",
    "message": "さ、咲美…。"
  },
  {
    "message": "飲んでしまいました。"
  },
  {
    "message": "僕の目の前で。"
  },
  {
    "message": "いかにも濃そうな布施の精液を。"
  },
  {
    "message": "それもゴクゴクと喉を鳴らしながら。"
  },
  {
    "message": "僕は軽い目眩を感じ。"
  },
  {
    "message": "勃起してたチンポも力無く縮みます。"
  },
  {
    "message": "だけど射精した布施は真逆で。"
  },
  {
    "message": "萎えを知らぬ性豪のようでした。"
  },
  {
    "message": "肉胴には太い血管を浮き上がらせたまま。"
  },
  {
    "message": "精飲した妻の顔を嬉しそうに眺めてます。"
  },
  {
    "message": "どうして横山が布施を誘ったのか。"
  },
  {
    "message": "この時に僕は思い知りました。"
  },
  {
    "name": "布施",
    "message": "…まだ序の口だよ。"
  },
  {
    "message": "いきなり布施は咲美をダッコ。"
  },
  {
    "message": "濡れそぼる股間がこっちに向けられ。"
  },
  {
    "message": "僕は目を背ける事しかできません。"
  },
  {
    "message": "たぶん妻は初めてではないでしょうか。"
  },
  {
    "message": "ああやって男に抱きかかえられ。"
  },
  {
    "message": "お姫様みたいに運ばれるのは。"
  },
  {
    "message": "ひ弱な僕には無理な話で。"
  },
  {
    "message": "しようと思った事すらないです。"
  },
  {
    "name": "咲美",
    "message": "…。"
  },
  {
    "message": "相変わらず咲美はされるがまま。"
  },
  {
    "message": "ダランとぶら下がった腕が物悲しく。"
  },
  {
    "message": "でも僕はそれを見てるだけの馬鹿。"
  },
  {
    "name": "布施",
    "message": "今度はセックスしようね。"
  },
  {
    "message": "布施の言葉。"
  },
  {
    "message": "予期してた事とは言え。"
  },
  {
    "message": "身体中の汗が一気に冷えました。"
  },
  {
    "message": "行き先はリビングのソファー。"
  },
  {
    "message": "僕と咲美が幾度となく語り合い。"
  },
  {
    "message": "キスやイチャイチャもしたあの場所です。"
  },
  {
    "message": "そこで遠慮の欠片もなく。"
  },
  {
    "message": "布施は妻の足を拡げ。"
  },
  {
    "message": "芋虫みたいな指で濡れ具合を確認し。"
  },
  {
    "message": "未だ精液の滲む鈴口を妻の割れ目に…。"
  },
  {
    "name": "横山",
    "message": "…布施さん。"
  },
  {
    "name": "布施",
    "message": "なに？"
  },
  {
    "name": "横山",
    "message": "避妊具を忘れてる。"
  },
  {
    "name": "布施",
    "message": "あ、ああ…そっか…ゴメン。"
  },
  {
    "message": "横山の言葉に胸を撫で下ろし。"
  },
  {
    "message": "僕はホッと安堵の溜息をついてます。"
  },
  {
    "message": "これは覚え書きにも明記してある事で。"
  },
  {
    "message": "避妊具の着用は譲れない条件だからです。"
  },
  {
    "name": "布施",
    "message": "ちょっと大きくなぁい？"
  },
  {
    "name": "横山",
    "message": "ＸＬだから。"
  },
  {
    "name": "布施",
    "message": "なんでそんな…。"
  },
  {
    "message": "嫌がらせだと思ったのか。"
  },
  {
    "message": "布施は珍しく不満そうな顔。"
  },
  {
    "message": "それでも先端にペトッと被せ。"
  },
  {
    "message": "クルクルと根元まで包み込んでます。"
  },
  {
    "name": "咲美",
    "message": "…。"
  },
  {
    "message": "そうしてる間も咲美は無表情。"
  },
  {
    "message": "天井をじっと見つめて、ピクリとも動きません。"
  },
  {
    "name": "横山",
    "message": "旦那さんもこちらへどうぞ。"
  },
  {
    "name": "夫",
    "message": "ぅ…。"
  },
  {
    "message": "横山から促され。"
  },
  {
    "message": "僕もソファーの傍らへ移動。"
  },
  {
    "message": "妻はその事を気にもせず。"
  },
  {
    "message": "チラリとも僕を見てくれないのです。"
  },
  {
    "name": "布施",
    "message": "今度こそ♪"
  },
  {
    "message": "仕切直し。"
  },
  {
    "message": "再び咲美の足を拡げ。"
  },
  {
    "message": "たぎるペニスの根元を握り締める布施。"
  },
  {
    "message": "そのまま暫し妻の性器を観察し。"
  },
  {
    "message": "当たりをつけた場所に先端を押し付けます。"
  },
  {
    "message": "それも僕に見せつけるよう。"
  },
  {
    "message": "彼女の腰をぐいっと持ち上げて。"
  },
  {
    "name": "咲美",
    "message": "ぁ…。"
  },
  {
    "message": "ビクッと妻の身体が震え。"
  },
  {
    "message": "怯えたように肩を窄めました。"
  },
  {
    "message": "この時の咲美はどんな気持ちだったのか。"
  },
  {
    "message": "自分が原因を作った事とは言え。"
  },
  {
    "message": "やはり慚愧の思いを禁じ得ません。"
  },
  {
    "name": "布施",
    "message": "…入れるよ、奥さぁん。"
  },
  {
    "message": "ぐにゅうっ、ずぶぅぅ…。"
  },
  {
    "name": "咲美",
    "message": "ああぁ…ぁぁ…。"
  },
  {
    "message": "ついに布施は挿入。"
  },
  {
    "message": "あの薄汚いペニスを、妻である咲美の中へ。"
  },
  {
    "message": "まるで自分の所有物であるかのように。"
  },
  {
    "message": "無遠慮にズブズブめり込ませていきます。"
  },
  {
    "message": "何度か途中で行き止まり。"
  },
  {
    "message": "その窮屈さが布施の顔を綻ばせる事に。"
  },
  {
    "message": "ニタついた顔でペニスを少しだけ戻し。"
  },
  {
    "message": "より深く侵入させるキッカケを掴もうとしてます。"
  },
  {
    "message": "だんだん咲美と一つになっていく過程。"
  },
  {
    "message": "それを間近で見せつけられ。"
  },
  {
    "message": "僕は呻き声一つ出す事ができなかった。"
  },
  {
    "message": "息が詰まるぐらい衝撃的で。"
  },
  {
    "message": "少し前から頭の中が真っ白に。"
  },
  {
    "name": "咲美",
    "message": "う…く…っ…。"
  },
  {
    "message": "さすがに彼女も無表情ではいられず。"
  },
  {
    "message": "侵入してくる圧力に表情を歪ませてました。"
  },
  {
    "message": "もちろん僕が自分のチンポを入れる時より。"
  },
  {
    "message": "ずっとずっと悩ましげな感じで。"
  },
  {
    "message": "ぐちゅっ…ぐちゅっ…。"
  },
  {
    "name": "布施",
    "message": "ああっ、いいね…これ、いいよ…。"
  },
  {
    "message": "ぐちゅっ…ぐちゅっ…ぐちゅっ…。"
  },
  {
    "name": "布施",
    "message": "凄く、いい…奥さんの、凄く、窮屈だよ…。"
  },
  {
    "message": "在り来たりな褒め言葉。"
  },
  {
    "message": "だけど布施の顔は本当に幸せそうで。"
  },
  {
    "message": "それが嘘偽りない感想だとわかります。"
  },
  {
    "message": "彼はその悦びを伝えるよう腰を揺すり。"
  },
  {
    "message": "場数を踏んだねちっこい動きで、咲美の反応を楽しみ始めました。"
  },
  {
    "name": "夫",
    "message": "ぁ…ぁ…。"
  },
  {
    "message": "セックスされてます。"
  },
  {
    "message": "妻が僕以外の男に。"
  },
  {
    "message": "ぶっといチンポを入れられ。"
  },
  {
    "message": "オッパイがブルンブルン揺れてます。"
  },
  {
    "message": "僕は呆然と見てました。"
  },
  {
    "message": "おぞましすぎるその接点を。"
  },
  {
    "message": "出入りするペニスは表面がヌラヌラ光り。"
  },
  {
    "message": "湿ったイヤらしい音も僕の耳に。"
  },
  {
    "message": "でもまだ良かったんです。"
  },
  {
    "message": "聞こえてくるのは、それだけでしたから。"
  },
  {
    "message": "だけどいつからでしょう。"
  },
  {
    "message": "妻の口から切なげな声が漏れ。"
  },
  {
    "message": "腰から下を淫靡に捩り始めたのは。"
  },
  {
    "name": "布施",
    "message": "おぉ…。"
  },
  {
    "message": "布施の顔は更に綻び。"
  },
  {
    "message": "腰の動きもますますリズミカルに。"
  },
  {
    "message": "妻はズンズンと膣の奥を突かれ。"
  },
  {
    "message": "その度に下腹をヒクヒク痙攣させてます。"
  },
  {
    "message": "ペニスの埋没はズッポリ根元まで。"
  },
  {
    "message": "サイズ的に妻と相性が良いのか。"
  },
  {
    "message": "あつらえたように全て埋まってました。"
  },
  {
    "name": "夫",
    "message": "っ…。"
  },
  {
    "message": "悔しかったです。"
  },
  {
    "message": "僕以上にお似合いの夫婦みたいで。"
  },
  {
    "message": "布施　咲美。"
  },
  {
    "message": "イヤでもこの姓名が頭に浮かび。"
  },
  {
    "message": "僕の名字より神々しく思えてなりません。"
  },
  {
    "name": "布施",
    "message": "…カワイイ声だね。"
  },
  {
    "name": "咲美",
    "message": "ぃ…ゃ…。"
  },
  {
    "name": "布施",
    "message": "こんなカワイイ声を出すんだ。"
  },
  {
    "message": "布施は腰をしゃくり。"
  },
  {
    "message": "埋没させる角度を微妙に変えてきます。"
  },
  {
    "message": "今までよりもやや上から。"
  },
  {
    "message": "たぶん妻のクリトリスをターゲットとし。"
  },
  {
    "message": "ゴツゴツした表面で擦りまくるつもりでしょう。"
  },
  {
    "name": "布施",
    "message": "どっちが大きい？"
  },
  {
    "message": "ぐちゅっ、ぐちゅっ、ぐちゅっ…。"
  },
  {
    "name": "布施",
    "message": "旦那さんと俺のペニス、どっちが大きいのかな？"
  },
  {
    "message": "咲美は何も答えず。"
  },
  {
    "message": "頑なに首を振るばかり。"
  },
  {
    "message": "布施の望みを全て聞き入れ、僕に呆れ果ててた彼女でも。"
  },
  {
    "message": "この返事だけはイヤがってくれました。"
  },
  {
    "name": "布施",
    "message": "…答えてよ、奥さぁん。"
  },
  {
    "message": "ぐちゅっ、ぐちゅっ、ぐちゅっ、ぐちゅっ…。"
  },
  {
    "name": "布施",
    "message": "旦那さんも知りたいってさ。"
  },
  {
    "name": "夫",
    "message": "ぼ、僕は…。"
  },
  {
    "name": "横山",
    "message": "…アナタは見てるだけですよ。"
  },
  {
    "name": "夫",
    "message": "ぅ…。"
  },
  {
    "name": "布施",
    "message": "言わないとこんなにしちゃうよ。"
  },
  {
    "message": "パンッ、パンッ、パンッ、パンッ。"
  },
  {
    "name": "布施",
    "message": "ほら、ほら…どう？"
  },
  {
    "message": "乳房だけじゃなく。"
  },
  {
    "message": "臀部の肉が弾むほどの勢い。"
  },
  {
    "message": "膣に溜まってた汁が行き場を失い。"
  },
  {
    "message": "飛沫となって外へ噴き出します。"
  },
  {
    "message": "その迫力に僕の目はまん丸。"
  },
  {
    "message": "布施に動物のような猛々しさを感じ。"
  },
  {
    "message": "妻が壊されそうで気が気じゃありません。"
  },
  {
    "name": "布施",
    "message": "汁を飛ばしちゃって、本当にイヤらしいなぁ。"
  },
  {
    "message": "パンッ、パンッ、パンッ、パンッ。"
  },
  {
    "name": "布施",
    "message": "ほらほらほら、どっちなのっ？"
  },
  {
    "message": "咲美は再びイヤイヤ。"
  },
  {
    "message": "だけど声のトーンは明らかに変化し。"
  },
  {
    "message": "布施の行為とリンクさせていきます。"
  },
  {
    "message": "それは女の悦びそのもので。"
  },
  {
    "message": "太いペニスで妻が何を与えられてるのか。"
  },
  {
    "message": "もはや否定のしようが無くなってきました。"
  },
  {
    "message": "壊されそう？"
  },
  {
    "message": "そう思った僕が馬鹿です。"
  },
  {
    "message": "彼女はしっかり布施を受け止め。"
  },
  {
    "message": "一つになってセックスをしてるんですから。"
  },
  {
    "message": "この嬌声を聞いて下さい。"
  },
  {
    "message": "こんなに悦んでる妻を僕は知りません。"
  },
  {
    "message": "悩ましげに瞳を濡らし。"
  },
  {
    "message": "艶っぽく頬を上気させながら。"
  },
  {
    "message": "妻は気持ち良くなってしまってるんです。"
  },
  {
    "name": "布施",
    "message": "言わないの？"
  },
  {
    "message": "パンッ、パンッ、パンッ、パンッ。"
  },
  {
    "name": "布施",
    "message": "言うの、言うの？"
  },
  {
    "message": "パンッ、パンッ、パンッ、パンッ。"
  },
  {
    "name": "布施",
    "message": "やっぱり言わない？"
  },
  {
    "message": "パンッ、パンッ、パンッ、パンッ。"
  },
  {
    "name": "布施",
    "message": "くうっ…。"
  },
  {
    "message": "布施は尻にエクボを作り。"
  },
  {
    "message": "明らかに射精を我慢してます。"
  },
  {
    "message": "二人の鬩ぎ合に僕は圧倒され。"
  },
  {
    "message": "自分のしてた行為が子供染み過ぎて。"
  },
  {
    "message": "彼女をロクに悦ばせなかった自分を恥じ。"
  },
  {
    "message": "骨が折れそうなくらい、拳を握り締めてました。"
  },
  {
    "name": "夫",
    "message": "っ…。"
  },
  {
    "message": "もっと頑張れば良かった。"
  },
  {
    "message": "妻を悦ばせる努力をすべきだった。"
  },
  {
    "message": "今の布施みたいに。"
  },
  {
    "message": "腰をガンガンに動かし。"
  },
  {
    "message": "たわわな乳房をグチャグチャに揉みながら。"
  },
  {
    "message": "咲美の内側を存分に蹂躙する。"
  },
  {
    "message": "彼女のクリだってビンビンに勃ち。"
  },
  {
    "message": "ちゃんとその行為に応えてくれる。"
  },
  {
    "message": "セックスは身勝手にするものじゃなく。"
  },
  {
    "message": "いかに相手を悦ばせられるかなんだ。"
  },
  {
    "message": "そんな大切な事を。"
  },
  {
    "message": "僕は妻を踏み台にして。"
  },
  {
    "message": "なおかつ隣人の布施から教えられ。"
  },
  {
    "message": "彼女の喘ぎを聞きながら。"
  },
  {
    "message": "まるで真理を見つけたような顔。"
  },
  {
    "message": "今の僕は世界で一番、醜く。"
  },
  {
    "message": "ダメなクソ野郎に成り下がってる。"
  },
  {
    "message": "伴侶である咲美に指一本触れられず。"
  },
  {
    "message": "他人のチンポを許してる男なのに。"
  },
  {
    "name": "布施",
    "message": "ど、どうよ。"
  },
  {
    "message": "パンッ、パンッ、パンッ、パンッ。"
  },
  {
    "name": "布施",
    "message": "どうなのよっ。"
  },
  {
    "message": "パンッ、パンッ、パンッ、パンッ。"
  },
  {
    "name": "布施",
    "message": "お、奥さんっ。"
  },
  {
    "name": "咲美",
    "message": "っ、布施…さん…の…。"
  },
  {
    "name": "布施",
    "message": "な、なに？"
  },
  {
    "message": "パンッ、パンッ、パンッ、パンッ。"
  },
  {
    "name": "布施",
    "message": "ハッキリ言って。"
  },
  {
    "name": "咲美",
    "message": "っ、布施さんの…ほうが…ほうが…。"
  },
  {
    "name": "布施",
    "message": "ほうがぁ？"
  },
  {
    "name": "咲美",
    "message": "お…お…き…い…っ。"
  },
  {
    "message": "ずびゅゅゅうっ！！"
  },
  {
    "message": "咲美の言葉に感極まり。"
  },
  {
    "message": "布施は膣の中で果てました。"
  },
  {
    "message": "咲美は射精に対する嫌悪からか。"
  },
  {
    "message": "身体をギュッと硬直させてます。"
  },
  {
    "message": "妊娠に対する潜在的な恐怖。"
  },
  {
    "message": "いくら避妊してもリスクはあり。"
  },
  {
    "message": "相手が夫でなければ当然の反応です。"
  },
  {
    "name": "布施",
    "message": "ああっ、最高…最高だよ…奥さんっ…。"
  },
  {
    "message": "腰をしゃくり。"
  },
  {
    "message": "余韻を楽しみながら最後の出し入れ。"
  },
  {
    "message": "布施は敏感になってる亀頭を労りながら。"
  },
  {
    "message": "最後の一滴まで搾り出そうとしてました。"
  },
  {
    "message": "僕は付け根のコンドームを確認し。"
  },
  {
    "message": "きちんと存在してる事にまず安堵。"
  },
  {
    "message": "これで直に膣と精液が触れ合う事はなく。"
  },
  {
    "message": "ギリギリ妻の操を守れた気が…。"
  },
  {
    "name": "咲美",
    "message": "ま、まだ…ってる…ぅ。"
  },
  {
    "name": "夫",
    "message": "…。"
  },
  {
    "name": "夫",
    "message": "…え？"
  },
  {
    "message": "イッてる？"
  },
  {
    "message": "はっきり聞き取れなかったけど。"
  },
  {
    "message": "僕の耳はそう捉えてました。"
  },
  {
    "name": "夫",
    "message": "っ…。"
  },
  {
    "message": "愚鈍すぎる僕。"
  },
  {
    "message": "譫言みたいな妻の言葉を聞き。"
  },
  {
    "message": "仰け反りの意味をようやく理解。"
  },
  {
    "message": "精液への嫌悪？"
  },
  {
    "message": "妊娠への恐怖？"
  },
  {
    "message": "そう思った己を嘲笑い。"
  },
  {
    "message": "未だ妻に甘えてる自分を恥じてます。"
  },
  {
    "message": "僕の存在なんか１ミリも関係ない。"
  },
  {
    "message": "彼女は布施とセックスをし。"
  },
  {
    "message": "単純にイッたのです。"
  },
  {
    "message": "まるで仲睦まじい夫婦みたいに。"
  },
  {
    "message": "布施の射精と時を同じにして。"
  },
  {
    "message": "ただの隣人であるこの男と。"
  },
  {
    "message": "一緒に果ててしまったのです。"
  },
  {
    "message": "咲美の身体は今も強張り。"
  },
  {
    "message": "下腹もヒクヒク波打ってます。"
  },
  {
    "message": "口から直接的な言葉はなくても。"
  },
  {
    "message": "オルガスムを得た事は、疑いようもありません。"
  },
  {
    "message": "でも改めて尋ねてしまいます。"
  },
  {
    "message": "僕はもの凄い馬鹿で。"
  },
  {
    "message": "自分が落ち込む事ほど、無理に訊きたがるから。"
  },
  {
    "name": "夫",
    "message": "…イッた…の？"
  },
  {
    "name": "咲美",
    "message": "ぅ…。"
  },
  {
    "name": "夫",
    "message": "っ…教えてよ…ね？"
  },
  {
    "message": "ニタニタと笑う布施。"
  },
  {
    "message": "相変わらず無表情な横山。"
  },
  {
    "message": "返事をしない妻を前に。"
  },
  {
    "message": "僕の身体はどんどん小さくなっていきます。"
  },
  {
    "message": "まるで豆粒みたいに。"
  },
  {
    "message": "どんどんどんどん小さく。"
  },
  {
    "message": "摘めるぐらいの大きさまで。"
  },
  {
    "message": "誰からも見られなくなる大きさまで…。"
  },
  {
    "message": "その後も契約は履行され。"
  },
  {
    "message": "布施は妻の身体を貪り続けました。"
  },
  {
    "message": "騎乗位で一回。"
  },
  {
    "message": "後ろから一回。"
  },
  {
    "message": "僅かな休憩を挟みながら、計３回の性行為を済まし。"
  },
  {
    "message": "ようやくそこで手綱を緩めてくれます。"
  },
  {
    "message": "宴が終わったのは午前５時頃。"
  },
  {
    "message": "空はもう明るくなっていて。"
  },
  {
    "message": "気が付けば僕は咲美と二人きりに。"
  },
  {
    "name": "咲美",
    "message": "…。"
  },
  {
    "message": "全てが終わった安堵からなのか。"
  },
  {
    "message": "或いは身も心も疲れ果てての事なのか。"
  },
  {
    "message": "咲美は少女のような寝顔で。"
  },
  {
    "message": "スウスウと寝息を立ててました。"
  },
  {
    "name": "夫",
    "message": "…。"
  },
  {
    "message": "これで契約は終了です。"
  },
  {
    "message": "恥を世間に晒す事も無く。"
  },
  {
    "message": "僕が最も憂慮してた事は避けられました。"
  },
  {
    "message": "こちらが不利になる書面は全て廃棄。"
  },
  {
    "message": "それらは目の前でシュレッダー行きとなり。"
  },
  {
    "message": "今は横山の書いた一筆だけが残ってます。"
  },
  {
    "message": "だから安心していいはず。"
  },
  {
    "message": "ヤツとの関わりが終わったのは事実で。"
  },
  {
    "message": "許されざる僕にも一時の安息が訪れ…。"
  },
  {
    "name": "夫",
    "message": "…。"
  },
  {
    "message": "ません。"
  },
  {
    "message": "あるのは妙な胸騒ぎだけ。"
  },
  {
    "message": "心のどこかで何かが納得できず。"
  },
  {
    "message": "胸の内がモヤモヤしまくってます。"
  },
  {
    "message": "妻にどうやって謝るか。"
  },
  {
    "message": "どうやって許しを請えばいいのか。"
  },
  {
    "message": "夫婦の問題は山積みで。"
  },
  {
    "message": "考えると暗澹たる気持ちになります。"
  },
  {
    "message": "でも違うんです。"
  },
  {
    "message": "それ以外の何かなんです。"
  },
  {
    "message": "もっと手前にある。"
  },
  {
    "message": "目立たないよう隠れてる何か。"
  },
  {
    "name": "夫",
    "message": "ぁ…。"
  },
  {
    "message": "僕はハッと顔を上げ。"
  },
  {
    "message": "今さらある事に気づきました。"
  },
  {
    "message": "僕だけじゃなく。"
  },
  {
    "message": "僕以外にも空気みたいにしてたヤツ。"
  },
  {
    "message": "本来なら主導権を握れるのに。"
  },
  {
    "message": "何故か傍観者に徹してた男。"
  },
  {
    "message": "横山だって布施と同様。"
  },
  {
    "message": "妻の身体に興味はあったはず。"
  },
  {
    "message": "なのに良いところばかり布施に許し。"
  },
  {
    "message": "自分はただのカメラマン役。"
  },
  {
    "message": "ほとんど咲美に触れる事もなく。"
  },
  {
    "message": "損な立場で満足してる意味がわかりません。"
  },
  {
    "name": "夫",
    "message": "…。"
  },
  {
    "message": "もしかしてＥＤ？"
  },
  {
    "message": "それなら逆に試すでしょう。"
  },
  {
    "message": "一度ぐらいはパンツを下ろし。"
  },
  {
    "message": "勃起目的で妻の口に含ませます。"
  },
  {
    "message": "でなければ単に臆した？"
  },
  {
    "message": "マズい事になった時を考え。"
  },
  {
    "message": "布施を首謀者に仕立て上げた？"
  },
  {
    "message": "でもそんな小細工に何の意味が？"
  },
  {
    "message": "本当にビビッたなら途中下車し。"
  },
  {
    "message": "何もなかった事として収拾を図るはず。"
  },
  {
    "message": "それこそヤツらしく文書を交わし。"
  },
  {
    "message": "抜け道が全くないほど徹底的に。"
  },
  {
    "message": "ちっとも考えが纏まらず。"
  },
  {
    "message": "それでいて湯水のように湧いてきて。"
  },
  {
    "message": "気が付いたら僕は立ち上がり。"
  },
  {
    "message": "隣接する横山の部屋へ向かってました。"
  },
  {
    "name": "夫",
    "message": "…。"
  },
  {
    "message": "そこからの事は記憶が曖昧です。"
  },
  {
    "message": "横山はいました。"
  },
  {
    "message": "奥さんは留守で一人きり。"
  },
  {
    "message": "寝ようとしてたのかパジャマ姿で。"
  },
  {
    "message": "それからヤツと何か喋り。"
  },
  {
    "message": "かなり揉めた事は覚えてます。"
  },
  {
    "message": "たぶん僕が問い詰めたのでしょう。"
  },
  {
    "message": "自分が疑問に思った事を。"
  },
  {
    "message": "それこそオブラートにも包まず。"
  },
  {
    "message": "怒りにまかせ居丈高な態度で。"
  },
  {
    "message": "ここから先の記憶がスッポリ抜けてます。"
  },
  {
    "message": "我に返った時は部屋が滅茶苦茶で。"
  },
  {
    "message": "僕はキッチンの床に座り込んでました。"
  },
  {
    "message": "目の前には薄型のノートパソコン。"
  },
  {
    "message": "もちろんそれは横山の所有物で。"
  },
  {
    "message": "電源は入った状態になってました。"
  },
  {
    "message": "画面には動画のソフトが表示され。"
  },
  {
    "message": "再生し終わった状態で待機です。"
  },
  {
    "message": "たぶん僕は一回、何か、見たのでしょう。"
  },
  {
    "message": "それで放心状態に陥り。"
  },
  {
    "message": "暫し時の過ぎる事すら忘れてました。"
  },
  {
    "message": "その時に僕が見た映像。"
  },
  {
    "message": "それがこれです。"
  },
  {
    "message": "最初は画面が真っ暗で。"
  },
  {
    "message": "音声だけが聞こえてきます。"
  },
  {
    "message": "後からヤツ自身が鑑賞する時の事を考え。"
  },
  {
    "message": "順序立てて記録を残すように…。"
  },
  {
    "message": "…。"
  },
  {
    "name": "咲美",
    "message": "ぅ…。"
  },
  {
    "name": "ケーキ屋の店員",
    "message": "大丈夫ですか？"
  },
  {
    "name": "横山",
    "message": "平気、平気。"
  },
  {
    "name": "ケーキ屋の店員",
    "message": "…救急車を呼びましょうか？"
  },
  {
    "name": "横山",
    "message": "すぐ近くだから連れて帰るよ。忙しいのに迷惑かけてゴメン。"
  },
  {
    "message": "バタン。"
  },
  {
    "name": "タクシーの運ちゃん",
    "message": "おツレのかた、辛そうですね。"
  },
  {
    "name": "横山",
    "message": "急に具合が悪くなっちゃって。"
  },
  {
    "name": "タクシーの運ちゃん",
    "message": "女性だから貧血ですかねぇ。"
  },
  {
    "name": "横山",
    "message": "そんな感じかな。"
  },
  {
    "name": "タクシーの運ちゃん",
    "message": "下りる時に手伝いましょうか？"
  },
  {
    "name": "横山",
    "message": "エレベーターもあるし大丈夫。"
  },
  {
    "name": "タクシーの運ちゃん",
    "message": "今日は道も空いてますし、あと少しで着きますから。"
  },
  {
    "name": "横山",
    "message": "ワンメーターで悪いね。"
  },
  {
    "name": "タクシーの運ちゃん",
    "message": "乗って貰えただけ有り難いですよ。"
  },
  {
    "name": "横山",
    "message": "そこの角で止めてもらえる？"
  },
  {
    "name": "タクシーの運ちゃん",
    "message": "わかりました。"
  },
  {
    "message": "ぶうぅぅぅ…。"
  },
  {
    "name": "咲美",
    "message": "…。"
  },
  {
    "name": "横山",
    "message": "…けっこう重いねぇ。"
  },
  {
    "name": "咲美",
    "message": "…。"
  },
  {
    "name": "横山",
    "message": "…ホールに人影はなし、と。"
  },
  {
    "message": "チンッ。"
  },
  {
    "name": "横山",
    "message": "おウチに帰ろうね。"
  },
  {
    "name": "咲美",
    "message": "…。"
  },
  {
    "name": "横山",
    "message": "何か言ってよ。"
  },
  {
    "name": "咲美",
    "message": "…。"
  },
  {
    "name": "横山",
    "message": "完全に意識が飛んじゃった？"
  },
  {
    "name": "咲美",
    "message": "…。"
  },
  {
    "name": "横山",
    "message": "もう何をされてもわからないか。"
  },
  {
    "message": "ゴソゴソと布が擦れる音。"
  },
  {
    "message": "たぶん横山は肩を貸したまま。"
  },
  {
    "message": "咲美の乳房を弄んでるのでしょう。"
  },
  {
    "message": "ここで音声は途切れ。"
  },
  {
    "message": "室内の光景に映像が変わります。"
  },
  {
    "message": "それは僕と咲美が暮らすあの部屋ではなく。"
  },
  {
    "message": "それでいて僕からしたら目と鼻の先にある。"
  },
  {
    "message": "卑劣極まりないアイツの部屋です。"
  },
  {
    "name": "横山",
    "message": "…。"
  },
  {
    "message": "全裸にされた妻。"
  },
  {
    "message": "大の字とまでいかなくても。"
  },
  {
    "message": "僕にとっては十分衝撃的でした。"
  },
  {
    "message": "横山の個人的な思惑。"
  },
  {
    "message": "明らかにそれが感じられる格好でしたから。"
  },
  {
    "message": "広さからして場所はリビング。"
  },
  {
    "message": "テーブルなど邪魔な物はどかし。"
  },
  {
    "message": "フレーム内に余計な物が入らないよう、細心の注意を払ってる感じがします。"
  },
  {
    "message": "ムービーカメラを三脚に固定し。"
  },
  {
    "message": "横山は妻の周りをぐるぐる闊歩。"
  },
  {
    "message": "あらゆる角度から裸体を観察し。"
  },
  {
    "message": "気に入ったアングルからの写真撮影です。"
  },
  {
    "message": "カシャ。"
  },
  {
    "message": "まずは全身。"
  },
  {
    "message": "続けて顔のアップ。"
  },
  {
    "message": "それから乳房を片方ずつ撮り。"
  },
  {
    "message": "そこでわざわざレンズを交換します。"
  },
  {
    "message": "たぶん接写用でしょう。"
  },
  {
    "message": "自慢の一眼レフを膨らみに近づけ。"
  },
  {
    "message": "乳首の部分だけ何枚も撮影してました。"
  },
  {
    "message": "カシャ。"
  },
  {
    "message": "日頃のダンディさは形を潜め。"
  },
  {
    "message": "その顔はただのエロオヤジです。"
  },
  {
    "message": "その後は両足の間にしゃがみ込み。"
  },
  {
    "message": "じいっと妻の性器を眺めてます。"
  },
  {
    "name": "横山",
    "message": "…。"
  },
  {
    "message": "カシャ。"
  },
  {
    "message": "おもむろに一枚。"
  },
  {
    "message": "さほどレンズはくっつけず。"
  },
  {
    "message": "取り敢えず咲美の大切な部分を撮影。"
  },
  {
    "message": "それから指を伸ばし。"
  },
  {
    "message": "妻の淫唇をヌチャッと拡げました。"
  },
  {
    "message": "露わになる桜肉。"
  },
  {
    "message": "思い込みじゃなく、そこは濡れており。"
  },
  {
    "message": "ここに至るまで何をされたのか。"
  },
  {
    "message": "僕は唇を噛まずにはいられません。"
  },
  {
    "message": "カシャ。"
  },
  {
    "message": "性器を拡げたまま一枚。"
  },
  {
    "message": "さらに大きく拡げてもう一枚。"
  },
  {
    "message": "レンズをぐっと近づけ一枚。"
  },
  {
    "message": "クリトリスだけ大接写でもう一枚。"
  },
  {
    "name": "横山",
    "message": "ふふ…。"
  },
  {
    "message": "思った以上の手応えがあったのか。"
  },
  {
    "message": "満足そうな含み笑いが聞こえ。"
  },
  {
    "message": "背面のディスプレイを、瞬きもせず凝視してます。"
  },
  {
    "message": "それから思い出したように立ち上がり。"
  },
  {
    "message": "再び乳房の撮影を始めました。"
  },
  {
    "message": "今度は入念に先端を弄り。"
  },
  {
    "message": "乳首を勃起状態にするつもりです。"
  },
  {
    "message": "しかし途中で欲情したのか。"
  },
  {
    "message": "横山はいきなりその部分を口に。"
  },
  {
    "name": "横山",
    "message": "ふむっ…んっ…。"
  },
  {
    "message": "妻は起きません。"
  },
  {
    "message": "全く反応は無しです。"
  },
  {
    "message": "明らかに貧血とかじゃなく。"
  },
  {
    "message": "もっと深く意識を飛ばされてます。"
  },
  {
    "name": "横山",
    "message": "んふっ…ぺちゅ…くちゅ…。"
  },
  {
    "message": "ペチャペチャと音が聞こえ。"
  },
  {
    "message": "ヒルのような唇が妻の乳首へ吸い付きました。"
  },
  {
    "message": "一眼レフは床に転がり。"
  },
  {
    "message": "画面の中は横山の本性一色です。"
  },
  {
    "message": "他人に見せる予定のない映像。"
  },
  {
    "message": "だからこそ好き勝手に振る舞い。"
  },
  {
    "message": "自分をさらけ出す事ができます。"
  },
  {
    "message": "相手をしてる妻には意識はなく。"
  },
  {
    "message": "ヤツがしてる事はヤツしか知り得ません。"
  },
  {
    "message": "もちろん横山はこれを僕に提出せず。"
  },
  {
    "message": "個人の趣味として秘匿するわけですから。"
  },
  {
    "message": "完全な裏切り。"
  },
  {
    "message": "完全な契約違反。"
  },
  {
    "message": "妻を布施へ与える前に、存分に自分で味わい。"
  },
  {
    "message": "ホクロの位置一つ逃さず、記録するつもりなのです。"
  },
  {
    "name": "横山",
    "message": "はむっ…はむっ…はむっ…。"
  },
  {
    "message": "横山はしゃぶりつきながら脱衣。"
  },
  {
    "message": "よほどこうする事が夢だったのか。"
  },
  {
    "message": "片時も乳房から手を放しません。"
  },
  {
    "message": "それでも器用に全裸となり。"
  },
  {
    "message": "勃起したペニスが画面に映りました。"
  },
  {
    "message": "それは僕よりだいぶ大きく。"
  },
  {
    "message": "中年と思えないほど天を向いてます。"
  },
  {
    "message": "これでＥＤの可能性は無しです。"
  },
  {
    "message": "コイツは咲美と交われます。"
  },
  {
    "message": "この僕よりもずっと大きいペニスを。"
  },
  {
    "message": "ヤツは妻の中に入れる事ができるんです。"
  },
  {
    "message": "その事実に顔は強張り。"
  },
  {
    "message": "身体中からイヤな汗が出てきました。"
  },
  {
    "message": "次は何をするのか。"
  },
  {
    "message": "やはり最後はセックスが目的なのか。"
  },
  {
    "message": "横山の一挙手一投足にビクビクし。"
  },
  {
    "message": "ますます僕は画面から目が離せません。"
  },
  {
    "name": "横山",
    "message": "んふぅ…。"
  },
  {
    "message": "どれくらい吸い続けてたでしょうか。"
  },
  {
    "message": "ヤツはようやく乳房から口を離し。"
  },
  {
    "message": "そのまま上へ上へと舐め上げていきます。"
  },
  {
    "message": "胸元から首筋へ。"
  },
  {
    "message": "首筋から妻の唇へ。"
  },
  {
    "name": "横山",
    "message": "奥さん…好きだ…。"
  },
  {
    "message": "ぶちゅううぅ。"
  },
  {
    "name": "夫",
    "message": "あぁ…。"
  },
  {
    "message": "思わず声が出てしまいました。"
  },
  {
    "message": "横山と妻が口づけ。"
  },
  {
    "message": "一方的とはいえ。"
  },
  {
    "message": "唾液の音が聞こえるほど濃厚に。"
  },
  {
    "message": "ヤツは息継ぎを忘れるほど夢中になり。"
  },
  {
    "message": "貪る感じで彼女の唇を吸い続けてます。"
  },
  {
    "message": "そして時々顔を離し。"
  },
  {
    "message": "自分が誰とキスしてるか確認するのです。"
  },
  {
    "message": "横山の行為はそれだけで終わりません。"
  },
  {
    "message": "妻の口を強制的に開き。"
  },
  {
    "message": "上から自分の唾液を流し込みます。"
  },
  {
    "message": "意識のない彼女はそれを受け容れるしかなく。"
  },
  {
    "message": "ゴクリと飲み込むしかありません。"
  },
  {
    "message": "僕の妻が。"
  },
  {
    "message": "アイツの唾液を身体の中へ。"
  },
  {
    "name": "夫",
    "message": "ぅ…。"
  },
  {
    "message": "汚された感が半端なく。"
  },
  {
    "message": "自分の腿を拳で叩き続けてました。"
  },
  {
    "message": "でも横山はやめてくれません。"
  },
  {
    "message": "唾液を流し込み。"
  },
  {
    "message": "再びディープキスへ戻りながら。"
  },
  {
    "message": "同時に咲美の腕を股間へ導き。"
  },
  {
    "message": "自分のペニスをニギニギさせてます。"
  },
  {
    "message": "もちろんちゃんとは握れず。"
  },
  {
    "message": "彼女の掌へ擦り付けてるような感じです。"
  },
  {
    "name": "横山",
    "message": "…。"
  },
  {
    "message": "やがてそれにも飽きたのか。"
  },
  {
    "message": "ヤツは肩口の傍らで膝立ちになりました。"
  },
  {
    "message": "キスしてた唇を指先でなぞり。"
  },
  {
    "message": "スペースを確保するように、ぐいっと中へ差し込みます。"
  },
  {
    "name": "横山",
    "message": "…奥さん。"
  },
  {
    "message": "大きく口を拡げられた咲美。"
  },
  {
    "message": "ヤツが何をする為にそうしたのか。"
  },
  {
    "message": "それは説明するまでもないでしょう。"
  },
  {
    "message": "垂れる我慢汁を頬に塗りたくり。"
  },
  {
    "message": "横山は腔内にペニスを突っ込みました。"
  },
  {
    "message": "さすがに真っ直ぐには入らず。"
  },
  {
    "message": "頬をピンポン球みたいに膨らませます。"
  },
  {
    "name": "横山",
    "message": "い、いつも見てたよ。"
  },
  {
    "message": "ぬちゅっ…ぬちゅっ…。"
  },
  {
    "name": "横山",
    "message": "奥さんが出勤する時とか、ゴミを捨ててる時とかぁ。"
  },
  {
    "message": "ぬちゅっ…ぬちゅっ…ぬちゅっ…。"
  },
  {
    "name": "横山",
    "message": "っ、洗濯してる時とかも素敵だったね。"
  },
  {
    "message": "ぬちゅっ…ぬちゅっ…ぬちゅっ…ぬちゅっ…。"
  },
  {
    "name": "横山",
    "message": "抱きてぇなぁって、ずっと思ってたよ。"
  },
  {
    "message": "自分の言葉に。"
  },
  {
    "message": "そして自分でしてる事に感極まり。"
  },
  {
    "message": "横山の身体がビクンッと波打ち。"
  },
  {
    "message": "ノドボトケがグリッと動きました。"
  },
  {
    "name": "横山",
    "message": "お、奥さん。"
  },
  {
    "message": "顔は上気し。"
  },
  {
    "message": "目が異様にギラついてます。"
  },
  {
    "message": "息はハアハアと荒くなって。"
  },
  {
    "message": "なおさら横山の本性を濃くした感じです。"
  },
  {
    "message": "そして呆気なく。"
  },
  {
    "message": "本当に呆気なく。"
  },
  {
    "message": "その時は訪れてしまいました。"
  },
  {
    "message": "ヤツは妻の両足を抱え上げ。"
  },
  {
    "message": "ペニスに手の介添えも無しで。"
  },
  {
    "message": "そのままズブズブと腰を落としていったんです。"
  },
  {
    "name": "夫",
    "message": "だ、だめだっ。"
  },
  {
    "message": "再び声を上げてしまう僕。"
  },
  {
    "message": "それも今までで一番大きく。"
  },
  {
    "message": "悲鳴に近い感じで。"
  },
  {
    "name": "夫",
    "message": "約束が違うっ。"
  },
  {
    "message": "顔が強張りました。"
  },
  {
    "message": "僕が絶対に譲らなかった事。"
  },
  {
    "message": "念を押してダメだと言った事。"
  },
  {
    "message": "覚え書きにも明記してあるのに。"
  },
  {
    "message": "それをいとも簡単に破ってたから。"
  },
  {
    "message": "ヤツは避妊具をつけず。"
  },
  {
    "message": "ナマでペニスを挿入してます。"
  },
  {
    "message": "何度も目を凝らしましたが。"
  },
  {
    "message": "明らかにヤツのは未装着です。"
  },
  {
    "message": "ぬちゃっ、ぬちゅっ…。"
  },
  {
    "name": "夫",
    "message": "ああ…ぁ…。"
  },
  {
    "message": "そんな事はお構い無しで。"
  },
  {
    "message": "横山は腰を動かし始めました。"
  },
  {
    "message": "ヤツの体温。"
  },
  {
    "message": "肉胴の細かな凹凸。"
  },
  {
    "message": "浮き出た血管。"
  },
  {
    "message": "それを隔ててる物はありません。"
  },
  {
    "message": "性器と性器を直に擦れ合わせ。"
  },
  {
    "message": "横山は妻を蹂躙してるのです。"
  },
  {
    "message": "目に涙が滲み。"
  },
  {
    "message": "画面が少しボケました。"
  },
  {
    "message": "だけど停止ボタンは押せず。"
  },
  {
    "message": "最後まで見届けようとしてる自分がいます。"
  },
  {
    "message": "ぬちゅっ…ぬちゅっ…ぬちゅっ…。"
  },
  {
    "name": "横山",
    "message": "はあっ…はあっ…。"
  },
  {
    "message": "ぬちゅっ…ぬちゅっ…ぬちゅっ…ぬちゅっ…。"
  },
  {
    "name": "横山",
    "message": "はあっ…はあっ…はあっ…。"
  },
  {
    "name": "夫",
    "message": "…。"
  },
  {
    "message": "それはモクモクとした行為で。"
  },
  {
    "message": "まるで記録映画を観てるようでした。"
  },
  {
    "message": "ちょっと不気味で。"
  },
  {
    "message": "なのにどこか生々しく。"
  },
  {
    "message": "まるで催眠術でもかけられたように。"
  },
  {
    "message": "僕はじっと見入ってしまいます。"
  },
  {
    "message": "僅かに聞こえるのは横山の吐息。"
  },
  {
    "message": "そして粘膜の音。"
  },
  {
    "message": "ペニスに避妊具をつけてない。"
  },
  {
    "message": "ナマで性器が擦れ合う音です。"
  },
  {
    "message": "横山は楔を打つように腰を上下させ。"
  },
  {
    "message": "咲美のたわわな臀部を震わせてました。"
  },
  {
    "message": "映像が真横からのせいか。"
  },
  {
    "message": "ペニスの出入りする様が事細かく映され。"
  },
  {
    "message": "ヌラヌラとテカる肉胴はもちろん。"
  },
  {
    "message": "柔肉の凹み具合までハッキリ見えてます。"
  },
  {
    "name": "咲美",
    "message": "…。"
  },
  {
    "message": "相変わらず妻は無反応で。"
  },
  {
    "message": "喘ぎ声一つ上げません。"
  },
  {
    "message": "だけど横山の腰がズンと下りる時。"
  },
  {
    "message": "僅かながら眉間に皺を深く刻み。"
  },
  {
    "message": "指先もピクッと動きます。"
  },
  {
    "message": "不憫でした。"
  },
  {
    "message": "道具のように扱われてる妻が。"
  },
  {
    "message": "でも横山にとってはそれが至福で。"
  },
  {
    "message": "僕の知り得ない性癖なのかも。"
  },
  {
    "message": "ぬちゅっ、ぬちゅっ、ぬちゅっ…。"
  },
  {
    "name": "横山",
    "message": "はあっ、はあっ…。"
  },
  {
    "message": "ぬちゅっ、ぬちゅっ、ぬちゅっ、ぬちゅっ…。"
  },
  {
    "name": "横山",
    "message": "はあっ、はあっ、はあっ…。"
  },
  {
    "message": "横山は見惚れるような表情で。"
  },
  {
    "message": "じっと咲美の顔を見つめ続けてます。"
  },
  {
    "message": "たぶん彼女に対する感情だけは偽りが無く。"
  },
  {
    "message": "本気の恋心を抱いてるのでしょう。"
  },
  {
    "message": "図々しいヤツですよね。"
  },
  {
    "message": "他人の妻なのに。"
  },
  {
    "message": "もちろん僕だって気づいてました。"
  },
  {
    "message": "挨拶する時に見せるコイツの態度で。"
  },
  {
    "message": "だから咲美をノーブラにさせ。"
  },
  {
    "message": "予約した先生のところへ行く時。"
  },
  {
    "message": "僕はわざと時間を合わせ。"
  },
  {
    "message": "横山に妻のポッチを見せつけてやります。"
  },
  {
    "message": "あの時の目。"
  },
  {
    "message": "横山の視線。"
  },
  {
    "message": "その視線を感じた妻のモジモジ。"
  },
  {
    "message": "困ったような作り笑顔。"
  },
  {
    "message": "それを後から思い出すたび。"
  },
  {
    "message": "僕のペニスは硬くなってしまいました。"
  },
  {
    "message": "この人しかいない。"
  },
  {
    "message": "妻の事を頼むならこの人だ。"
  },
  {
    "message": "そう思い込んでしまった僕。"
  },
  {
    "message": "その結果がこれです。"
  },
  {
    "message": "彼女を愛してるのに。"
  },
  {
    "message": "咲美は運命で出会った女性なのに。"
  },
  {
    "name": "咲美",
    "message": "そこに突っ立っていられると、もの凄～く邪魔なんだけど。"
  },
  {
    "name": "雅史",
    "message": "す、すみません。"
  },
  {
    "name": "咲美",
    "message": "このヒョロヒョロは？"
  },
  {
    "name": "現場監督",
    "message": "新しいバイトの子。"
  },
  {
    "name": "雅史",
    "message": "ちょっとっ…なに、勝手に…。"
  },
  {
    "name": "咲美",
    "message": "コイツがバイトって…悪い冗談だよね？"
  },
  {
    "name": "現場監督",
    "message": "サキミ一人じゃどうにもならん。"
  },
  {
    "name": "咲美",
    "message": "そんなひょろっこいの、役になんか立つモンか。"
  },
  {
    "name": "咲美",
    "message": "バ・イ・ト、君っ。"
  },
  {
    "name": "雅史",
    "message": "は、はい。"
  },
  {
    "name": "咲美",
    "message": "仕事は慣れた？"
  },
  {
    "name": "雅史",
    "message": "っ、少しずつですけど。"
  },
  {
    "name": "咲美",
    "message": "で、独り寂しくコンビニ弁当？"
  },
  {
    "name": "雅史",
    "message": "っ、すみません。お邪魔なら、他の場所で…。"
  },
  {
    "name": "咲美",
    "message": "どーせならみんなと一緒に食べよ。そんな場所に腰掛けてないで、キミも詰め所に入りなってば。"
  },
  {
    "name": "雅史",
    "message": "で、でも…。"
  },
  {
    "name": "咲美",
    "message": "いーから、いーから、こっちにおいで。"
  },
  {
    "name": "雅史",
    "message": "…なんで誘ってくれるんですか？"
  },
  {
    "name": "咲美",
    "message": "へ？"
  },
  {
    "name": "雅史",
    "message": "…気を遣ってくれる理由が判らないです。"
  },
  {
    "name": "咲美",
    "message": "だって、仲間だろ？"
  },
  {
    "name": "雅史",
    "message": "…ナカマ？"
  },
  {
    "name": "咲美",
    "message": "一緒に仕事してる仲間。"
  },
  {
    "name": "雅史",
    "message": "…。"
  },
  {
    "name": "咲美",
    "message": "メシはみんなで一緒に喰ったほうがウマい。ウチのとーちゃんは昔からそう言ってた。"
  },
  {
    "name": "咲美",
    "message": "だから四の五の言ってないで、中に入れ。ウチは面白いヤツがいっぱいいるから、口に御飯が入ってる時は気を付けろよっ。"
  },
  {
    "name": "咲美",
    "message": "これで今日はおしまい。"
  },
  {
    "name": "雅史",
    "message": "っ、お疲れ様でした。"
  },
  {
    "name": "咲美",
    "message": "早いモンだね。"
  },
  {
    "name": "雅史",
    "message": "は？"
  },
  {
    "name": "咲美",
    "message": "綾瀬がアルバイトに来て、もう３ヶ月も経っちゃった。"
  },
  {
    "name": "雅史",
    "message": "…本当に早いです。"
  },
  {
    "name": "咲美",
    "message": "何か私に言う事は？"
  },
  {
    "name": "雅史",
    "message": "っ、チーフにはいつもお世話になってます。"
  },
  {
    "name": "咲美",
    "message": "よしよし。"
  },
  {
    "name": "雅史",
    "message": "じ、じゃあ僕はこれで…。"
  },
  {
    "name": "咲美",
    "message": "ちょっと待った。"
  },
  {
    "name": "雅史",
    "message": "は、はい。"
  },
  {
    "name": "咲美",
    "message": "師走だな。"
  },
  {
    "name": "雅史",
    "message": "で、ですね。"
  },
  {
    "name": "咲美",
    "message": "明日はクリスマスだ。"
  },
  {
    "name": "雅史",
    "message": "っ、世間一般的には。"
  },
  {
    "name": "咲美",
    "message": "予定は？"
  },
  {
    "name": "雅史",
    "message": "別に何も…。"
  },
  {
    "name": "咲美",
    "message": "ぐーぜん。"
  },
  {
    "name": "雅史",
    "message": "は？"
  },
  {
    "name": "咲美",
    "message": "実は私も予定がないんだ。"
  },
  {
    "name": "雅史",
    "message": "そ、そうなんですか？"
  },
  {
    "name": "咲美",
    "message": "どうしよっか。"
  },
  {
    "name": "雅史",
    "message": "ど、どうしましょ。"
  },
  {
    "name": "咲美",
    "message": "一人でいるとヒマかも。"
  },
  {
    "name": "雅史",
    "message": "…。"
  },
  {
    "name": "咲美",
    "message": "最近はテレビとか、ツマンナイしさぁ。"
  },
  {
    "name": "雅史",
    "message": "…。"
  },
  {
    "name": "咲美",
    "message": "なんかいいアイデア、ない？"
  },
  {
    "name": "雅史",
    "message": "あ、あ、あ、あの。"
  },
  {
    "name": "咲美",
    "message": "なに？"
  },
  {
    "name": "雅史",
    "message": "っ、もし良ければ、僕と食事でも…。"
  },
  {
    "name": "咲美",
    "message": "…。"
  },
  {
    "name": "咲美",
    "message": "…いいの？"
  },
  {
    "name": "雅史",
    "message": "は、はい。"
  },
  {
    "name": "咲美",
    "message": "またあのオデン屋に行く？"
  },
  {
    "name": "雅史",
    "message": "っ、喜んでお供します。"
  },
  {
    "name": "咲美",
    "message": "誘ったのはそっち。"
  },
  {
    "name": "雅史",
    "message": "そ、そうでした。"
  },
  {
    "name": "咲美",
    "message": "…私、おシャレしていくね。"
  },
  {
    "name": "雅史",
    "message": "え？"
  },
  {
    "name": "咲美",
    "message": "私が女だって事を、覚えて貰う為にさ。"
  },
  {
    "name": "雅史",
    "message": "…。"
  },
  {
    "name": "咲美",
    "message": "何だか明日は記念日になりそう。さっきまで普通だったのに、すっごくドキドキしてきたよ。"
  },
  {
    "message": "ぐちゅっ、ぐちゅっ、ぐちゅっ。"
  },
  {
    "name": "夫",
    "message": "っ…。"
  },
  {
    "message": "ぐちゅっ、ぐちゅっ、ぐちゅっ、ぐちゅっ。"
  },
  {
    "name": "夫",
    "message": "っ…っ…。"
  },
  {
    "message": "すまない。"
  },
  {
    "message": "すまない、咲美。"
  },
  {
    "message": "僕が馬鹿だった。"
  },
  {
    "message": "どんなに妻の事を愛してるか。"
  },
  {
    "message": "どれほど必要な女性だったのか。"
  },
  {
    "message": "一方的に自分の癖を押し付けて。"
  },
  {
    "message": "彼女を慰み者にする道を選ぶなんて。"
  },
  {
    "name": "夫",
    "message": "くぅ…っ…。"
  },
  {
    "message": "早く終わって欲しい。"
  },
  {
    "message": "とにかく早く終わってくれ。"
  },
  {
    "message": "それがどういう事なのかよく考えず。"
  },
  {
    "message": "僕は祈るように手を前で組んでました。"
  },
  {
    "message": "その願いが届いたのでしょうか。"
  },
  {
    "message": "スピーカーから、パン、パン、パン、と弾ける音がし。"
  },
  {
    "message": "横山の動きがどんどん過激に。"
  },
  {
    "message": "引き抜くペニスの幅は最大限で。"
  },
  {
    "message": "叩き付けるように腰を落とし始めます。"
  },
  {
    "message": "体位は同じでも、速さが凄いんです。"
  },
  {
    "message": "ストロークがあれだけあるのに。"
  },
  {
    "message": "肉胴がしなる事も厭わず、横山は突っ込み続けます。"
  },
  {
    "message": "実際に何度か膣からはずれ。"
  },
  {
    "message": "グニャリと曲がるのを目にしました。"
  },
  {
    "message": "でもヤツは自分の情念をぶつけるよう。"
  },
  {
    "message": "一瞬たりとも怯みません。"
  },
  {
    "message": "妻の身体に己を刻み込むよう。"
  },
  {
    "message": "妻を見る度に今の事を思い出せるよう。"
  },
  {
    "message": "彼女の都合など一切構わず。"
  },
  {
    "message": "遮二無二ペニスを叩き付ける横山。"
  },
  {
    "message": "彼女は乳房をブルブル震わせ。"
  },
  {
    "message": "その強烈な衝撃を受け取るしかありません。"
  },
  {
    "message": "パンッ、パンッ、パンッ、パンッ。"
  },
  {
    "name": "咲美",
    "message": "ぅ…ぁ…。"
  },
  {
    "message": "パンッ、パンッ、パンッ、パンッ。"
  },
  {
    "name": "咲美",
    "message": "っ…ぅ…ぁ…。"
  },
  {
    "message": "辛そうな声。"
  },
  {
    "message": "意識は閉じていても。"
  },
  {
    "message": "与えられ続ける刺激が妻を呻かせます。"
  },
  {
    "message": "身体はセックスされてる事を知っていて。"
  },
  {
    "message": "脳は何とか妻を守ろうと必死になり。"
  },
  {
    "message": "だから膣をグチュグチュに潤わせ。"
  },
  {
    "message": "横山の乱暴な行為に順応しようとするのです。"
  },
  {
    "name": "夫",
    "message": "…。"
  },
  {
    "message": "もし意識があったら。"
  },
  {
    "message": "素の状態でこんな事をされてたら。"
  },
  {
    "message": "妻はどんな声を出して。"
  },
  {
    "message": "どんな感じになっちゃってるのでしょう。"
  },
  {
    "message": "その事を想像すると背筋が寒くなり。"
  },
  {
    "message": "画面を真っ直ぐに見られなくなります。"
  },
  {
    "name": "横山",
    "message": "ぅ…。"
  },
  {
    "message": "再び呻き声。"
  },
  {
    "message": "でも今度は横山です。"
  },
  {
    "message": "ヤツは眉頭をヒクつかせ。"
  },
  {
    "message": "臀部の筋肉を硬くさせてました。"
  },
  {
    "message": "同じ男としてそれが何を意味するか。"
  },
  {
    "message": "愚鈍な僕でも理解できないわけがないです。"
  },
  {
    "message": "やっと終わってくれる。"
  },
  {
    "message": "たぶんあと数十秒。"
  },
  {
    "message": "もしかしたらもっと早く。"
  },
  {
    "message": "しかしそこで血の気が引き。"
  },
  {
    "message": "僕はパソコンを両側から掴みました。"
  },
  {
    "message": "がしっ！"
  },
  {
    "message": "顔は鬼の形相。"
  },
  {
    "message": "目は血走り。"
  },
  {
    "message": "口は般若のように歪んでます。"
  },
  {
    "message": "パンッ、パンッ、パンッ、パンッ。"
  },
  {
    "name": "横山",
    "message": "ぅ…ぅ…。"
  },
  {
    "name": "夫",
    "message": "ば、馬鹿っ、抜けっ！"
  },
  {
    "message": "パンッ、パンッ、パンッ、パンッ。"
  },
  {
    "name": "夫",
    "message": "お前はゴムをつけてないんだぞ！"
  },
  {
    "message": "パンッ、パンッ、パンッ、パンッ。"
  },
  {
    "name": "夫",
    "message": "その薄汚いチンポを抜けっ！"
  },
  {
    "message": "いくらパソコンを揺すっても。"
  },
  {
    "message": "画面の横山はこっちを振り向きません。"
  },
  {
    "name": "横山",
    "message": "っ…奥さん。"
  },
  {
    "name": "咲美",
    "message": "ぅ…。"
  },
  {
    "name": "横山",
    "message": "…奥さん…奥さん…。"
  },
  {
    "message": "パンッ、パンッ、パンッ、パンッ。"
  },
  {
    "name": "咲美",
    "message": "ぁ…ぅ…。"
  },
  {
    "name": "横山",
    "message": "一つになろうね。"
  },
  {
    "message": "パンッ、パンッ、パンッ、パンッ。"
  },
  {
    "name": "横山",
    "message": "子供ができてもできなくても…。"
  },
  {
    "message": "パンッ、パンッ、パンッ、パンッ。"
  },
  {
    "name": "横山",
    "message": "奥さんはあの馬鹿亭主と離婚して…。"
  },
  {
    "message": "パンッ、パンッ、パンッ、パンッ。"
  },
  {
    "name": "横山",
    "message": "…私と一緒になるんだ。"
  },
  {
    "name": "夫",
    "message": "こ、この…っ。"
  },
  {
    "message": "僕はパソコンを振り回し。"
  },
  {
    "message": "画面の横山をどかそうとしてます。"
  },
  {
    "message": "そんな事ができないのはわかっていても。"
  },
  {
    "message": "僕はそうせずにいられないのです。"
  },
  {
    "name": "横山",
    "message": "私なら奥さんを幸せにできる。"
  },
  {
    "message": "パンッ、パンッ、パンッ、パンッ。"
  },
  {
    "name": "横山",
    "message": "あの馬鹿亭主の何倍もね。"
  },
  {
    "message": "ますます臀部の筋肉は硬くなり。"
  },
  {
    "message": "腿の筋まで緊張が漲ってきました。"
  },
  {
    "message": "あと数秒。"
  },
  {
    "message": "数秒でコイツは射精するっ。"
  },
  {
    "name": "夫",
    "message": "やめろぉぉぉぉぉぉ！！"
  },
  {
    "name": "横山",
    "message": "く…は…。"
  },
  {
    "name": "夫",
    "message": "やめてくれぇぇぇぇぇぇ！！"
  },
  {
    "name": "横山",
    "message": "で、出る…出る…出る…ぅ。"
  },
  {
    "message": "どびゅううう！！"
  },
  {
    "message": "どびゅっ、ばびゅっ、どびゅっ、どびゅっ、どびゅっ、ばびゅっ！"
  },
  {
    "name": "夫",
    "message": "あぁ…ぁ…。"
  },
  {
    "message": "迸りました。"
  },
  {
    "message": "妻の体内に横山の精液が。"
  },
  {
    "message": "僕は女座りの格好でヘタり込み。"
  },
  {
    "message": "パソコンを床へ戻す事しかできません。"
  },
  {
    "message": "でもその直後です。"
  },
  {
    "message": "たぶん僕も横山も。"
  },
  {
    "message": "思いもしなかった事が起こるのは。"
  },
  {
    "name": "咲美",
    "message": "…。"
  },
  {
    "name": "横山",
    "message": "え？"
  },
  {
    "message": "驚いた横山。"
  },
  {
    "message": "目をパチクリさせ。"
  },
  {
    "message": "妻の顔をじっと見ます。"
  },
  {
    "name": "咲美",
    "message": "…セン…セ…。"
  },
  {
    "name": "横山",
    "message": "…。"
  },
  {
    "name": "咲美",
    "message": "セン…セ…。"
  },
  {
    "message": "腕はポトリと落ち。"
  },
  {
    "message": "元の状態に。"
  },
  {
    "message": "横山の顔は引きつり。"
  },
  {
    "message": "見た事ないくらい歪んでました。"
  },
  {
    "message": "妻に対する達成感や征服欲。"
  },
  {
    "message": "そして射精後の余韻。"
  },
  {
    "message": "その全てを消してしまう強烈な一言。"
  },
  {
    "message": "意識のない時に口から出た。"
  },
  {
    "message": "本心以外の何ものでもない言葉。"
  },
  {
    "message": "それも射精時に。"
  },
  {
    "message": "子宮がじんわり温もった時に出た言葉です。"
  },
  {
    "message": "横山はペニスを急速に縮ませ。"
  },
  {
    "message": "完全に血の気を失せさせてました。"
  },
  {
    "message": "夫である僕でも自分でもない誰か。"
  },
  {
    "message": "全てをその人物に持って行かれたのです。"
  },
  {
    "message": "咲美の顔を見て下さい。"
  },
  {
    "message": "少し微笑んでる気がしませんか？"
  },
  {
    "message": "つまり先生なら許せるんです。"
  },
  {
    "message": "妻は中で出されても。"
  },
  {
    "message": "相手が先生ならイヤと思いません。"
  },
  {
    "message": "妻はちゃんとわかってます。"
  },
  {
    "message": "誰が一番優しくて。"
  },
  {
    "message": "誰が自分を傷つけず。"
  },
  {
    "message": "どんな時も味方でいてくれるかを。"
  },
  {
    "message": "夫である僕以上の信頼関係。"
  },
  {
    "message": "それが先生との間にはあるんです。"
  },
  {
    "message": "嫉妬はしません。"
  },
  {
    "message": "僕はそれすらできる立場になく。"
  },
  {
    "message": "ただただ情けなく思うだけです。"
  },
  {
    "message": "横山の部屋を隅々まで調べ。"
  },
  {
    "message": "咲美の尊厳を冒す物は全て排除しました。"
  },
  {
    "message": "警察が来て細かく調べた時。"
  },
  {
    "message": "もう何も出て来ない事を祈るばかりです。"
  },
  {
    "message": "あとパソコンを包んでたラップ。"
  },
  {
    "message": "たぶんそれには血痕がついてます。"
  },
  {
    "message": "もし良かったら捨てちゃって下さい。"
  },
  {
    "message": "もちろん先生の判断に委ねますが。"
  },
  {
    "message": "あと番号ですね。"
  },
  {
    "message": "左が０１３、右が４２５。"
  },
  {
    "message": "咲美が先生と最初に出会った日付です。"
  },
  {
    "message": "横山の部屋にあった睡眠薬。"
  },
  {
    "message": "それを少し多目に与えました。"
  },
  {
    "message": "もちろん本人には内緒でしたが。"
  },
  {
    "message": "眠らせるにはこの方法しか思いつきません。"
  },
  {
    "message": "妻の事を宜しくお願いします。"
  },
  {
    "message": "面会とかは必要ない事も、どうか妻にお伝え下さい。"
  },
  {
    "message": "それではさようなら。"
  },
  {
    "message": "先生と妻に幸多からん事を願って。"
  },
  {
    "message": "綾瀬　雅史。"
  },
  {
    "name": "彦麻呂",
    "message": "っ…。"
  },
  {
    "message": "身体が震え。"
  },
  {
    "message": "指先がうまく動かない。"
  },
  {
    "name": "彦麻呂",
    "message": "０１３…っ。"
  },
  {
    "message": "かちゃっ。"
  },
  {
    "name": "彦麻呂",
    "message": "４２５…っ。"
  },
  {
    "message": "かちゃっ。"
  },
  {
    "name": "咲美",
    "message": "…。"
  },
  {
    "name": "彦麻呂",
    "message": "うおおぉぉぉぉぉぉぉぉ…っ。"
  },
  {
    "message": "悲鳴でも叫び声でもない。"
  },
  {
    "message": "空気が震えるような唸り声。"
  },
  {
    "message": "身体のどこからそれが出てるのか。"
  },
  {
    "message": "麻呂本人にもわからない。"
  },
  {
    "name": "咲美",
    "message": "すうすう…すうすう…。"
  },
  {
    "name": "彦麻呂",
    "message": "っ、助けられなくてゴメンでおじゃるぅ。"
  },
  {
    "name": "咲美",
    "message": "すうすう…くうくう…。"
  },
  {
    "name": "彦麻呂",
    "message": "こ、これからは麻呂が守るでおじゃるよ。奥さんの親友として、奥さんの仲間として、ずっと麻呂が側にいるでおじゃるよぉ。"
  },
  {
    "message": "麻呂は詫び。"
  },
  {
    "message": "花に埋もれる彼女を抱き締めた。"
  },
  {
    "message": "生きてる証の温もりが伝わり。"
  },
  {
    "message": "それだけで更に号泣してしまいそう。"
  },
  {
    "name": "彦麻呂",
    "message": "ず、ずっと一緒でおじゃる。"
  },
  {
    "message": "ぶちゅっ。"
  },
  {
    "name": "咲美",
    "message": "…。"
  },
  {
    "name": "彦麻呂",
    "message": "ず、ずっとずっと一緒でおじゃるよ。"
  },
  {
    "message": "ぶちゅっ。"
  },
  {
    "message": "頬に繰り返しキス。"
  },
  {
    "message": "意識は失せてるままなのに。"
  },
  {
    "message": "ほんの少し微笑んでくれた気が。"
  },
  {
    "message": "お風呂を湧かそう。"
  },
  {
    "message": "御飯の用意をしよう。"
  },
  {
    "message": "何もなかったように振る舞い。"
  },
  {
    "message": "１ミリでも多く奥さんの役に立とう。"
  },
  {
    "message": "イヤな記憶の消去はできなくても。"
  },
  {
    "message": "時間という魔法が彼女を救ってくれるはず。"
  },
  {
    "message": "麻呂はそれを手伝うでおじゃる。"
  },
  {
    "message": "命懸けで手伝うでおじゃる。"
  },
  {
    "message": "奥さんの杖となれるのは麻呂だけで。"
  },
  {
    "message": "他に一人としていないのだから…。"
  }
]